Workbook
Name Set_Year: SETTINGS!$C$7
Name Set_ChristmasDate: SETTINGS!$C$8
Name Set_SeasonStart: SETTINGS!$C$9
Name Set_Currency: SETTINGS!$C$10
Name Set_Household: SETTINGS!$C$11
Name Set_WarnThreshold: SETTINGS!$C$12
Name Set_ShipWindow: SETTINGS!$C$13
Name Set_LowStock: SETTINGS!$C$14
Name Set_WeekStart: SETTINGS!$C$15
Name Set_Edition: SETTINGS!$C$16
Name List_Currency: LISTS!$B$8:$B$12
Name List_WeekStart: LISTS!$C$8:$C$9
Name List_YesNo: LISTS!$D$8:$D$9
Name List_Group: LISTS!$E$8:$E$16
Name List_BudgetCategory: LISTS!$F$8:$F$19
Name List_GiftStatus: LISTS!$G$8:$G$13
Name List_GiftType: LISTS!$H$8:$H$10
Name List_DeliveryType: LISTS!$I$8:$I$12
Name List_Priority: LISTS!$J$8:$J$10
Name List_OrderStatus: LISTS!$K$8:$K$13
Name List_IssueType: LISTS!$L$8:$L$13
Name List_ReturnStatus: LISTS!$M$8:$M$13
Name List_CalendarType: LISTS!$N$8:$N$13
Name List_CalendarStatus: LISTS!$O$8:$O$13
Name List_VendorCategory: LISTS!$P$8:$P$17
Name List_VendorStatus: LISTS!$Q$8:$Q$14
Name List_DecorCategory: LISTS!$R$8:$R$19
Name List_Condition: LISTS!$S$8:$S$12
Name List_Room: LISTS!$T$8:$T$18
Name List_ApprovalStatus: LISTS!$U$8:$U$11
Name List_Course: LISTS!$V$8:$V$16
Name List_MealStatus: LISTS!$W$8:$W$13
Name List_DietaryTag: LISTS!$X$8:$X$17
Name List_GroceryCategory: LISTS!$Y$8:$Y$18
Name List_RecipeCategory: LISTS!$Z$8:$Z$15
Name List_GuestStatus: LISTS!$AA$8:$AA$13
Name List_Sleeping: LISTS!$AB$8:$AB$13
Name List_TraditionCategory: LISTS!$AC$8:$AC$15
Name List_MediaType: LISTS!$AD$8:$AD$14
Name List_Audience: LISTS!$AE$8:$AE$12
Name List_CardStatus: LISTS!$AF$8:$AF$13
Name List_AddressStatus: LISTS!$AG$8:$AG$11
Name List_WardrobeStatus: LISTS!$AH$8:$AH$12
Name List_TravelType: LISTS!$AI$8:$AI$15
Name List_BookingStatus: LISTS!$AJ$8:$AJ$13
Name List_Recurrence: LISTS!$AK$8:$AK$13
Name List_TaskStatus: LISTS!$AL$8:$AL$12
Name List_GivingType: LISTS!$AM$8:$AM$12
Name List_Ownership: LISTS!$AN$8:$AN$11
Name List_Rating: LISTS!$AO$8:$AO$12
Name List_NextYearTheme: LISTS!$AP$8:$AP$14
Name List_Relationship: LISTS!$AQ$8:$AQ$20
Name Vision_Theme: 'SEASON VISION'!$C$7
Name Vision_Feelings: 'SEASON VISION'!$C$8
Name Vision_Colours: 'SEASON VISION'!$C$9
Name Vision_Scent: 'SEASON VISION'!$C$10
Name Vision_Protect: 'SEASON VISION'!$C$11
Name QA_Exceptions: 'QUALITY CHECK'!$C$91

Sheet COVER
B6: A PRIVATE CHRISTMAS ATELIER
B9: The Christmas Season
B12: Master Command Center
B17: Curate every exquisite detail in one private Christmas atelier.
B20: =IF(Set_Household="","Welcome.","For the "&Set_Household&" household.")
B22: ="Christmas "&Set_Year&" · "&MAX(0,Set_ChristmasDate-TODAY())&" days to go"
B25: Begin here → START HERE
B26: Straight to the dashboard → DASHBOARD
B32: ="Edition "&Set_Edition&" · Google Sheets edition"
B33: [SELLER BRAND] · For your own household. Not for resale, redistribution or sharing.
B34: See TERMS OF USE, included with your download, for the full licence.

Sheet START HERE
B1: Dashboard | D1: Start here | F1: Calendar | H1: Budget | J1: All sheets
B2: Start here
B3: Six steps, ten minutes, and the rest of the season has somewhere to live.
B6: Setting up
B8: 1 | C8: Save a clean copy first
C9: Before you type anything, save a copy called “master”. Come next year you will want an empty one to start from.
B11: 2 | C11: Set up SETTINGS
C12: Year, Christmas date, season start, currency and household name. Everything else reads from there.
B14: 3 | C14: Add people before gifts
C15: Fill in PEOPLE + BUDGETS, then RECIPIENT PROFILES if you like keeping notes. Gift rows attach to a Person ID.
B17: 4 | C17: Choose your modules
C18: Use what suits you. TRAVEL PLAN, ADVENT + REFLECTION and MOVIES + MUSIC hide cleanly — right-click the tab and choose Hide.
B20: 5 | C20: Write the season vision
C21: Five lines on SEASON VISION, and the first few dates on CHRISTMAS CALENDAR.
B23: 6 | C23: Go to the dashboard
C24: It will tell you what is unfinished. Work down the attention board; that is the whole method.
B27: What the colours mean
C29: Cream | D29: Yours to fill in.
C30: Pale green | D30: Calculates itself. Locked so it cannot be typed over by accident.
C31: Amber | D31: Either an example row to delete, or something asking for attention.
C32: Rose | D32: Over budget, overdue or late. Read the word in the cell — the colour is never the whole story.
C34: Every colour is backed by a word. If you cannot see the fill, the cell still says OVERDUE, NEAR LIMIT or ON TRACK.
B37: Working in the workbook
B39: Filters | D39: Every tracker has them, on the header row. Filter, do not delete.
B40: Sorting | D40: Safe. IDs are typed text, not row numbers, so nothing comes unstuck when you re-order a table.
B41: Adding rows | D41: Insert a row inside the table — click a row in the middle, not the one after the last. Formulas and dropdowns come with it. Then copy a calculated cell down into the new row.
B42: Dropdown lists | D42: They live on LISTS. To add a value, insert a row inside the block rather than below it, and every dropdown that uses it widens automatically.
B43: Hiding a module | D43: Right-click the tab and choose Hide. Nothing breaks: every total reads an empty sheet as zero.
B44: Unprotecting | D44: Review, then Unprotect Sheet. There is no password. The lock is only there to stop a calculation being typed over by accident.
B45: Examples | D45: Three amber rows on each tracker, every one marked EXAMPLE — DELETE ME. Delete the contents when you are ready; deleting them breaks nothing.
B46: Printing | D46: The dashboard prints as two pages. A tracker prints its first columns — the ones worth carrying to the shops — at full size. To print the whole table instead, go to Page Layout, Print Area, Clear. Filter the sheet first either way, or you will print every empty row.
B49: Putting the year away
B51: 1. | C51: Save this year’s workbook under its own name — “Christmas 2026”, and leave it alone.
B52: 2. | C52: Open your clean master copy, or copy the figures below into ANNUAL ARCHIVE before you clear anything.
B53: 3. | C53: From MASTER BUDGET copy the Budget and Actual totals; from the dashboard, gifts given and guests hosted.
B54: 4. | C54: Delete the contents of the cream cells on each tracker. Do not delete rows, and do not touch the pale green columns.
B55: 5. | C55: Update the year on SETTINGS. The countdown, the calendar and every label follow it.
B56: 6. | C56: Read NEXT YEAR NOTES before you plan anything. That is what it was for.
B59: A note on what you keep here
B61: This is an ordinary spreadsheet on your own device. It is not encrypted, and anyone who opens the file can read it. Keep hiding places, sizes and preferences here if they help you plan. Keep card numbers, passwords and identity documents somewhere else.
B64: Set in Georgia and Aptos so it looks the same on every machine. If you own Cormorant Garamond, select the workbook and change the heading font — the layout is built to take it.

Sheet SETTINGS
B1: Dashboard | C1: Start here | D1: Calendar | E1: Budget | F1: All sheets
B2: Settings
B3: Nine decisions the whole workbook reads from. Set them once, at the start of the season.
B4: Cream cells are yours · the edition below is fixed · everything else in the workbook follows these values
B7: Christmas year | C7: 2026 | D7: The season this copy of the workbook plans. Change it once, at the start of the season.
B8: Christmas date | C8: 46381 | D8: Defaults to 25 December of the year above. Edit only if you keep Christmas on another day.
B9: Season start | C9: 46266 | D9: The date your planning calendar opens. 1 September by default.
B10: Currency symbol | C10: CAD | D10: Sets the symbol shown beside every amount.
B11: Household / planner name | D11: Used in the welcome line on the cover and dashboard. Leave blank if you prefer.
B12: Budget warning threshold | C12: 0.9 | D12: The share of a budget that turns a category amber. 90% by default.
B13: Shipping risk window (days) | C13: 7 | D13: How many days before an expected delivery an order without tracking starts asking for attention.
B14: Low-stock threshold | C14: 1 | D14: Décor quantity at or below this prompts a replacement note.
B15: Week starts | C15: Sunday | D15: Sunday or Monday, for calendar week numbers.
B16: Edition | C16: 1.0 | D16: The version of this workbook. Quote it if you contact support.
B19: What these change
B21: Christmas year | C21: The countdown, every label that names the year, and the default Christmas date.
B22: Budget warning threshold | C22: When a category turns amber instead of green. Lower it if you want warning sooner.
B23: Shipping risk window | C23: How many days out an order with no tracking starts asking to be chased.
B24: Low-stock threshold | C24: When DÉCOR INVENTORY says LOW rather than IN STOCK.
B25: Currency symbol | C25: The symbol on every amount. It does not convert anything — one workbook, one currency.

Sheet DASHBOARD
B1: Dashboard | D1: Start here | G1: Calendar | I1: Budget | K1: All sheets
B2: Dashboard
B3: =IF(Set_Household="","Christmas "&Set_Year&" — where everything stands today.","Christmas "&Set_Year&" for the "&Set_Household&" household — where everything stands today.")
B4: Every figure below is calculated. Follow a card to its sheet using the strip above, or the SHEET INDEX.
B6: DAYS TO CHRISTMAS | F6: BUDGET SET | J6: SPENT SO FAR | N6: REMAINING
B7: =MAX(0,Set_ChristmasDate-TODAY()) | F7: =SUM('MASTER BUDGET'!$E$6:$E$25) | J7: =SUM('MASTER BUDGET'!$G$6:$G$25) | N7: =SUM('MASTER BUDGET'!$E$6:$E$25)-SUM('MASTER BUDGET'!$G$6:$G$25)
B9: ="Christmas falls on "&TEXT(Set_ChristmasDate,"dddd d mmmm") | F9: The total of every category on MASTER BUDGET. | J9: ="Planned, including what you have not bought yet: "&TEXT(SUM('MASTER BUDGET'!$F$6:$F$25),"""$""#,##0.00;[Red]-""$""#,##0.00;""$""—") | N9: =IF(SUM('MASTER BUDGET'!$E$6:$E$25)=0,"No budget set yet.",IF(SUM('MASTER BUDGET'!$E$6:$E$25)-SUM('MASTER BUDGET'!$G$6:$G$25)<0,"OVER BUDGET — see MASTER BUDGET.","Against the budget you set."))
B11: GIFTS CHOSEN | F11: WRAPPED | J11: DELIVERED | N11: ON THE LIST
B12: =IF(COUNTIFS('GIFT PLANNER'!$E$6:$E$205,"Yes")=0,0,COUNTIFS('GIFT PLANNER'!$E$6:$E$205,"Yes",'GIFT PLANNER'!$T$6:$T$205,"Yes")/COUNTIFS('GIFT PLANNER'!$E$6:$E$205,"Yes")) | F12: =IF(COUNTIFS('GIFT PLANNER'!$E$6:$E$205,"Yes",'GIFT PLANNER'!$T$6:$T$205,"Yes",'GIFT PLANNER'!$Y$6:$Y$205,"Physical")=0,0,COUNTIFS('GIFT PLANNER'!$E$6:$E$205,"Yes",'GIFT PLANNER'!$T$6:$T$205,"Yes",'GIFT PLANNER'!$Y$6:$Y$205,"Physical",'GIFT PLANNER'!$Z$6:$Z$205,"Yes")/COUNTIFS('GIFT PLANNER'!$E$6:$E$205,"Yes",'GIFT PLANNER'!$T$6:$T$205,"Yes",'GIFT PLANNER'!$Y$6:$Y$205,"Physical")) | J12: =IF(COUNTIFS('ONLINE ORDERS'!$B$6:$B$155,"?*",'ONLINE ORDERS'!$K$6:$K$155,"<>Cancelled")=0,0,COUNTIFS('ONLINE ORDERS'!$B$6:$B$155,"?*",'ONLINE ORDERS'!$K$6:$K$155,"<>Cancelled",'ONLINE ORDERS'!$M$6:$M$155,"Yes")/COUNTIFS('ONLINE ORDERS'!$B$6:$B$155,"?*",'ONLINE ORDERS'!$K$6:$K$155,"<>Cancelled")) | N12: =IF(COUNTIFS('CHRISTMAS CALENDAR'!$B$6:$B$205,"?*",'CHRISTMAS CALENDAR'!$Q$6:$Q$205,"Yes")+COUNTIFS('CHRISTMAS CALENDAR'!$B$6:$B$205,"?*",'CHRISTMAS CALENDAR'!$Q$6:$Q$205,"No")=0,0,COUNTIFS('CHRISTMAS CALENDAR'!$B$6:$B$205,"?*",'CHRISTMAS CALENDAR'!$Q$6:$Q$205,"No")/(COUNTIFS('CHRISTMAS CALENDAR'!$B$6:$B$205,"?*",'CHRISTMAS CALENDAR'!$Q$6:$Q$205,"Yes")+COUNTIFS('CHRISTMAS CALENDAR'!$B$6:$B$205,"?*",'CHRISTMAS CALENDAR'!$Q$6:$Q$205,"No")))
B14: =IF(COUNTIFS('GIFT PLANNER'!$E$6:$E$205,"Yes")=0,"Not started.",COUNTIFS('GIFT PLANNER'!$E$6:$E$205,"Yes",'GIFT PLANNER'!$T$6:$T$205,"Yes")&" of "&COUNTIFS('GIFT PLANNER'!$E$6:$E$205,"Yes")&" bought") | F14: =IF(COUNTIFS('GIFT PLANNER'!$E$6:$E$205,"Yes",'GIFT PLANNER'!$T$6:$T$205,"Yes",'GIFT PLANNER'!$Y$6:$Y$205,"Physical")=0,"Nothing to wrap yet.",COUNTIFS('GIFT PLANNER'!$E$6:$E$205,"Yes",'GIFT PLANNER'!$T$6:$T$205,"Yes",'GIFT PLANNER'!$Y$6:$Y$205,"Physical",'GIFT PLANNER'!$Z$6:$Z$205,"Yes")&" of "&COUNTIFS('GIFT PLANNER'!$E$6:$E$205,"Yes",'GIFT PLANNER'!$T$6:$T$205,"Yes",'GIFT PLANNER'!$Y$6:$Y$205,"Physical")&" — digital and experience gifts are not counted") | J14: =IF(COUNTIFS('ONLINE ORDERS'!$B$6:$B$155,"?*",'ONLINE ORDERS'!$K$6:$K$155,"<>Cancelled")=0,"No orders yet.",COUNTIFS('ONLINE ORDERS'!$B$6:$B$155,"?*",'ONLINE ORDERS'!$K$6:$K$155,"<>Cancelled")-COUNTIFS('ONLINE ORDERS'!$B$6:$B$155,"?*",'ONLINE ORDERS'!$K$6:$K$155,"<>Cancelled",'ONLINE ORDERS'!$M$6:$M$155,"Yes")&" still on their way") | N14: =IF(COUNTIFS('CHRISTMAS CALENDAR'!$B$6:$B$205,"?*",'CHRISTMAS CALENDAR'!$Q$6:$Q$205,"Yes")+COUNTIFS('CHRISTMAS CALENDAR'!$B$6:$B$205,"?*",'CHRISTMAS CALENDAR'!$Q$6:$Q$205,"No")=0,"Nothing in the calendar yet.",COUNTIFS('CHRISTMAS CALENDAR'!$B$6:$B$205,"?*",'CHRISTMAS CALENDAR'!$Q$6:$Q$205,"Yes")&" still open")
B16: What needs you | J16: This season
B17: =COUNTIF('MASTER BUDGET'!$J$6:$J$25,"OVER BUDGET") | C17: categories over budget | G17: MASTER BUDGET | J17: This year is for | L17: =IF(Vision_Theme="","Write one line on SEASON VISION.",Vision_Theme)
B18: =COUNTIF('MASTER BUDGET'!$J$6:$J$25,"NEAR LIMIT") | C18: categories near their limit | G18: MASTER BUDGET | J18: It should feel | L18: =IF(Vision_Feelings="","—",Vision_Feelings)
B19: =COUNTIFS('GIFT PLANNER'!$E$6:$E$205,"Yes",'GIFT PLANNER'!$T$6:$T$205,"No") | C19: gifts still to choose or buy | G19: GIFT PLANNER | J19: First priority | L19: =IFERROR(INDEX('SEASON VISION'!$C$15:$C$38,MATCH("?*",'SEASON VISION'!$C$15:$C$38,0)),"Nothing written yet.")
B20: =COUNTIFS('GIFT PLANNER'!$E$6:$E$205,"Yes",'GIFT PLANNER'!$T$6:$T$205,"Yes",'GIFT PLANNER'!$Y$6:$Y$205,"Physical",'GIFT PLANNER'!$Z$6:$Z$205,"<>Yes") | C20: bought gifts not yet wrapped | G20: GIFT PLANNER | J20: Next tradition | L20: =IF(MIN('TRADITIONS + BUCKET LIST'!$P$6:$P$85)=0,"Nothing dated yet.",IFERROR(INDEX('TRADITIONS + BUCKET LIST'!$C$6:$C$85,MATCH(MIN('TRADITIONS + BUCKET LIST'!$P$6:$P$85),'TRADITIONS + BUCKET LIST'!$P$6:$P$85,0)),"")&" — "&TEXT(MIN('TRADITIONS + BUCKET LIST'!$P$6:$P$85),"d mmm"))
B21: =COUNTIF('ONLINE ORDERS'!$R$6:$R$155,"LATE") | C21: orders running late | G21: ONLINE ORDERS | J21: Protecting | L21: =IF(Vision_Protect="","—",Vision_Protect)
B22: =COUNTIF('ONLINE ORDERS'!$R$6:$R$155,"NO TRACKING") | C22: orders with no tracking yet | G22: ONLINE ORDERS
B23: =COUNTIF('ONLINE ORDERS'!$R$6:$R$155,"MISSING DATE") | C23: orders with no expected date | G23: ONLINE ORDERS | J23: The next seven days
B24: =COUNTIF('ONLINE ORDERS'!$S$6:$S$155,"CLOSING SOON") | C24: return windows closing this week | G24: ONLINE ORDERS | J24: =IFERROR(INT(SMALL('CHRISTMAS CALENDAR'!$T$6:$T$205,1)),"") | L24: =IFERROR(INDEX('CHRISTMAS CALENDAR'!$F$6:$F$205,MATCH(SMALL('CHRISTMAS CALENDAR'!$T$6:$T$205,1),'CHRISTMAS CALENDAR'!$T$6:$T$205,0)),IF(1=1,"Nothing in the next seven days.",""))
B25: =COUNTIFS('RETURNS + EXCHANGES'!$B$6:$B$65,"?*",'RETURNS + EXCHANGES'!$P$6:$P$65,"<>Yes",'RETURNS + EXCHANGES'!$O$6:$O$65,">0") | C25: refunds owed to you | G25: RETURNS + EXCHANGES | J25: =IFERROR(INT(SMALL('CHRISTMAS CALENDAR'!$T$6:$T$205,2)),"") | L25: =IFERROR(INDEX('CHRISTMAS CALENDAR'!$F$6:$F$205,MATCH(SMALL('CHRISTMAS CALENDAR'!$T$6:$T$205,2),'CHRISTMAS CALENDAR'!$T$6:$T$205,0)),IF(2=1,"Nothing in the next seven days.",""))
B26: =COUNTIF('CHRISTMAS CALENDAR'!$R$6:$R$205,"OVERDUE") | C26: tasks and events overdue | G26: CHRISTMAS CALENDAR | J26: =IFERROR(INT(SMALL('CHRISTMAS CALENDAR'!$T$6:$T$205,3)),"") | L26: =IFERROR(INDEX('CHRISTMAS CALENDAR'!$F$6:$F$205,MATCH(SMALL('CHRISTMAS CALENDAR'!$T$6:$T$205,3),'CHRISTMAS CALENDAR'!$T$6:$T$205,0)),IF(3=1,"Nothing in the next seven days.",""))
B27: =COUNTIF('GROCERY LIST'!$P$6:$P$205,"TO BUY") | C27: things still to buy for the table | G27: GROCERY LIST | J27: =IFERROR(INT(SMALL('CHRISTMAS CALENDAR'!$T$6:$T$205,4)),"") | L27: =IFERROR(INDEX('CHRISTMAS CALENDAR'!$F$6:$F$205,MATCH(SMALL('CHRISTMAS CALENDAR'!$T$6:$T$205,4),'CHRISTMAS CALENDAR'!$T$6:$T$205,0)),IF(4=1,"Nothing in the next seven days.",""))
B28: =QA_Exceptions | C28: items on QUALITY CHECK | G28: QUALITY CHECK | J28: =IFERROR(INT(SMALL('CHRISTMAS CALENDAR'!$T$6:$T$205,5)),"") | L28: =IFERROR(INDEX('CHRISTMAS CALENDAR'!$F$6:$F$205,MATCH(SMALL('CHRISTMAS CALENDAR'!$T$6:$T$205,5),'CHRISTMAS CALENDAR'!$T$6:$T$205,0)),IF(5=1,"Nothing in the next seven days.",""))
J29: =IFERROR(INT(SMALL('CHRISTMAS CALENDAR'!$T$6:$T$205,6)),"") | L29: =IFERROR(INDEX('CHRISTMAS CALENDAR'!$F$6:$F$205,MATCH(SMALL('CHRISTMAS CALENDAR'!$T$6:$T$205,6),'CHRISTMAS CALENDAR'!$T$6:$T$205,0)),IF(6=1,"Nothing in the next seven days.",""))
B31: Where the money is going | J31: How far along you are
B58: Chart data — calculated. Safe to ignore; it is what the two charts above read.
B59: Category | D59: Budget | E59: Spent | J59: Progress | L59: Done
B60: =IFERROR(INDEX('MASTER BUDGET'!$D$6:$D$25,MATCH(LARGE('MASTER BUDGET'!$L$6:$L$25,1),'MASTER BUDGET'!$L$6:$L$25,0)),"") | D60: =IFERROR(INDEX('MASTER BUDGET'!$E$6:$E$25,MATCH(LARGE('MASTER BUDGET'!$L$6:$L$25,1),'MASTER BUDGET'!$L$6:$L$25,0)),0) | E60: =IFERROR(INDEX('MASTER BUDGET'!$G$6:$G$25,MATCH(LARGE('MASTER BUDGET'!$L$6:$L$25,1),'MASTER BUDGET'!$L$6:$L$25,0)),0) | J60: Gifts chosen | L60: =IF(COUNTIFS('GIFT PLANNER'!$E$6:$E$205,"Yes")=0,0,COUNTIFS('GIFT PLANNER'!$E$6:$E$205,"Yes",'GIFT PLANNER'!$T$6:$T$205,"Yes")/COUNTIFS('GIFT PLANNER'!$E$6:$E$205,"Yes"))
B61: =IFERROR(INDEX('MASTER BUDGET'!$D$6:$D$25,MATCH(LARGE('MASTER BUDGET'!$L$6:$L$25,2),'MASTER BUDGET'!$L$6:$L$25,0)),"") | D61: =IFERROR(INDEX('MASTER BUDGET'!$E$6:$E$25,MATCH(LARGE('MASTER BUDGET'!$L$6:$L$25,2),'MASTER BUDGET'!$L$6:$L$25,0)),0) | E61: =IFERROR(INDEX('MASTER BUDGET'!$G$6:$G$25,MATCH(LARGE('MASTER BUDGET'!$L$6:$L$25,2),'MASTER BUDGET'!$L$6:$L$25,0)),0) | J61: Wrapped | L61: =IF(COUNTIFS('GIFT PLANNER'!$E$6:$E$205,"Yes",'GIFT PLANNER'!$T$6:$T$205,"Yes",'GIFT PLANNER'!$Y$6:$Y$205,"Physical")=0,0,COUNTIFS('GIFT PLANNER'!$E$6:$E$205,"Yes",'GIFT PLANNER'!$T$6:$T$205,"Yes",'GIFT PLANNER'!$Y$6:$Y$205,"Physical",'GIFT PLANNER'!$Z$6:$Z$205,"Yes")/COUNTIFS('GIFT PLANNER'!$E$6:$E$205,"Yes",'GIFT PLANNER'!$T$6:$T$205,"Yes",'GIFT PLANNER'!$Y$6:$Y$205,"Physical"))
B62: =IFERROR(INDEX('MASTER BUDGET'!$D$6:$D$25,MATCH(LARGE('MASTER BUDGET'!$L$6:$L$25,3),'MASTER BUDGET'!$L$6:$L$25,0)),"") | D62: =IFERROR(INDEX('MASTER BUDGET'!$E$6:$E$25,MATCH(LARGE('MASTER BUDGET'!$L$6:$L$25,3),'MASTER BUDGET'!$L$6:$L$25,0)),0) | E62: =IFERROR(INDEX('MASTER BUDGET'!$G$6:$G$25,MATCH(LARGE('MASTER BUDGET'!$L$6:$L$25,3),'MASTER BUDGET'!$L$6:$L$25,0)),0) | J62: Delivered | L62: =IF(COUNTIFS('ONLINE ORDERS'!$B$6:$B$155,"?*",'ONLINE ORDERS'!$K$6:$K$155,"<>Cancelled")=0,0,COUNTIFS('ONLINE ORDERS'!$B$6:$B$155,"?*",'ONLINE ORDERS'!$K$6:$K$155,"<>Cancelled",'ONLINE ORDERS'!$M$6:$M$155,"Yes")/COUNTIFS('ONLINE ORDERS'!$B$6:$B$155,"?*",'ONLINE ORDERS'!$K$6:$K$155,"<>Cancelled"))
B63: =IFERROR(INDEX('MASTER BUDGET'!$D$6:$D$25,MATCH(LARGE('MASTER BUDGET'!$L$6:$L$25,4),'MASTER BUDGET'!$L$6:$L$25,0)),"") | D63: =IFERROR(INDEX('MASTER BUDGET'!$E$6:$E$25,MATCH(LARGE('MASTER BUDGET'!$L$6:$L$25,4),'MASTER BUDGET'!$L$6:$L$25,0)),0) | E63: =IFERROR(INDEX('MASTER BUDGET'!$G$6:$G$25,MATCH(LARGE('MASTER BUDGET'!$L$6:$L$25,4),'MASTER BUDGET'!$L$6:$L$25,0)),0) | J63: On the list | L63: =IF(COUNTIFS('CHRISTMAS CALENDAR'!$B$6:$B$205,"?*",'CHRISTMAS CALENDAR'!$Q$6:$Q$205,"Yes")+COUNTIFS('CHRISTMAS CALENDAR'!$B$6:$B$205,"?*",'CHRISTMAS CALENDAR'!$Q$6:$Q$205,"No")=0,0,COUNTIFS('CHRISTMAS CALENDAR'!$B$6:$B$205,"?*",'CHRISTMAS CALENDAR'!$Q$6:$Q$205,"No")/(COUNTIFS('CHRISTMAS CALENDAR'!$B$6:$B$205,"?*",'CHRISTMAS CALENDAR'!$Q$6:$Q$205,"Yes")+COUNTIFS('CHRISTMAS CALENDAR'!$B$6:$B$205,"?*",'CHRISTMAS CALENDAR'!$Q$6:$Q$205,"No")))
B64: =IFERROR(INDEX('MASTER BUDGET'!$D$6:$D$25,MATCH(LARGE('MASTER BUDGET'!$L$6:$L$25,5),'MASTER BUDGET'!$L$6:$L$25,0)),"") | D64: =IFERROR(INDEX('MASTER BUDGET'!$E$6:$E$25,MATCH(LARGE('MASTER BUDGET'!$L$6:$L$25,5),'MASTER BUDGET'!$L$6:$L$25,0)),0) | E64: =IFERROR(INDEX('MASTER BUDGET'!$G$6:$G$25,MATCH(LARGE('MASTER BUDGET'!$L$6:$L$25,5),'MASTER BUDGET'!$L$6:$L$25,0)),0)
B65: =IFERROR(INDEX('MASTER BUDGET'!$D$6:$D$25,MATCH(LARGE('MASTER BUDGET'!$L$6:$L$25,6),'MASTER BUDGET'!$L$6:$L$25,0)),"") | D65: =IFERROR(INDEX('MASTER BUDGET'!$E$6:$E$25,MATCH(LARGE('MASTER BUDGET'!$L$6:$L$25,6),'MASTER BUDGET'!$L$6:$L$25,0)),0) | E65: =IFERROR(INDEX('MASTER BUDGET'!$G$6:$G$25,MATCH(LARGE('MASTER BUDGET'!$L$6:$L$25,6),'MASTER BUDGET'!$L$6:$L$25,0)),0)
B66: =IFERROR(INDEX('MASTER BUDGET'!$D$6:$D$25,MATCH(LARGE('MASTER BUDGET'!$L$6:$L$25,7),'MASTER BUDGET'!$L$6:$L$25,0)),"") | D66: =IFERROR(INDEX('MASTER BUDGET'!$E$6:$E$25,MATCH(LARGE('MASTER BUDGET'!$L$6:$L$25,7),'MASTER BUDGET'!$L$6:$L$25,0)),0) | E66: =IFERROR(INDEX('MASTER BUDGET'!$G$6:$G$25,MATCH(LARGE('MASTER BUDGET'!$L$6:$L$25,7),'MASTER BUDGET'!$L$6:$L$25,0)),0)
B67: =IFERROR(INDEX('MASTER BUDGET'!$D$6:$D$25,MATCH(LARGE('MASTER BUDGET'!$L$6:$L$25,8),'MASTER BUDGET'!$L$6:$L$25,0)),"") | D67: =IFERROR(INDEX('MASTER BUDGET'!$E$6:$E$25,MATCH(LARGE('MASTER BUDGET'!$L$6:$L$25,8),'MASTER BUDGET'!$L$6:$L$25,0)),0) | E67: =IFERROR(INDEX('MASTER BUDGET'!$G$6:$G$25,MATCH(LARGE('MASTER BUDGET'!$L$6:$L$25,8),'MASTER BUDGET'!$L$6:$L$25,0)),0)
B68: =IFERROR(INDEX('MASTER BUDGET'!$D$6:$D$25,MATCH(LARGE('MASTER BUDGET'!$L$6:$L$25,9),'MASTER BUDGET'!$L$6:$L$25,0)),"") | D68: =IFERROR(INDEX('MASTER BUDGET'!$E$6:$E$25,MATCH(LARGE('MASTER BUDGET'!$L$6:$L$25,9),'MASTER BUDGET'!$L$6:$L$25,0)),0) | E68: =IFERROR(INDEX('MASTER BUDGET'!$G$6:$G$25,MATCH(LARGE('MASTER BUDGET'!$L$6:$L$25,9),'MASTER BUDGET'!$L$6:$L$25,0)),0)
B69: =IFERROR(INDEX('MASTER BUDGET'!$D$6:$D$25,MATCH(LARGE('MASTER BUDGET'!$L$6:$L$25,10),'MASTER BUDGET'!$L$6:$L$25,0)),"") | D69: =IFERROR(INDEX('MASTER BUDGET'!$E$6:$E$25,MATCH(LARGE('MASTER BUDGET'!$L$6:$L$25,10),'MASTER BUDGET'!$L$6:$L$25,0)),0) | E69: =IFERROR(INDEX('MASTER BUDGET'!$G$6:$G$25,MATCH(LARGE('MASTER BUDGET'!$L$6:$L$25,10),'MASTER BUDGET'!$L$6:$L$25,0)),0)

Sheet SEASON VISION
B1: Dashboard | D1: Start here | E1: Calendar | F1: Budget | G1: All sheets
B2: SEASON VISION
B3: What you want this Christmas to feel like, written down before the list-making starts.
B4: Cream cells are yours to fill in · pale green cells calculate themselves · amber rows are examples you can delete
B6: The season in five lines
B7: This year's theme | C7: Quieter, warmer, fewer things
B8: Three words for how it should feel | C8: Unhurried · candlelit · generous
B9: Colour story | C9: Evergreen, ivory, one note of oxblood
B10: Scent and sound | C10: Bitter orange, woodsmoke, the old carols
B11: What you are protecting this year | C11: The mornings. Nothing booked before eleven.
B12: The amber lines above are examples — write over them. The dashboard shows the theme, the feeling and the first priority below.
B14: Priority ID | C14: Priority | D14: Why it matters | E14: Owner | F14: Non-negotiable? | G14: Inspiration link | H14: Notes | I14: QA · duplicate ID
B15: VN-001 | C15: Christmas Eve supper with only the six of us | D15: It is the part everyone remembers | E15: Me | F15: Yes | H15: EXAMPLE — DELETE ME | I15: =IF($B15="",0,IF(COUNTIF('SEASON VISION'!$B$15:$B$38,$B15)>1,1,0))
B16: VN-002 | C16: Every gift chosen by the end of November | D16: December should be for people, not parcels | E16: Me | F16: Yes | H16: EXAMPLE — DELETE ME | I16: =IF($B16="",0,IF(COUNTIF('SEASON VISION'!$B$15:$B$38,$B16)>1,1,0))
B17: VN-003 | C17: One afternoon with nothing in it at all | D17: Last year there was not one | E17: Both | F17: No | H17: EXAMPLE — DELETE ME | I17: =IF($B17="",0,IF(COUNTIF('SEASON VISION'!$B$15:$B$38,$B17)>1,1,0))
I18: =IF($B18="",0,IF(COUNTIF('SEASON VISION'!$B$15:$B$38,$B18)>1,1,0))
I19: =IF($B19="",0,IF(COUNTIF('SEASON VISION'!$B$15:$B$38,$B19)>1,1,0))
I20: =IF($B20="",0,IF(COUNTIF('SEASON VISION'!$B$15:$B$38,$B20)>1,1,0))
I21: =IF($B21="",0,IF(COUNTIF('SEASON VISION'!$B$15:$B$38,$B21)>1,1,0))
I22: =IF($B22="",0,IF(COUNTIF('SEASON VISION'!$B$15:$B$38,$B22)>1,1,0))
I23: =IF($B23="",0,IF(COUNTIF('SEASON VISION'!$B$15:$B$38,$B23)>1,1,0))
I24: =IF($B24="",0,IF(COUNTIF('SEASON VISION'!$B$15:$B$38,$B24)>1,1,0))
I25: =IF($B25="",0,IF(COUNTIF('SEASON VISION'!$B$15:$B$38,$B25)>1,1,0))
I26: =IF($B26="",0,IF(COUNTIF('SEASON VISION'!$B$15:$B$38,$B26)>1,1,0))
I27: =IF($B27="",0,IF(COUNTIF('SEASON VISION'!$B$15:$B$38,$B27)>1,1,0))
I28: =IF($B28="",0,IF(COUNTIF('SEASON VISION'!$B$15:$B$38,$B28)>1,1,0))
I29: =IF($B29="",0,IF(COUNTIF('SEASON VISION'!$B$15:$B$38,$B29)>1,1,0))
... I38: =IF($B38="",0,IF(COUNTIF('SEASON VISION'!$B$15:$B$38,$B38)>1,1,0))

Sheet RECIPIENT PROFILES
B1: Dashboard | D1: Start here | E1: Calendar | F1: Budget | G1: All sheets
B2: RECIPIENT PROFILES
B3: What you know about the people you are giving to, so a gift never has to be guessed at twice.
B4: Cream cells are yours to fill in · pale green cells calculate themselves · amber rows are examples you can delete
B5: Person ID | C5: Name | D5: Relationship | E5: Birthday | F5: Sizes | G5: Preferred colours | H5: Interests | I5: Dislikes | J5: Sensitivities / allergies | K5: Favourite makers | L5: Monogram / engraving | M5: Preferred charities | N5: Address status | O5: Given before | P5: Do not repeat | Q5: Where it is hidden | R5: Notes | S5: QA · duplicate ID
B6: P-001 | C6: Eleanor Whitmore | D6: Parent | F6: Cashmere M · glove 7 | G6: Camel, ivory, deep green | H6: Gardening, Elgar, letter writing | I6: Anything battery powered | J6: Wool next to skin | K6: Smythson, Crabtree | L6: E.M.W. | N6: Confirmed | O6: 2024 silk scarf · 2023 secateurs | P6: Scented candles | Q6: Cedar chest, guest room | R6: EXAMPLE — DELETE ME | S6: =IF($B6="",0,IF(COUNTIF('RECIPIENT PROFILES'!$B$6:$B$105,$B6)>1,1,0))
B7: P-002 | C7: James Whitmore | D7: Spouse or partner | F7: Shirt 16 · shoe 10 | G7: Navy, oxblood | H7: Sailing, single malt, Ordnance Survey maps | I7: Novelty anything | K7: Barbour, Dents | L7: J.A.W. | N7: Confirmed | O7: 2024 chart of the Solent | P7: Ties | Q7: Top of the linen cupboard | R7: EXAMPLE — DELETE ME | S7: =IF($B7="",0,IF(COUNTIF('RECIPIENT PROFILES'!$B$6:$B$105,$B7)>1,1,0))
B8: P-003 | C8: Sofia Lindqvist | D8: Friend | G8: Ink blue | H8: Ceramics, cold-water swimming | J8: Nut allergy — serious | M8: Local river trust | N8: Needs checking | R8: EXAMPLE — DELETE ME | S8: =IF($B8="",0,IF(COUNTIF('RECIPIENT PROFILES'!$B$6:$B$105,$B8)>1,1,0))
S9: =IF($B9="",0,IF(COUNTIF('RECIPIENT PROFILES'!$B$6:$B$105,$B9)>1,1,0))
S10: =IF($B10="",0,IF(COUNTIF('RECIPIENT PROFILES'!$B$6:$B$105,$B10)>1,1,0))
S11: =IF($B11="",0,IF(COUNTIF('RECIPIENT PROFILES'!$B$6:$B$105,$B11)>1,1,0))
S12: =IF($B12="",0,IF(COUNTIF('RECIPIENT PROFILES'!$B$6:$B$105,$B12)>1,1,0))
S13: =IF($B13="",0,IF(COUNTIF('RECIPIENT PROFILES'!$B$6:$B$105,$B13)>1,1,0))
S14: =IF($B14="",0,IF(COUNTIF('RECIPIENT PROFILES'!$B$6:$B$105,$B14)>1,1,0))
S15: =IF($B15="",0,IF(COUNTIF('RECIPIENT PROFILES'!$B$6:$B$105,$B15)>1,1,0))
S16: =IF($B16="",0,IF(COUNTIF('RECIPIENT PROFILES'!$B$6:$B$105,$B16)>1,1,0))
S17: =IF($B17="",0,IF(COUNTIF('RECIPIENT PROFILES'!$B$6:$B$105,$B17)>1,1,0))
S18: =IF($B18="",0,IF(COUNTIF('RECIPIENT PROFILES'!$B$6:$B$105,$B18)>1,1,0))
S19: =IF($B19="",0,IF(COUNTIF('RECIPIENT PROFILES'!$B$6:$B$105,$B19)>1,1,0))
S20: =IF($B20="",0,IF(COUNTIF('RECIPIENT PROFILES'!$B$6:$B$105,$B20)>1,1,0))
... S105: =IF($B105="",0,IF(COUNTIF('RECIPIENT PROFILES'!$B$6:$B$105,$B105)>1,1,0))
B108: Keep only what helps you give well. Do not store payment card numbers, government ID numbers, passwords, or anything you would not want in a spreadsheet.

Sheet PEOPLE + BUDGETS
B1: Dashboard | D1: Start here | E1: Calendar | F1: Budget | G1: All sheets
B2: PEOPLE + BUDGETS
B3: Who you are giving to this year, and what you intend to spend on each of them.
B4: Cream cells are yours to fill in · pale green cells calculate themselves · amber rows are examples you can delete
B5: Person ID | C5: Name | D5: Group | E5: Gift budget | F5: Stocking budget | G5: Total budget | H5: Gifts planned | I5: Gifts actual | J5: Stockings planned | K5: Stockings actual | L5: Spent so far | M5: Remaining | N5: Status | O5: Active? | P5: Notes | Q5: QA · duplicate ID
B6: P-001 | C6: Eleanor Whitmore | D6: Immediate family | E6: 400 | F6: 60 | G6: =IF($B6="","",$E6+$F6) | H6: =IF($B6="","",SUMIFS('GIFT PLANNER'!$Q$6:$Q$205,'GIFT PLANNER'!$C$6:$C$205,$B6,'GIFT PLANNER'!$E$6:$E$205,"Yes")) | I6: =IF($B6="","",SUMIFS('GIFT PLANNER'!$R$6:$R$205,'GIFT PLANNER'!$C$6:$C$205,$B6,'GIFT PLANNER'!$E$6:$E$205,"Yes")) | J6: =IF($B6="","",SUMIFS('STOCKING STUFFERS'!$J$6:$J$155,'STOCKING STUFFERS'!$C$6:$C$155,$B6)) | K6: =IF($B6="","",SUMIFS('STOCKING STUFFERS'!$K$6:$K$155,'STOCKING STUFFERS'!$C$6:$C$155,$B6)) | L6: =IF($B6="","",$I6+$K6) | M6: =IF($B6="","",$G6-$L6) | N6: =IF($B6="","",IF(AND($G6=0,$L6=0),"NOT SET",IF($L6>$G6,"OVER BUDGET",IF($L6=$G6,"AT BUDGET",IF(AND($G6>0,$L6/$G6>=Set_WarnThreshold),"NEAR LIMIT","ON TRACK"))))) | O6: Yes | P6: EXAMPLE — DELETE ME | Q6: =IF($B6="",0,IF(COUNTIF('PEOPLE + BUDGETS'!$B$6:$B$105,$B6)>1,1,0))
B7: P-002 | C7: James Whitmore | D7: Immediate family | E7: 500 | F7: 60 | G7: =IF($B7="","",$E7+$F7) | H7: =IF($B7="","",SUMIFS('GIFT PLANNER'!$Q$6:$Q$205,'GIFT PLANNER'!$C$6:$C$205,$B7,'GIFT PLANNER'!$E$6:$E$205,"Yes")) | I7: =IF($B7="","",SUMIFS('GIFT PLANNER'!$R$6:$R$205,'GIFT PLANNER'!$C$6:$C$205,$B7,'GIFT PLANNER'!$E$6:$E$205,"Yes")) | J7: =IF($B7="","",SUMIFS('STOCKING STUFFERS'!$J$6:$J$155,'STOCKING STUFFERS'!$C$6:$C$155,$B7)) | K7: =IF($B7="","",SUMIFS('STOCKING STUFFERS'!$K$6:$K$155,'STOCKING STUFFERS'!$C$6:$C$155,$B7)) | L7: =IF($B7="","",$I7+$K7) | M7: =IF($B7="","",$G7-$L7) | N7: =IF($B7="","",IF(AND($G7=0,$L7=0),"NOT SET",IF($L7>$G7,"OVER BUDGET",IF($L7=$G7,"AT BUDGET",IF(AND($G7>0,$L7/$G7>=Set_WarnThreshold),"NEAR LIMIT","ON TRACK"))))) | O7: Yes | P7: EXAMPLE — DELETE ME | Q7: =IF($B7="",0,IF(COUNTIF('PEOPLE + BUDGETS'!$B$6:$B$105,$B7)>1,1,0))
B8: P-003 | C8: Sofia Lindqvist | D8: Friends | E8: 120 | F8: 0 | G8: =IF($B8="","",$E8+$F8) | H8: =IF($B8="","",SUMIFS('GIFT PLANNER'!$Q$6:$Q$205,'GIFT PLANNER'!$C$6:$C$205,$B8,'GIFT PLANNER'!$E$6:$E$205,"Yes")) | I8: =IF($B8="","",SUMIFS('GIFT PLANNER'!$R$6:$R$205,'GIFT PLANNER'!$C$6:$C$205,$B8,'GIFT PLANNER'!$E$6:$E$205,"Yes")) | J8: =IF($B8="","",SUMIFS('STOCKING STUFFERS'!$J$6:$J$155,'STOCKING STUFFERS'!$C$6:$C$155,$B8)) | K8: =IF($B8="","",SUMIFS('STOCKING STUFFERS'!$K$6:$K$155,'STOCKING STUFFERS'!$C$6:$C$155,$B8)) | L8: =IF($B8="","",$I8+$K8) | M8: =IF($B8="","",$G8-$L8) | N8: =IF($B8="","",IF(AND($G8=0,$L8=0),"NOT SET",IF($L8>$G8,"OVER BUDGET",IF($L8=$G8,"AT BUDGET",IF(AND($G8>0,$L8/$G8>=Set_WarnThreshold),"NEAR LIMIT","ON TRACK"))))) | O8: Yes | P8: EXAMPLE — DELETE ME | Q8: =IF($B8="",0,IF(COUNTIF('PEOPLE + BUDGETS'!$B$6:$B$105,$B8)>1,1,0))
G9: =IF($B9="","",$E9+$F9) | H9: =IF($B9="","",SUMIFS('GIFT PLANNER'!$Q$6:$Q$205,'GIFT PLANNER'!$C$6:$C$205,$B9,'GIFT PLANNER'!$E$6:$E$205,"Yes")) | I9: =IF($B9="","",SUMIFS('GIFT PLANNER'!$R$6:$R$205,'GIFT PLANNER'!$C$6:$C$205,$B9,'GIFT PLANNER'!$E$6:$E$205,"Yes")) | J9: =IF($B9="","",SUMIFS('STOCKING STUFFERS'!$J$6:$J$155,'STOCKING STUFFERS'!$C$6:$C$155,$B9)) | K9: =IF($B9="","",SUMIFS('STOCKING STUFFERS'!$K$6:$K$155,'STOCKING STUFFERS'!$C$6:$C$155,$B9)) | L9: =IF($B9="","",$I9+$K9) | M9: =IF($B9="","",$G9-$L9) | N9: =IF($B9="","",IF(AND($G9=0,$L9=0),"NOT SET",IF($L9>$G9,"OVER BUDGET",IF($L9=$G9,"AT BUDGET",IF(AND($G9>0,$L9/$G9>=Set_WarnThreshold),"NEAR LIMIT","ON TRACK"))))) | Q9: =IF($B9="",0,IF(COUNTIF('PEOPLE + BUDGETS'!$B$6:$B$105,$B9)>1,1,0))
G10: =IF($B10="","",$E10+$F10) | H10: =IF($B10="","",SUMIFS('GIFT PLANNER'!$Q$6:$Q$205,'GIFT PLANNER'!$C$6:$C$205,$B10,'GIFT PLANNER'!$E$6:$E$205,"Yes")) | I10: =IF($B10="","",SUMIFS('GIFT PLANNER'!$R$6:$R$205,'GIFT PLANNER'!$C$6:$C$205,$B10,'GIFT PLANNER'!$E$6:$E$205,"Yes")) | J10: =IF($B10="","",SUMIFS('STOCKING STUFFERS'!$J$6:$J$155,'STOCKING STUFFERS'!$C$6:$C$155,$B10)) | K10: =IF($B10="","",SUMIFS('STOCKING STUFFERS'!$K$6:$K$155,'STOCKING STUFFERS'!$C$6:$C$155,$B10)) | L10: =IF($B10="","",$I10+$K10) | M10: =IF($B10="","",$G10-$L10) | N10: =IF($B10="","",IF(AND($G10=0,$L10=0),"NOT SET",IF($L10>$G10,"OVER BUDGET",IF($L10=$G10,"AT BUDGET",IF(AND($G10>0,$L10/$G10>=Set_WarnThreshold),"NEAR LIMIT","ON TRACK"))))) | Q10: =IF($B10="",0,IF(COUNTIF('PEOPLE + BUDGETS'!$B$6:$B$105,$B10)>1,1,0))
G11: =IF($B11="","",$E11+$F11) | H11: =IF($B11="","",SUMIFS('GIFT PLANNER'!$Q$6:$Q$205,'GIFT PLANNER'!$C$6:$C$205,$B11,'GIFT PLANNER'!$E$6:$E$205,"Yes")) | I11: =IF($B11="","",SUMIFS('GIFT PLANNER'!$R$6:$R$205,'GIFT PLANNER'!$C$6:$C$205,$B11,'GIFT PLANNER'!$E$6:$E$205,"Yes")) | J11: =IF($B11="","",SUMIFS('STOCKING STUFFERS'!$J$6:$J$155,'STOCKING STUFFERS'!$C$6:$C$155,$B11)) | K11: =IF($B11="","",SUMIFS('STOCKING STUFFERS'!$K$6:$K$155,'STOCKING STUFFERS'!$C$6:$C$155,$B11)) | L11: =IF($B11="","",$I11+$K11) | M11: =IF($B11="","",$G11-$L11) | N11: =IF($B11="","",IF(AND($G11=0,$L11=0),"NOT SET",IF($L11>$G11,"OVER BUDGET",IF($L11=$G11,"AT BUDGET",IF(AND($G11>0,$L11/$G11>=Set_WarnThreshold),"NEAR LIMIT","ON TRACK"))))) | Q11: =IF($B11="",0,IF(COUNTIF('PEOPLE + BUDGETS'!$B$6:$B$105,$B11)>1,1,0))
G12: =IF($B12="","",$E12+$F12) | H12: =IF($B12="","",SUMIFS('GIFT PLANNER'!$Q$6:$Q$205,'GIFT PLANNER'!$C$6:$C$205,$B12,'GIFT PLANNER'!$E$6:$E$205,"Yes")) | I12: =IF($B12="","",SUMIFS('GIFT PLANNER'!$R$6:$R$205,'GIFT PLANNER'!$C$6:$C$205,$B12,'GIFT PLANNER'!$E$6:$E$205,"Yes")) | J12: =IF($B12="","",SUMIFS('STOCKING STUFFERS'!$J$6:$J$155,'STOCKING STUFFERS'!$C$6:$C$155,$B12)) | K12: =IF($B12="","",SUMIFS('STOCKING STUFFERS'!$K$6:$K$155,'STOCKING STUFFERS'!$C$6:$C$155,$B12)) | L12: =IF($B12="","",$I12+$K12) | M12: =IF($B12="","",$G12-$L12) | N12: =IF($B12="","",IF(AND($G12=0,$L12=0),"NOT SET",IF($L12>$G12,"OVER BUDGET",IF($L12=$G12,"AT BUDGET",IF(AND($G12>0,$L12/$G12>=Set_WarnThreshold),"NEAR LIMIT","ON TRACK"))))) | Q12: =IF($B12="",0,IF(COUNTIF('PEOPLE + BUDGETS'!$B$6:$B$105,$B12)>1,1,0))
G13: =IF($B13="","",$E13+$F13) | H13: =IF($B13="","",SUMIFS('GIFT PLANNER'!$Q$6:$Q$205,'GIFT PLANNER'!$C$6:$C$205,$B13,'GIFT PLANNER'!$E$6:$E$205,"Yes")) | I13: =IF($B13="","",SUMIFS('GIFT PLANNER'!$R$6:$R$205,'GIFT PLANNER'!$C$6:$C$205,$B13,'GIFT PLANNER'!$E$6:$E$205,"Yes")) | J13: =IF($B13="","",SUMIFS('STOCKING STUFFERS'!$J$6:$J$155,'STOCKING STUFFERS'!$C$6:$C$155,$B13)) | K13: =IF($B13="","",SUMIFS('STOCKING STUFFERS'!$K$6:$K$155,'STOCKING STUFFERS'!$C$6:$C$155,$B13)) | L13: =IF($B13="","",$I13+$K13) | M13: =IF($B13="","",$G13-$L13) | N13: =IF($B13="","",IF(AND($G13=0,$L13=0),"NOT SET",IF($L13>$G13,"OVER BUDGET",IF($L13=$G13,"AT BUDGET",IF(AND($G13>0,$L13/$G13>=Set_WarnThreshold),"NEAR LIMIT","ON TRACK"))))) | Q13: =IF($B13="",0,IF(COUNTIF('PEOPLE + BUDGETS'!$B$6:$B$105,$B13)>1,1,0))
G14: =IF($B14="","",$E14+$F14) | H14: =IF($B14="","",SUMIFS('GIFT PLANNER'!$Q$6:$Q$205,'GIFT PLANNER'!$C$6:$C$205,$B14,'GIFT PLANNER'!$E$6:$E$205,"Yes")) | I14: =IF($B14="","",SUMIFS('GIFT PLANNER'!$R$6:$R$205,'GIFT PLANNER'!$C$6:$C$205,$B14,'GIFT PLANNER'!$E$6:$E$205,"Yes")) | J14: =IF($B14="","",SUMIFS('STOCKING STUFFERS'!$J$6:$J$155,'STOCKING STUFFERS'!$C$6:$C$155,$B14)) | K14: =IF($B14="","",SUMIFS('STOCKING STUFFERS'!$K$6:$K$155,'STOCKING STUFFERS'!$C$6:$C$155,$B14)) | L14: =IF($B14="","",$I14+$K14) | M14: =IF($B14="","",$G14-$L14) | N14: =IF($B14="","",IF(AND($G14=0,$L14=0),"NOT SET",IF($L14>$G14,"OVER BUDGET",IF($L14=$G14,"AT BUDGET",IF(AND($G14>0,$L14/$G14>=Set_WarnThreshold),"NEAR LIMIT","ON TRACK"))))) | Q14: =IF($B14="",0,IF(COUNTIF('PEOPLE + BUDGETS'!$B$6:$B$105,$B14)>1,1,0))
G15: =IF($B15="","",$E15+$F15) | H15: =IF($B15="","",SUMIFS('GIFT PLANNER'!$Q$6:$Q$205,'GIFT PLANNER'!$C$6:$C$205,$B15,'GIFT PLANNER'!$E$6:$E$205,"Yes")) | I15: =IF($B15="","",SUMIFS('GIFT PLANNER'!$R$6:$R$205,'GIFT PLANNER'!$C$6:$C$205,$B15,'GIFT PLANNER'!$E$6:$E$205,"Yes")) | J15: =IF($B15="","",SUMIFS('STOCKING STUFFERS'!$J$6:$J$155,'STOCKING STUFFERS'!$C$6:$C$155,$B15)) | K15: =IF($B15="","",SUMIFS('STOCKING STUFFERS'!$K$6:$K$155,'STOCKING STUFFERS'!$C$6:$C$155,$B15)) | L15: =IF($B15="","",$I15+$K15) | M15: =IF($B15="","",$G15-$L15) | N15: =IF($B15="","",IF(AND($G15=0,$L15=0),"NOT SET",IF($L15>$G15,"OVER BUDGET",IF($L15=$G15,"AT BUDGET",IF(AND($G15>0,$L15/$G15>=Set_WarnThreshold),"NEAR LIMIT","ON TRACK"))))) | Q15: =IF($B15="",0,IF(COUNTIF('PEOPLE + BUDGETS'!$B$6:$B$105,$B15)>1,1,0))
G16: =IF($B16="","",$E16+$F16) | H16: =IF($B16="","",SUMIFS('GIFT PLANNER'!$Q$6:$Q$205,'GIFT PLANNER'!$C$6:$C$205,$B16,'GIFT PLANNER'!$E$6:$E$205,"Yes")) | I16: =IF($B16="","",SUMIFS('GIFT PLANNER'!$R$6:$R$205,'GIFT PLANNER'!$C$6:$C$205,$B16,'GIFT PLANNER'!$E$6:$E$205,"Yes")) | J16: =IF($B16="","",SUMIFS('STOCKING STUFFERS'!$J$6:$J$155,'STOCKING STUFFERS'!$C$6:$C$155,$B16)) | K16: =IF($B16="","",SUMIFS('STOCKING STUFFERS'!$K$6:$K$155,'STOCKING STUFFERS'!$C$6:$C$155,$B16)) | L16: =IF($B16="","",$I16+$K16) | M16: =IF($B16="","",$G16-$L16) | N16: =IF($B16="","",IF(AND($G16=0,$L16=0),"NOT SET",IF($L16>$G16,"OVER BUDGET",IF($L16=$G16,"AT BUDGET",IF(AND($G16>0,$L16/$G16>=Set_WarnThreshold),"NEAR LIMIT","ON TRACK"))))) | Q16: =IF($B16="",0,IF(COUNTIF('PEOPLE + BUDGETS'!$B$6:$B$105,$B16)>1,1,0))
G17: =IF($B17="","",$E17+$F17) | H17: =IF($B17="","",SUMIFS('GIFT PLANNER'!$Q$6:$Q$205,'GIFT PLANNER'!$C$6:$C$205,$B17,'GIFT PLANNER'!$E$6:$E$205,"Yes")) | I17: =IF($B17="","",SUMIFS('GIFT PLANNER'!$R$6:$R$205,'GIFT PLANNER'!$C$6:$C$205,$B17,'GIFT PLANNER'!$E$6:$E$205,"Yes")) | J17: =IF($B17="","",SUMIFS('STOCKING STUFFERS'!$J$6:$J$155,'STOCKING STUFFERS'!$C$6:$C$155,$B17)) | K17: =IF($B17="","",SUMIFS('STOCKING STUFFERS'!$K$6:$K$155,'STOCKING STUFFERS'!$C$6:$C$155,$B17)) | L17: =IF($B17="","",$I17+$K17) | M17: =IF($B17="","",$G17-$L17) | N17: =IF($B17="","",IF(AND($G17=0,$L17=0),"NOT SET",IF($L17>$G17,"OVER BUDGET",IF($L17=$G17,"AT BUDGET",IF(AND($G17>0,$L17/$G17>=Set_WarnThreshold),"NEAR LIMIT","ON TRACK"))))) | Q17: =IF($B17="",0,IF(COUNTIF('PEOPLE + BUDGETS'!$B$6:$B$105,$B17)>1,1,0))
G18: =IF($B18="","",$E18+$F18) | H18: =IF($B18="","",SUMIFS('GIFT PLANNER'!$Q$6:$Q$205,'GIFT PLANNER'!$C$6:$C$205,$B18,'GIFT PLANNER'!$E$6:$E$205,"Yes")) | I18: =IF($B18="","",SUMIFS('GIFT PLANNER'!$R$6:$R$205,'GIFT PLANNER'!$C$6:$C$205,$B18,'GIFT PLANNER'!$E$6:$E$205,"Yes")) | J18: =IF($B18="","",SUMIFS('STOCKING STUFFERS'!$J$6:$J$155,'STOCKING STUFFERS'!$C$6:$C$155,$B18)) | K18: =IF($B18="","",SUMIFS('STOCKING STUFFERS'!$K$6:$K$155,'STOCKING STUFFERS'!$C$6:$C$155,$B18)) | L18: =IF($B18="","",$I18+$K18) | M18: =IF($B18="","",$G18-$L18) | N18: =IF($B18="","",IF(AND($G18=0,$L18=0),"NOT SET",IF($L18>$G18,"OVER BUDGET",IF($L18=$G18,"AT BUDGET",IF(AND($G18>0,$L18/$G18>=Set_WarnThreshold),"NEAR LIMIT","ON TRACK"))))) | Q18: =IF($B18="",0,IF(COUNTIF('PEOPLE + BUDGETS'!$B$6:$B$105,$B18)>1,1,0))
G19: =IF($B19="","",$E19+$F19) | H19: =IF($B19="","",SUMIFS('GIFT PLANNER'!$Q$6:$Q$205,'GIFT PLANNER'!$C$6:$C$205,$B19,'GIFT PLANNER'!$E$6:$E$205,"Yes")) | I19: =IF($B19="","",SUMIFS('GIFT PLANNER'!$R$6:$R$205,'GIFT PLANNER'!$C$6:$C$205,$B19,'GIFT PLANNER'!$E$6:$E$205,"Yes")) | J19: =IF($B19="","",SUMIFS('STOCKING STUFFERS'!$J$6:$J$155,'STOCKING STUFFERS'!$C$6:$C$155,$B19)) | K19: =IF($B19="","",SUMIFS('STOCKING STUFFERS'!$K$6:$K$155,'STOCKING STUFFERS'!$C$6:$C$155,$B19)) | L19: =IF($B19="","",$I19+$K19) | M19: =IF($B19="","",$G19-$L19) | N19: =IF($B19="","",IF(AND($G19=0,$L19=0),"NOT SET",IF($L19>$G19,"OVER BUDGET",IF($L19=$G19,"AT BUDGET",IF(AND($G19>0,$L19/$G19>=Set_WarnThreshold),"NEAR LIMIT","ON TRACK"))))) | Q19: =IF($B19="",0,IF(COUNTIF('PEOPLE + BUDGETS'!$B$6:$B$105,$B19)>1,1,0))
G20: =IF($B20="","",$E20+$F20) | H20: =IF($B20="","",SUMIFS('GIFT PLANNER'!$Q$6:$Q$205,'GIFT PLANNER'!$C$6:$C$205,$B20,'GIFT PLANNER'!$E$6:$E$205,"Yes")) | I20: =IF($B20="","",SUMIFS('GIFT PLANNER'!$R$6:$R$205,'GIFT PLANNER'!$C$6:$C$205,$B20,'GIFT PLANNER'!$E$6:$E$205,"Yes")) | J20: =IF($B20="","",SUMIFS('STOCKING STUFFERS'!$J$6:$J$155,'STOCKING STUFFERS'!$C$6:$C$155,$B20)) | K20: =IF($B20="","",SUMIFS('STOCKING STUFFERS'!$K$6:$K$155,'STOCKING STUFFERS'!$C$6:$C$155,$B20)) | L20: =IF($B20="","",$I20+$K20) | M20: =IF($B20="","",$G20-$L20) | N20: =IF($B20="","",IF(AND($G20=0,$L20=0),"NOT SET",IF($L20>$G20,"OVER BUDGET",IF($L20=$G20,"AT BUDGET",IF(AND($G20>0,$L20/$G20>=Set_WarnThreshold),"NEAR LIMIT","ON TRACK"))))) | Q20: =IF($B20="",0,IF(COUNTIF('PEOPLE + BUDGETS'!$B$6:$B$105,$B20)>1,1,0))
... G105: =IF($B105="","",$E105+$F105) | H105: =IF($B105="","",SUMIFS('GIFT PLANNER'!$Q$6:$Q$205,'GIFT PLANNER'!$C$6:$C$205,$B105,'GIFT PLANNER'!$E$6:$E$205,"Yes")) | I105: =IF($B105="","",SUMIFS('GIFT PLANNER'!$R$6:$R$205,'GIFT PLANNER'!$C$6:$C$205,$B105,'GIFT PLANNER'!$E$6:$E$205,"Yes")) | J105: =IF($B105="","",SUMIFS('STOCKING STUFFERS'!$J$6:$J$155,'STOCKING STUFFERS'!$C$6:$C$155,$B105)) | K105: =IF($B105="","",SUMIFS('STOCKING STUFFERS'!$K$6:$K$155,'STOCKING STUFFERS'!$C$6:$C$155,$B105)) | L105: =IF($B105="","",$I105+$K105) | M105: =IF($B105="","",$G105-$L105) | N105: =IF($B105="","",IF(AND($G105=0,$L105=0),"NOT SET",IF($L105>$G105,"OVER BUDGET",IF($L105=$G105,"AT BUDGET",IF(AND($G105>0,$L105/$G105>=Set_WarnThreshold),"NEAR LIMIT","ON TRACK"))))) | Q105: =IF($B105="",0,IF(COUNTIF('PEOPLE + BUDGETS'!$B$6:$B$105,$B105)>1,1,0))

Sheet MASTER BUDGET
B1: Dashboard | D1: Start here | E1: Calendar | F1: Budget | G1: All sheets
B2: MASTER BUDGET
B3: What you set aside, what is planned against it, and what has actually left your account.
B4: Cream cells are yours to fill in · pale green cells calculate themselves · amber rows are examples you can delete
B5: Category ID | C5: In use? | D5: Category | E5: Budget | F5: Planned | G5: Actual | H5: Remaining | I5: Used | J5: Status | K5: Notes | L5: Chart rank key | M5: QA · duplicate ID
B6: B-001 | C6: Yes | D6: Gifts | E6: 2400 | F6: =IF($D6="","",SUMIFS('CARDS + MAIL'!$I$6:$I$155,'CARDS + MAIL'!$H$6:$H$155,$D6)+SUMIFS('DONATIONS + GIVING'!$G$6:$G$65,'DONATIONS + GIVING'!$F$6:$F$65,$D6)+SUMIFS('GIFT PLANNER'!$Q$6:$Q$205,'GIFT PLANNER'!$G$6:$G$205,$D6)+SUMIFS('STOCKING STUFFERS'!$J$6:$J$155,'STOCKING STUFFERS'!$F$6:$F$155,$D6)+SUMIFS('CHRISTMAS CALENDAR'!$K$6:$K$205,'CHRISTMAS CALENDAR'!$J$6:$J$205,$D6)+SUMIFS('DECOR INVENTORY'!$P$6:$P$105,'DECOR INVENTORY'!$O$6:$O$105,$D6)+SUMIFS('DECORATING PLAN'!$H$6:$H$65,'DECORATING PLAN'!$G$6:$G$65,$D6)+SUMIFS('TABLESCAPE + FLORALS'!$R$6:$R$65,'TABLESCAPE + FLORALS'!$Q$6:$Q$65,$D6)+SUMIFS('TRAVEL PLAN'!$M$6:$M$45,'TRAVEL PLAN'!$L$6:$L$45,$D6)+SUMIFS('VENDORS + APPOINTMENTS'!$M$6:$M$65,'VENDORS + APPOINTMENTS'!$L$6:$L$65,$D6)+SUMIFS('EVENTS + WARDROBE'!$N$6:$N$65,'EVENTS + WARDROBE'!$M$6:$M$65,$D6)+SUMIFS('GROCERY LIST'!$L$6:$L$205,'GROCERY LIST'!$K$6:$K$205,$D6)+SUMIFS('MEAL + BAKING PLAN'!$Q$6:$Q$155,'MEAL + BAKING PLAN'!$P$6:$P$155,$D6)+SUMIFS('TRADITIONS + BUCKET LIST'!$I$6:$I$85,'TRADITIONS + BUCKET LIST'!$H$6:$H$85,$D6)) | G6: =IF($D6="","",SUMIFS('CARDS + MAIL'!$J$6:$J$155,'CARDS + MAIL'!$H$6:$H$155,$D6)+SUMIFS('DONATIONS + GIVING'!$H$6:$H$65,'DONATIONS + GIVING'!$F$6:$F$65,$D6)+SUMIFS('GIFT PLANNER'!$R$6:$R$205,'GIFT PLANNER'!$G$6:$G$205,$D6)+SUMIFS('STOCKING STUFFERS'!$K$6:$K$155,'STOCKING STUFFERS'!$F$6:$F$155,$D6)+SUMIFS('CHRISTMAS CALENDAR'!$L$6:$L$205,'CHRISTMAS CALENDAR'!$J$6:$J$205,$D6)+SUMIFS('DECOR INVENTORY'!$Q$6:$Q$105,'DECOR INVENTORY'!$O$6:$O$105,$D6)+SUMIFS('DECORATING PLAN'!$I$6:$I$65,'DECORATING PLAN'!$G$6:$G$65,$D6)+SUMIFS('TABLESCAPE + FLORALS'!$S$6:$S$65,'TABLESCAPE + FLORALS'!$Q$6:$Q$65,$D6)+SUMIFS('TRAVEL PLAN'!$N$6:$N$45,'TRAVEL PLAN'!$L$6:$L$45,$D6)+SUMIFS('VENDORS + APPOINTMENTS'!$Q$6:$Q$65,'VENDORS + APPOINTMENTS'!$L$6:$L$65,$D6)+SUMIFS('EVENTS + WARDROBE'!$O$6:$O$65,'EVENTS + WARDROBE'!$M$6:$M$65,$D6)+SUMIFS('GROCERY LIST'!$M$6:$M$205,'GROCERY LIST'!$K$6:$K$205,$D6)+SUMIFS('MEAL + BAKING PLAN'!$R$6:$R$155,'MEAL + BAKING PLAN'!$P$6:$P$155,$D6)+SUMIFS('TRADITIONS + BUCKET LIST'!$J$6:$J$85,'TRADITIONS + BUCKET LIST'!$H$6:$H$85,$D6)-SUMIFS('RETURNS + EXCHANGES'!$R$6:$R$65,'RETURNS + EXCHANGES'!$K$6:$K$65,$D6)) | H6: =IF($D6="","",$E6-$G6) | I6: =IF($D6="","",IF($E6=0,0,$G6/$E6)) | J6: =IF($D6="","",IF(AND($E6=0,$G6=0),"NOT SET",IF($G6>$E6,"OVER BUDGET",IF($G6=$E6,"AT BUDGET",IF(AND($E6>0,$G6/$E6>=Set_WarnThreshold),"NEAR LIMIT","ON TRACK"))))) | K6: EXAMPLE FIGURE — type your own over it | L6: =IF(AND($C6="Yes",$D6<>"",OR(N($E6)>0,N($G6)>0)),$E6+(100-ROW())/10000,"") | M6: =IF($B6="",0,IF(COUNTIF('MASTER BUDGET'!$B$6:$B$25,$B6)>1,1,0))
B7: B-002 | C7: Yes | D7: Stockings | E7: 300 | F7: =IF($D7="","",SUMIFS('CARDS + MAIL'!$I$6:$I$155,'CARDS + MAIL'!$H$6:$H$155,$D7)+SUMIFS('DONATIONS + GIVING'!$G$6:$G$65,'DONATIONS + GIVING'!$F$6:$F$65,$D7)+SUMIFS('GIFT PLANNER'!$Q$6:$Q$205,'GIFT PLANNER'!$G$6:$G$205,$D7)+SUMIFS('STOCKING STUFFERS'!$J$6:$J$155,'STOCKING STUFFERS'!$F$6:$F$155,$D7)+SUMIFS('CHRISTMAS CALENDAR'!$K$6:$K$205,'CHRISTMAS CALENDAR'!$J$6:$J$205,$D7)+SUMIFS('DECOR INVENTORY'!$P$6:$P$105,'DECOR INVENTORY'!$O$6:$O$105,$D7)+SUMIFS('DECORATING PLAN'!$H$6:$H$65,'DECORATING PLAN'!$G$6:$G$65,$D7)+SUMIFS('TABLESCAPE + FLORALS'!$R$6:$R$65,'TABLESCAPE + FLORALS'!$Q$6:$Q$65,$D7)+SUMIFS('TRAVEL PLAN'!$M$6:$M$45,'TRAVEL PLAN'!$L$6:$L$45,$D7)+SUMIFS('VENDORS + APPOINTMENTS'!$M$6:$M$65,'VENDORS + APPOINTMENTS'!$L$6:$L$65,$D7)+SUMIFS('EVENTS + WARDROBE'!$N$6:$N$65,'EVENTS + WARDROBE'!$M$6:$M$65,$D7)+SUMIFS('GROCERY LIST'!$L$6:$L$205,'GROCERY LIST'!$K$6:$K$205,$D7)+SUMIFS('MEAL + BAKING PLAN'!$Q$6:$Q$155,'MEAL + BAKING PLAN'!$P$6:$P$155,$D7)+SUMIFS('TRADITIONS + BUCKET LIST'!$I$6:$I$85,'TRADITIONS + BUCKET LIST'!$H$6:$H$85,$D7)) | G7: =IF($D7="","",SUMIFS('CARDS + MAIL'!$J$6:$J$155,'CARDS + MAIL'!$H$6:$H$155,$D7)+SUMIFS('DONATIONS + GIVING'!$H$6:$H$65,'DONATIONS + GIVING'!$F$6:$F$65,$D7)+SUMIFS('GIFT PLANNER'!$R$6:$R$205,'GIFT PLANNER'!$G$6:$G$205,$D7)+SUMIFS('STOCKING STUFFERS'!$K$6:$K$155,'STOCKING STUFFERS'!$F$6:$F$155,$D7)+SUMIFS('CHRISTMAS CALENDAR'!$L$6:$L$205,'CHRISTMAS CALENDAR'!$J$6:$J$205,$D7)+SUMIFS('DECOR INVENTORY'!$Q$6:$Q$105,'DECOR INVENTORY'!$O$6:$O$105,$D7)+SUMIFS('DECORATING PLAN'!$I$6:$I$65,'DECORATING PLAN'!$G$6:$G$65,$D7)+SUMIFS('TABLESCAPE + FLORALS'!$S$6:$S$65,'TABLESCAPE + FLORALS'!$Q$6:$Q$65,$D7)+SUMIFS('TRAVEL PLAN'!$N$6:$N$45,'TRAVEL PLAN'!$L$6:$L$45,$D7)+SUMIFS('VENDORS + APPOINTMENTS'!$Q$6:$Q$65,'VENDORS + APPOINTMENTS'!$L$6:$L$65,$D7)+SUMIFS('EVENTS + WARDROBE'!$O$6:$O$65,'EVENTS + WARDROBE'!$M$6:$M$65,$D7)+SUMIFS('GROCERY LIST'!$M$6:$M$205,'GROCERY LIST'!$K$6:$K$205,$D7)+SUMIFS('MEAL + BAKING PLAN'!$R$6:$R$155,'MEAL + BAKING PLAN'!$P$6:$P$155,$D7)+SUMIFS('TRADITIONS + BUCKET LIST'!$J$6:$J$85,'TRADITIONS + BUCKET LIST'!$H$6:$H$85,$D7)-SUMIFS('RETURNS + EXCHANGES'!$R$6:$R$65,'RETURNS + EXCHANGES'!$K$6:$K$65,$D7)) | H7: =IF($D7="","",$E7-$G7) | I7: =IF($D7="","",IF($E7=0,0,$G7/$E7)) | J7: =IF($D7="","",IF(AND($E7=0,$G7=0),"NOT SET",IF($G7>$E7,"OVER BUDGET",IF($G7=$E7,"AT BUDGET",IF(AND($E7>0,$G7/$E7>=Set_WarnThreshold),"NEAR LIMIT","ON TRACK"))))) | K7: EXAMPLE FIGURE — type your own over it | L7: =IF(AND($C7="Yes",$D7<>"",OR(N($E7)>0,N($G7)>0)),$E7+(100-ROW())/10000,"") | M7: =IF($B7="",0,IF(COUNTIF('MASTER BUDGET'!$B$6:$B$25,$B7)>1,1,0))
B8: B-003 | C8: Yes | D8: Decorations | E8: 600 | F8: =IF($D8="","",SUMIFS('CARDS + MAIL'!$I$6:$I$155,'CARDS + MAIL'!$H$6:$H$155,$D8)+SUMIFS('DONATIONS + GIVING'!$G$6:$G$65,'DONATIONS + GIVING'!$F$6:$F$65,$D8)+SUMIFS('GIFT PLANNER'!$Q$6:$Q$205,'GIFT PLANNER'!$G$6:$G$205,$D8)+SUMIFS('STOCKING STUFFERS'!$J$6:$J$155,'STOCKING STUFFERS'!$F$6:$F$155,$D8)+SUMIFS('CHRISTMAS CALENDAR'!$K$6:$K$205,'CHRISTMAS CALENDAR'!$J$6:$J$205,$D8)+SUMIFS('DECOR INVENTORY'!$P$6:$P$105,'DECOR INVENTORY'!$O$6:$O$105,$D8)+SUMIFS('DECORATING PLAN'!$H$6:$H$65,'DECORATING PLAN'!$G$6:$G$65,$D8)+SUMIFS('TABLESCAPE + FLORALS'!$R$6:$R$65,'TABLESCAPE + FLORALS'!$Q$6:$Q$65,$D8)+SUMIFS('TRAVEL PLAN'!$M$6:$M$45,'TRAVEL PLAN'!$L$6:$L$45,$D8)+SUMIFS('VENDORS + APPOINTMENTS'!$M$6:$M$65,'VENDORS + APPOINTMENTS'!$L$6:$L$65,$D8)+SUMIFS('EVENTS + WARDROBE'!$N$6:$N$65,'EVENTS + WARDROBE'!$M$6:$M$65,$D8)+SUMIFS('GROCERY LIST'!$L$6:$L$205,'GROCERY LIST'!$K$6:$K$205,$D8)+SUMIFS('MEAL + BAKING PLAN'!$Q$6:$Q$155,'MEAL + BAKING PLAN'!$P$6:$P$155,$D8)+SUMIFS('TRADITIONS + BUCKET LIST'!$I$6:$I$85,'TRADITIONS + BUCKET LIST'!$H$6:$H$85,$D8)) | G8: =IF($D8="","",SUMIFS('CARDS + MAIL'!$J$6:$J$155,'CARDS + MAIL'!$H$6:$H$155,$D8)+SUMIFS('DONATIONS + GIVING'!$H$6:$H$65,'DONATIONS + GIVING'!$F$6:$F$65,$D8)+SUMIFS('GIFT PLANNER'!$R$6:$R$205,'GIFT PLANNER'!$G$6:$G$205,$D8)+SUMIFS('STOCKING STUFFERS'!$K$6:$K$155,'STOCKING STUFFERS'!$F$6:$F$155,$D8)+SUMIFS('CHRISTMAS CALENDAR'!$L$6:$L$205,'CHRISTMAS CALENDAR'!$J$6:$J$205,$D8)+SUMIFS('DECOR INVENTORY'!$Q$6:$Q$105,'DECOR INVENTORY'!$O$6:$O$105,$D8)+SUMIFS('DECORATING PLAN'!$I$6:$I$65,'DECORATING PLAN'!$G$6:$G$65,$D8)+SUMIFS('TABLESCAPE + FLORALS'!$S$6:$S$65,'TABLESCAPE + FLORALS'!$Q$6:$Q$65,$D8)+SUMIFS('TRAVEL PLAN'!$N$6:$N$45,'TRAVEL PLAN'!$L$6:$L$45,$D8)+SUMIFS('VENDORS + APPOINTMENTS'!$Q$6:$Q$65,'VENDORS + APPOINTMENTS'!$L$6:$L$65,$D8)+SUMIFS('EVENTS + WARDROBE'!$O$6:$O$65,'EVENTS + WARDROBE'!$M$6:$M$65,$D8)+SUMIFS('GROCERY LIST'!$M$6:$M$205,'GROCERY LIST'!$K$6:$K$205,$D8)+SUMIFS('MEAL + BAKING PLAN'!$R$6:$R$155,'MEAL + BAKING PLAN'!$P$6:$P$155,$D8)+SUMIFS('TRADITIONS + BUCKET LIST'!$J$6:$J$85,'TRADITIONS + BUCKET LIST'!$H$6:$H$85,$D8)-SUMIFS('RETURNS + EXCHANGES'!$R$6:$R$65,'RETURNS + EXCHANGES'!$K$6:$K$65,$D8)) | H8: =IF($D8="","",$E8-$G8) | I8: =IF($D8="","",IF($E8=0,0,$G8/$E8)) | J8: =IF($D8="","",IF(AND($E8=0,$G8=0),"NOT SET",IF($G8>$E8,"OVER BUDGET",IF($G8=$E8,"AT BUDGET",IF(AND($E8>0,$G8/$E8>=Set_WarnThreshold),"NEAR LIMIT","ON TRACK"))))) | K8: EXAMPLE FIGURE — type your own over it | L8: =IF(AND($C8="Yes",$D8<>"",OR(N($E8)>0,N($G8)>0)),$E8+(100-ROW())/10000,"") | M8: =IF($B8="",0,IF(COUNTIF('MASTER BUDGET'!$B$6:$B$25,$B8)>1,1,0))
B9: B-004 | C9: Yes | D9: Food & Baking | E9: 900 | F9: =IF($D9="","",SUMIFS('CARDS + MAIL'!$I$6:$I$155,'CARDS + MAIL'!$H$6:$H$155,$D9)+SUMIFS('DONATIONS + GIVING'!$G$6:$G$65,'DONATIONS + GIVING'!$F$6:$F$65,$D9)+SUMIFS('GIFT PLANNER'!$Q$6:$Q$205,'GIFT PLANNER'!$G$6:$G$205,$D9)+SUMIFS('STOCKING STUFFERS'!$J$6:$J$155,'STOCKING STUFFERS'!$F$6:$F$155,$D9)+SUMIFS('CHRISTMAS CALENDAR'!$K$6:$K$205,'CHRISTMAS CALENDAR'!$J$6:$J$205,$D9)+SUMIFS('DECOR INVENTORY'!$P$6:$P$105,'DECOR INVENTORY'!$O$6:$O$105,$D9)+SUMIFS('DECORATING PLAN'!$H$6:$H$65,'DECORATING PLAN'!$G$6:$G$65,$D9)+SUMIFS('TABLESCAPE + FLORALS'!$R$6:$R$65,'TABLESCAPE + FLORALS'!$Q$6:$Q$65,$D9)+SUMIFS('TRAVEL PLAN'!$M$6:$M$45,'TRAVEL PLAN'!$L$6:$L$45,$D9)+SUMIFS('VENDORS + APPOINTMENTS'!$M$6:$M$65,'VENDORS + APPOINTMENTS'!$L$6:$L$65,$D9)+SUMIFS('EVENTS + WARDROBE'!$N$6:$N$65,'EVENTS + WARDROBE'!$M$6:$M$65,$D9)+SUMIFS('GROCERY LIST'!$L$6:$L$205,'GROCERY LIST'!$K$6:$K$205,$D9)+SUMIFS('MEAL + BAKING PLAN'!$Q$6:$Q$155,'MEAL + BAKING PLAN'!$P$6:$P$155,$D9)+SUMIFS('TRADITIONS + BUCKET LIST'!$I$6:$I$85,'TRADITIONS + BUCKET LIST'!$H$6:$H$85,$D9)) | G9: =IF($D9="","",SUMIFS('CARDS + MAIL'!$J$6:$J$155,'CARDS + MAIL'!$H$6:$H$155,$D9)+SUMIFS('DONATIONS + GIVING'!$H$6:$H$65,'DONATIONS + GIVING'!$F$6:$F$65,$D9)+SUMIFS('GIFT PLANNER'!$R$6:$R$205,'GIFT PLANNER'!$G$6:$G$205,$D9)+SUMIFS('STOCKING STUFFERS'!$K$6:$K$155,'STOCKING STUFFERS'!$F$6:$F$155,$D9)+SUMIFS('CHRISTMAS CALENDAR'!$L$6:$L$205,'CHRISTMAS CALENDAR'!$J$6:$J$205,$D9)+SUMIFS('DECOR INVENTORY'!$Q$6:$Q$105,'DECOR INVENTORY'!$O$6:$O$105,$D9)+SUMIFS('DECORATING PLAN'!$I$6:$I$65,'DECORATING PLAN'!$G$6:$G$65,$D9)+SUMIFS('TABLESCAPE + FLORALS'!$S$6:$S$65,'TABLESCAPE + FLORALS'!$Q$6:$Q$65,$D9)+SUMIFS('TRAVEL PLAN'!$N$6:$N$45,'TRAVEL PLAN'!$L$6:$L$45,$D9)+SUMIFS('VENDORS + APPOINTMENTS'!$Q$6:$Q$65,'VENDORS + APPOINTMENTS'!$L$6:$L$65,$D9)+SUMIFS('EVENTS + WARDROBE'!$O$6:$O$65,'EVENTS + WARDROBE'!$M$6:$M$65,$D9)+SUMIFS('GROCERY LIST'!$M$6:$M$205,'GROCERY LIST'!$K$6:$K$205,$D9)+SUMIFS('MEAL + BAKING PLAN'!$R$6:$R$155,'MEAL + BAKING PLAN'!$P$6:$P$155,$D9)+SUMIFS('TRADITIONS + BUCKET LIST'!$J$6:$J$85,'TRADITIONS + BUCKET LIST'!$H$6:$H$85,$D9)-SUMIFS('RETURNS + EXCHANGES'!$R$6:$R$65,'RETURNS + EXCHANGES'!$K$6:$K$65,$D9)) | H9: =IF($D9="","",$E9-$G9) | I9: =IF($D9="","",IF($E9=0,0,$G9/$E9)) | J9: =IF($D9="","",IF(AND($E9=0,$G9=0),"NOT SET",IF($G9>$E9,"OVER BUDGET",IF($G9=$E9,"AT BUDGET",IF(AND($E9>0,$G9/$E9>=Set_WarnThreshold),"NEAR LIMIT","ON TRACK"))))) | K9: EXAMPLE FIGURE — type your own over it | L9: =IF(AND($C9="Yes",$D9<>"",OR(N($E9)>0,N($G9)>0)),$E9+(100-ROW())/10000,"") | M9: =IF($B9="",0,IF(COUNTIF('MASTER BUDGET'!$B$6:$B$25,$B9)>1,1,0))
B10: B-005 | C10: Yes | D10: Cards & Postage | E10: 150 | F10: =IF($D10="","",SUMIFS('CARDS + MAIL'!$I$6:$I$155,'CARDS + MAIL'!$H$6:$H$155,$D10)+SUMIFS('DONATIONS + GIVING'!$G$6:$G$65,'DONATIONS + GIVING'!$F$6:$F$65,$D10)+SUMIFS('GIFT PLANNER'!$Q$6:$Q$205,'GIFT PLANNER'!$G$6:$G$205,$D10)+SUMIFS('STOCKING STUFFERS'!$J$6:$J$155,'STOCKING STUFFERS'!$F$6:$F$155,$D10)+SUMIFS('CHRISTMAS CALENDAR'!$K$6:$K$205,'CHRISTMAS CALENDAR'!$J$6:$J$205,$D10)+SUMIFS('DECOR INVENTORY'!$P$6:$P$105,'DECOR INVENTORY'!$O$6:$O$105,$D10)+SUMIFS('DECORATING PLAN'!$H$6:$H$65,'DECORATING PLAN'!$G$6:$G$65,$D10)+SUMIFS('TABLESCAPE + FLORALS'!$R$6:$R$65,'TABLESCAPE + FLORALS'!$Q$6:$Q$65,$D10)+SUMIFS('TRAVEL PLAN'!$M$6:$M$45,'TRAVEL PLAN'!$L$6:$L$45,$D10)+SUMIFS('VENDORS + APPOINTMENTS'!$M$6:$M$65,'VENDORS + APPOINTMENTS'!$L$6:$L$65,$D10)+SUMIFS('EVENTS + WARDROBE'!$N$6:$N$65,'EVENTS + WARDROBE'!$M$6:$M$65,$D10)+SUMIFS('GROCERY LIST'!$L$6:$L$205,'GROCERY LIST'!$K$6:$K$205,$D10)+SUMIFS('MEAL + BAKING PLAN'!$Q$6:$Q$155,'MEAL + BAKING PLAN'!$P$6:$P$155,$D10)+SUMIFS('TRADITIONS + BUCKET LIST'!$I$6:$I$85,'TRADITIONS + BUCKET LIST'!$H$6:$H$85,$D10)) | G10: =IF($D10="","",SUMIFS('CARDS + MAIL'!$J$6:$J$155,'CARDS + MAIL'!$H$6:$H$155,$D10)+SUMIFS('DONATIONS + GIVING'!$H$6:$H$65,'DONATIONS + GIVING'!$F$6:$F$65,$D10)+SUMIFS('GIFT PLANNER'!$R$6:$R$205,'GIFT PLANNER'!$G$6:$G$205,$D10)+SUMIFS('STOCKING STUFFERS'!$K$6:$K$155,'STOCKING STUFFERS'!$F$6:$F$155,$D10)+SUMIFS('CHRISTMAS CALENDAR'!$L$6:$L$205,'CHRISTMAS CALENDAR'!$J$6:$J$205,$D10)+SUMIFS('DECOR INVENTORY'!$Q$6:$Q$105,'DECOR INVENTORY'!$O$6:$O$105,$D10)+SUMIFS('DECORATING PLAN'!$I$6:$I$65,'DECORATING PLAN'!$G$6:$G$65,$D10)+SUMIFS('TABLESCAPE + FLORALS'!$S$6:$S$65,'TABLESCAPE + FLORALS'!$Q$6:$Q$65,$D10)+SUMIFS('TRAVEL PLAN'!$N$6:$N$45,'TRAVEL PLAN'!$L$6:$L$45,$D10)+SUMIFS('VENDORS + APPOINTMENTS'!$Q$6:$Q$65,'VENDORS + APPOINTMENTS'!$L$6:$L$65,$D10)+SUMIFS('EVENTS + WARDROBE'!$O$6:$O$65,'EVENTS + WARDROBE'!$M$6:$M$65,$D10)+SUMIFS('GROCERY LIST'!$M$6:$M$205,'GROCERY LIST'!$K$6:$K$205,$D10)+SUMIFS('MEAL + BAKING PLAN'!$R$6:$R$155,'MEAL + BAKING PLAN'!$P$6:$P$155,$D10)+SUMIFS('TRADITIONS + BUCKET LIST'!$J$6:$J$85,'TRADITIONS + BUCKET LIST'!$H$6:$H$85,$D10)-SUMIFS('RETURNS + EXCHANGES'!$R$6:$R$65,'RETURNS + EXCHANGES'!$K$6:$K$65,$D10)) | H10: =IF($D10="","",$E10-$G10) | I10: =IF($D10="","",IF($E10=0,0,$G10/$E10)) | J10: =IF($D10="","",IF(AND($E10=0,$G10=0),"NOT SET",IF($G10>$E10,"OVER BUDGET",IF($G10=$E10,"AT BUDGET",IF(AND($E10>0,$G10/$E10>=Set_WarnThreshold),"NEAR LIMIT","ON TRACK"))))) | K10: EXAMPLE FIGURE — type your own over it | L10: =IF(AND($C10="Yes",$D10<>"",OR(N($E10)>0,N($G10)>0)),$E10+(100-ROW())/10000,"") | M10: =IF($B10="",0,IF(COUNTIF('MASTER BUDGET'!$B$6:$B$25,$B10)>1,1,0))
B11: B-006 | C11: Yes | D11: Events | E11: 700 | F11: =IF($D11="","",SUMIFS('CARDS + MAIL'!$I$6:$I$155,'CARDS + MAIL'!$H$6:$H$155,$D11)+SUMIFS('DONATIONS + GIVING'!$G$6:$G$65,'DONATIONS + GIVING'!$F$6:$F$65,$D11)+SUMIFS('GIFT PLANNER'!$Q$6:$Q$205,'GIFT PLANNER'!$G$6:$G$205,$D11)+SUMIFS('STOCKING STUFFERS'!$J$6:$J$155,'STOCKING STUFFERS'!$F$6:$F$155,$D11)+SUMIFS('CHRISTMAS CALENDAR'!$K$6:$K$205,'CHRISTMAS CALENDAR'!$J$6:$J$205,$D11)+SUMIFS('DECOR INVENTORY'!$P$6:$P$105,'DECOR INVENTORY'!$O$6:$O$105,$D11)+SUMIFS('DECORATING PLAN'!$H$6:$H$65,'DECORATING PLAN'!$G$6:$G$65,$D11)+SUMIFS('TABLESCAPE + FLORALS'!$R$6:$R$65,'TABLESCAPE + FLORALS'!$Q$6:$Q$65,$D11)+SUMIFS('TRAVEL PLAN'!$M$6:$M$45,'TRAVEL PLAN'!$L$6:$L$45,$D11)+SUMIFS('VENDORS + APPOINTMENTS'!$M$6:$M$65,'VENDORS + APPOINTMENTS'!$L$6:$L$65,$D11)+SUMIFS('EVENTS + WARDROBE'!$N$6:$N$65,'EVENTS + WARDROBE'!$M$6:$M$65,$D11)+SUMIFS('GROCERY LIST'!$L$6:$L$205,'GROCERY LIST'!$K$6:$K$205,$D11)+SUMIFS('MEAL + BAKING PLAN'!$Q$6:$Q$155,'MEAL + BAKING PLAN'!$P$6:$P$155,$D11)+SUMIFS('TRADITIONS + BUCKET LIST'!$I$6:$I$85,'TRADITIONS + BUCKET LIST'!$H$6:$H$85,$D11)) | G11: =IF($D11="","",SUMIFS('CARDS + MAIL'!$J$6:$J$155,'CARDS + MAIL'!$H$6:$H$155,$D11)+SUMIFS('DONATIONS + GIVING'!$H$6:$H$65,'DONATIONS + GIVING'!$F$6:$F$65,$D11)+SUMIFS('GIFT PLANNER'!$R$6:$R$205,'GIFT PLANNER'!$G$6:$G$205,$D11)+SUMIFS('STOCKING STUFFERS'!$K$6:$K$155,'STOCKING STUFFERS'!$F$6:$F$155,$D11)+SUMIFS('CHRISTMAS CALENDAR'!$L$6:$L$205,'CHRISTMAS CALENDAR'!$J$6:$J$205,$D11)+SUMIFS('DECOR INVENTORY'!$Q$6:$Q$105,'DECOR INVENTORY'!$O$6:$O$105,$D11)+SUMIFS('DECORATING PLAN'!$I$6:$I$65,'DECORATING PLAN'!$G$6:$G$65,$D11)+SUMIFS('TABLESCAPE + FLORALS'!$S$6:$S$65,'TABLESCAPE + FLORALS'!$Q$6:$Q$65,$D11)+SUMIFS('TRAVEL PLAN'!$N$6:$N$45,'TRAVEL PLAN'!$L$6:$L$45,$D11)+SUMIFS('VENDORS + APPOINTMENTS'!$Q$6:$Q$65,'VENDORS + APPOINTMENTS'!$L$6:$L$65,$D11)+SUMIFS('EVENTS + WARDROBE'!$O$6:$O$65,'EVENTS + WARDROBE'!$M$6:$M$65,$D11)+SUMIFS('GROCERY LIST'!$M$6:$M$205,'GROCERY LIST'!$K$6:$K$205,$D11)+SUMIFS('MEAL + BAKING PLAN'!$R$6:$R$155,'MEAL + BAKING PLAN'!$P$6:$P$155,$D11)+SUMIFS('TRADITIONS + BUCKET LIST'!$J$6:$J$85,'TRADITIONS + BUCKET LIST'!$H$6:$H$85,$D11)-SUMIFS('RETURNS + EXCHANGES'!$R$6:$R$65,'RETURNS + EXCHANGES'!$K$6:$K$65,$D11)) | H11: =IF($D11="","",$E11-$G11) | I11: =IF($D11="","",IF($E11=0,0,$G11/$E11)) | J11: =IF($D11="","",IF(AND($E11=0,$G11=0),"NOT SET",IF($G11>$E11,"OVER BUDGET",IF($G11=$E11,"AT BUDGET",IF(AND($E11>0,$G11/$E11>=Set_WarnThreshold),"NEAR LIMIT","ON TRACK"))))) | K11: EXAMPLE FIGURE — type your own over it | L11: =IF(AND($C11="Yes",$D11<>"",OR(N($E11)>0,N($G11)>0)),$E11+(100-ROW())/10000,"") | M11: =IF($B11="",0,IF(COUNTIF('MASTER BUDGET'!$B$6:$B$25,$B11)>1,1,0))
B12: B-007 | C12: Yes | D12: Outfits | E12: 400 | F12: =IF($D12="","",SUMIFS('CARDS + MAIL'!$I$6:$I$155,'CARDS + MAIL'!$H$6:$H$155,$D12)+SUMIFS('DONATIONS + GIVING'!$G$6:$G$65,'DONATIONS + GIVING'!$F$6:$F$65,$D12)+SUMIFS('GIFT PLANNER'!$Q$6:$Q$205,'GIFT PLANNER'!$G$6:$G$205,$D12)+SUMIFS('STOCKING STUFFERS'!$J$6:$J$155,'STOCKING STUFFERS'!$F$6:$F$155,$D12)+SUMIFS('CHRISTMAS CALENDAR'!$K$6:$K$205,'CHRISTMAS CALENDAR'!$J$6:$J$205,$D12)+SUMIFS('DECOR INVENTORY'!$P$6:$P$105,'DECOR INVENTORY'!$O$6:$O$105,$D12)+SUMIFS('DECORATING PLAN'!$H$6:$H$65,'DECORATING PLAN'!$G$6:$G$65,$D12)+SUMIFS('TABLESCAPE + FLORALS'!$R$6:$R$65,'TABLESCAPE + FLORALS'!$Q$6:$Q$65,$D12)+SUMIFS('TRAVEL PLAN'!$M$6:$M$45,'TRAVEL PLAN'!$L$6:$L$45,$D12)+SUMIFS('VENDORS + APPOINTMENTS'!$M$6:$M$65,'VENDORS + APPOINTMENTS'!$L$6:$L$65,$D12)+SUMIFS('EVENTS + WARDROBE'!$N$6:$N$65,'EVENTS + WARDROBE'!$M$6:$M$65,$D12)+SUMIFS('GROCERY LIST'!$L$6:$L$205,'GROCERY LIST'!$K$6:$K$205,$D12)+SUMIFS('MEAL + BAKING PLAN'!$Q$6:$Q$155,'MEAL + BAKING PLAN'!$P$6:$P$155,$D12)+SUMIFS('TRADITIONS + BUCKET LIST'!$I$6:$I$85,'TRADITIONS + BUCKET LIST'!$H$6:$H$85,$D12)) | G12: =IF($D12="","",SUMIFS('CARDS + MAIL'!$J$6:$J$155,'CARDS + MAIL'!$H$6:$H$155,$D12)+SUMIFS('DONATIONS + GIVING'!$H$6:$H$65,'DONATIONS + GIVING'!$F$6:$F$65,$D12)+SUMIFS('GIFT PLANNER'!$R$6:$R$205,'GIFT PLANNER'!$G$6:$G$205,$D12)+SUMIFS('STOCKING STUFFERS'!$K$6:$K$155,'STOCKING STUFFERS'!$F$6:$F$155,$D12)+SUMIFS('CHRISTMAS CALENDAR'!$L$6:$L$205,'CHRISTMAS CALENDAR'!$J$6:$J$205,$D12)+SUMIFS('DECOR INVENTORY'!$Q$6:$Q$105,'DECOR INVENTORY'!$O$6:$O$105,$D12)+SUMIFS('DECORATING PLAN'!$I$6:$I$65,'DECORATING PLAN'!$G$6:$G$65,$D12)+SUMIFS('TABLESCAPE + FLORALS'!$S$6:$S$65,'TABLESCAPE + FLORALS'!$Q$6:$Q$65,$D12)+SUMIFS('TRAVEL PLAN'!$N$6:$N$45,'TRAVEL PLAN'!$L$6:$L$45,$D12)+SUMIFS('VENDORS + APPOINTMENTS'!$Q$6:$Q$65,'VENDORS + APPOINTMENTS'!$L$6:$L$65,$D12)+SUMIFS('EVENTS + WARDROBE'!$O$6:$O$65,'EVENTS + WARDROBE'!$M$6:$M$65,$D12)+SUMIFS('GROCERY LIST'!$M$6:$M$205,'GROCERY LIST'!$K$6:$K$205,$D12)+SUMIFS('MEAL + BAKING PLAN'!$R$6:$R$155,'MEAL + BAKING PLAN'!$P$6:$P$155,$D12)+SUMIFS('TRADITIONS + BUCKET LIST'!$J$6:$J$85,'TRADITIONS + BUCKET LIST'!$H$6:$H$85,$D12)-SUMIFS('RETURNS + EXCHANGES'!$R$6:$R$65,'RETURNS + EXCHANGES'!$K$6:$K$65,$D12)) | H12: =IF($D12="","",$E12-$G12) | I12: =IF($D12="","",IF($E12=0,0,$G12/$E12)) | J12: =IF($D12="","",IF(AND($E12=0,$G12=0),"NOT SET",IF($G12>$E12,"OVER BUDGET",IF($G12=$E12,"AT BUDGET",IF(AND($E12>0,$G12/$E12>=Set_WarnThreshold),"NEAR LIMIT","ON TRACK"))))) | K12: EXAMPLE FIGURE — type your own over it | L12: =IF(AND($C12="Yes",$D12<>"",OR(N($E12)>0,N($G12)>0)),$E12+(100-ROW())/10000,"") | M12: =IF($B12="",0,IF(COUNTIF('MASTER BUDGET'!$B$6:$B$25,$B12)>1,1,0))
B13: B-008 | C13: Yes | D13: Travel | E13: 1200 | F13: =IF($D13="","",SUMIFS('CARDS + MAIL'!$I$6:$I$155,'CARDS + MAIL'!$H$6:$H$155,$D13)+SUMIFS('DONATIONS + GIVING'!$G$6:$G$65,'DONATIONS + GIVING'!$F$6:$F$65,$D13)+SUMIFS('GIFT PLANNER'!$Q$6:$Q$205,'GIFT PLANNER'!$G$6:$G$205,$D13)+SUMIFS('STOCKING STUFFERS'!$J$6:$J$155,'STOCKING STUFFERS'!$F$6:$F$155,$D13)+SUMIFS('CHRISTMAS CALENDAR'!$K$6:$K$205,'CHRISTMAS CALENDAR'!$J$6:$J$205,$D13)+SUMIFS('DECOR INVENTORY'!$P$6:$P$105,'DECOR INVENTORY'!$O$6:$O$105,$D13)+SUMIFS('DECORATING PLAN'!$H$6:$H$65,'DECORATING PLAN'!$G$6:$G$65,$D13)+SUMIFS('TABLESCAPE + FLORALS'!$R$6:$R$65,'TABLESCAPE + FLORALS'!$Q$6:$Q$65,$D13)+SUMIFS('TRAVEL PLAN'!$M$6:$M$45,'TRAVEL PLAN'!$L$6:$L$45,$D13)+SUMIFS('VENDORS + APPOINTMENTS'!$M$6:$M$65,'VENDORS + APPOINTMENTS'!$L$6:$L$65,$D13)+SUMIFS('EVENTS + WARDROBE'!$N$6:$N$65,'EVENTS + WARDROBE'!$M$6:$M$65,$D13)+SUMIFS('GROCERY LIST'!$L$6:$L$205,'GROCERY LIST'!$K$6:$K$205,$D13)+SUMIFS('MEAL + BAKING PLAN'!$Q$6:$Q$155,'MEAL + BAKING PLAN'!$P$6:$P$155,$D13)+SUMIFS('TRADITIONS + BUCKET LIST'!$I$6:$I$85,'TRADITIONS + BUCKET LIST'!$H$6:$H$85,$D13)) | G13: =IF($D13="","",SUMIFS('CARDS + MAIL'!$J$6:$J$155,'CARDS + MAIL'!$H$6:$H$155,$D13)+SUMIFS('DONATIONS + GIVING'!$H$6:$H$65,'DONATIONS + GIVING'!$F$6:$F$65,$D13)+SUMIFS('GIFT PLANNER'!$R$6:$R$205,'GIFT PLANNER'!$G$6:$G$205,$D13)+SUMIFS('STOCKING STUFFERS'!$K$6:$K$155,'STOCKING STUFFERS'!$F$6:$F$155,$D13)+SUMIFS('CHRISTMAS CALENDAR'!$L$6:$L$205,'CHRISTMAS CALENDAR'!$J$6:$J$205,$D13)+SUMIFS('DECOR INVENTORY'!$Q$6:$Q$105,'DECOR INVENTORY'!$O$6:$O$105,$D13)+SUMIFS('DECORATING PLAN'!$I$6:$I$65,'DECORATING PLAN'!$G$6:$G$65,$D13)+SUMIFS('TABLESCAPE + FLORALS'!$S$6:$S$65,'TABLESCAPE + FLORALS'!$Q$6:$Q$65,$D13)+SUMIFS('TRAVEL PLAN'!$N$6:$N$45,'TRAVEL PLAN'!$L$6:$L$45,$D13)+SUMIFS('VENDORS + APPOINTMENTS'!$Q$6:$Q$65,'VENDORS + APPOINTMENTS'!$L$6:$L$65,$D13)+SUMIFS('EVENTS + WARDROBE'!$O$6:$O$65,'EVENTS + WARDROBE'!$M$6:$M$65,$D13)+SUMIFS('GROCERY LIST'!$M$6:$M$205,'GROCERY LIST'!$K$6:$K$205,$D13)+SUMIFS('MEAL + BAKING PLAN'!$R$6:$R$155,'MEAL + BAKING PLAN'!$P$6:$P$155,$D13)+SUMIFS('TRADITIONS + BUCKET LIST'!$J$6:$J$85,'TRADITIONS + BUCKET LIST'!$H$6:$H$85,$D13)-SUMIFS('RETURNS + EXCHANGES'!$R$6:$R$65,'RETURNS + EXCHANGES'!$K$6:$K$65,$D13)) | H13: =IF($D13="","",$E13-$G13) | I13: =IF($D13="","",IF($E13=0,0,$G13/$E13)) | J13: =IF($D13="","",IF(AND($E13=0,$G13=0),"NOT SET",IF($G13>$E13,"OVER BUDGET",IF($G13=$E13,"AT BUDGET",IF(AND($E13>0,$G13/$E13>=Set_WarnThreshold),"NEAR LIMIT","ON TRACK"))))) | K13: EXAMPLE FIGURE — type your own over it | L13: =IF(AND($C13="Yes",$D13<>"",OR(N($E13)>0,N($G13)>0)),$E13+(100-ROW())/10000,"") | M13: =IF($B13="",0,IF(COUNTIF('MASTER BUDGET'!$B$6:$B$25,$B13)>1,1,0))
B14: B-009 | C14: Yes | D14: Donations | E14: 500 | F14: =IF($D14="","",SUMIFS('CARDS + MAIL'!$I$6:$I$155,'CARDS + MAIL'!$H$6:$H$155,$D14)+SUMIFS('DONATIONS + GIVING'!$G$6:$G$65,'DONATIONS + GIVING'!$F$6:$F$65,$D14)+SUMIFS('GIFT PLANNER'!$Q$6:$Q$205,'GIFT PLANNER'!$G$6:$G$205,$D14)+SUMIFS('STOCKING STUFFERS'!$J$6:$J$155,'STOCKING STUFFERS'!$F$6:$F$155,$D14)+SUMIFS('CHRISTMAS CALENDAR'!$K$6:$K$205,'CHRISTMAS CALENDAR'!$J$6:$J$205,$D14)+SUMIFS('DECOR INVENTORY'!$P$6:$P$105,'DECOR INVENTORY'!$O$6:$O$105,$D14)+SUMIFS('DECORATING PLAN'!$H$6:$H$65,'DECORATING PLAN'!$G$6:$G$65,$D14)+SUMIFS('TABLESCAPE + FLORALS'!$R$6:$R$65,'TABLESCAPE + FLORALS'!$Q$6:$Q$65,$D14)+SUMIFS('TRAVEL PLAN'!$M$6:$M$45,'TRAVEL PLAN'!$L$6:$L$45,$D14)+SUMIFS('VENDORS + APPOINTMENTS'!$M$6:$M$65,'VENDORS + APPOINTMENTS'!$L$6:$L$65,$D14)+SUMIFS('EVENTS + WARDROBE'!$N$6:$N$65,'EVENTS + WARDROBE'!$M$6:$M$65,$D14)+SUMIFS('GROCERY LIST'!$L$6:$L$205,'GROCERY LIST'!$K$6:$K$205,$D14)+SUMIFS('MEAL + BAKING PLAN'!$Q$6:$Q$155,'MEAL + BAKING PLAN'!$P$6:$P$155,$D14)+SUMIFS('TRADITIONS + BUCKET LIST'!$I$6:$I$85,'TRADITIONS + BUCKET LIST'!$H$6:$H$85,$D14)) | G14: =IF($D14="","",SUMIFS('CARDS + MAIL'!$J$6:$J$155,'CARDS + MAIL'!$H$6:$H$155,$D14)+SUMIFS('DONATIONS + GIVING'!$H$6:$H$65,'DONATIONS + GIVING'!$F$6:$F$65,$D14)+SUMIFS('GIFT PLANNER'!$R$6:$R$205,'GIFT PLANNER'!$G$6:$G$205,$D14)+SUMIFS('STOCKING STUFFERS'!$K$6:$K$155,'STOCKING STUFFERS'!$F$6:$F$155,$D14)+SUMIFS('CHRISTMAS CALENDAR'!$L$6:$L$205,'CHRISTMAS CALENDAR'!$J$6:$J$205,$D14)+SUMIFS('DECOR INVENTORY'!$Q$6:$Q$105,'DECOR INVENTORY'!$O$6:$O$105,$D14)+SUMIFS('DECORATING PLAN'!$I$6:$I$65,'DECORATING PLAN'!$G$6:$G$65,$D14)+SUMIFS('TABLESCAPE + FLORALS'!$S$6:$S$65,'TABLESCAPE + FLORALS'!$Q$6:$Q$65,$D14)+SUMIFS('TRAVEL PLAN'!$N$6:$N$45,'TRAVEL PLAN'!$L$6:$L$45,$D14)+SUMIFS('VENDORS + APPOINTMENTS'!$Q$6:$Q$65,'VENDORS + APPOINTMENTS'!$L$6:$L$65,$D14)+SUMIFS('EVENTS + WARDROBE'!$O$6:$O$65,'EVENTS + WARDROBE'!$M$6:$M$65,$D14)+SUMIFS('GROCERY LIST'!$M$6:$M$205,'GROCERY LIST'!$K$6:$K$205,$D14)+SUMIFS('MEAL + BAKING PLAN'!$R$6:$R$155,'MEAL + BAKING PLAN'!$P$6:$P$155,$D14)+SUMIFS('TRADITIONS + BUCKET LIST'!$J$6:$J$85,'TRADITIONS + BUCKET LIST'!$H$6:$H$85,$D14)-SUMIFS('RETURNS + EXCHANGES'!$R$6:$R$65,'RETURNS + EXCHANGES'!$K$6:$K$65,$D14)) | H14: =IF($D14="","",$E14-$G14) | I14: =IF($D14="","",IF($E14=0,0,$G14/$E14)) | J14: =IF($D14="","",IF(AND($E14=0,$G14=0),"NOT SET",IF($G14>$E14,"OVER BUDGET",IF($G14=$E14,"AT BUDGET",IF(AND($E14>0,$G14/$E14>=Set_WarnThreshold),"NEAR LIMIT","ON TRACK"))))) | K14: EXAMPLE FIGURE — type your own over it | L14: =IF(AND($C14="Yes",$D14<>"",OR(N($E14)>0,N($G14)>0)),$E14+(100-ROW())/10000,"") | M14: =IF($B14="",0,IF(COUNTIF('MASTER BUDGET'!$B$6:$B$25,$B14)>1,1,0))
B15: B-010 | C15: Yes | D15: Hosting | E15: 1600 | F15: =IF($D15="","",SUMIFS('CARDS + MAIL'!$I$6:$I$155,'CARDS + MAIL'!$H$6:$H$155,$D15)+SUMIFS('DONATIONS + GIVING'!$G$6:$G$65,'DONATIONS + GIVING'!$F$6:$F$65,$D15)+SUMIFS('GIFT PLANNER'!$Q$6:$Q$205,'GIFT PLANNER'!$G$6:$G$205,$D15)+SUMIFS('STOCKING STUFFERS'!$J$6:$J$155,'STOCKING STUFFERS'!$F$6:$F$155,$D15)+SUMIFS('CHRISTMAS CALENDAR'!$K$6:$K$205,'CHRISTMAS CALENDAR'!$J$6:$J$205,$D15)+SUMIFS('DECOR INVENTORY'!$P$6:$P$105,'DECOR INVENTORY'!$O$6:$O$105,$D15)+SUMIFS('DECORATING PLAN'!$H$6:$H$65,'DECORATING PLAN'!$G$6:$G$65,$D15)+SUMIFS('TABLESCAPE + FLORALS'!$R$6:$R$65,'TABLESCAPE + FLORALS'!$Q$6:$Q$65,$D15)+SUMIFS('TRAVEL PLAN'!$M$6:$M$45,'TRAVEL PLAN'!$L$6:$L$45,$D15)+SUMIFS('VENDORS + APPOINTMENTS'!$M$6:$M$65,'VENDORS + APPOINTMENTS'!$L$6:$L$65,$D15)+SUMIFS('EVENTS + WARDROBE'!$N$6:$N$65,'EVENTS + WARDROBE'!$M$6:$M$65,$D15)+SUMIFS('GROCERY LIST'!$L$6:$L$205,'GROCERY LIST'!$K$6:$K$205,$D15)+SUMIFS('MEAL + BAKING PLAN'!$Q$6:$Q$155,'MEAL + BAKING PLAN'!$P$6:$P$155,$D15)+SUMIFS('TRADITIONS + BUCKET LIST'!$I$6:$I$85,'TRADITIONS + BUCKET LIST'!$H$6:$H$85,$D15)) | G15: =IF($D15="","",SUMIFS('CARDS + MAIL'!$J$6:$J$155,'CARDS + MAIL'!$H$6:$H$155,$D15)+SUMIFS('DONATIONS + GIVING'!$H$6:$H$65,'DONATIONS + GIVING'!$F$6:$F$65,$D15)+SUMIFS('GIFT PLANNER'!$R$6:$R$205,'GIFT PLANNER'!$G$6:$G$205,$D15)+SUMIFS('STOCKING STUFFERS'!$K$6:$K$155,'STOCKING STUFFERS'!$F$6:$F$155,$D15)+SUMIFS('CHRISTMAS CALENDAR'!$L$6:$L$205,'CHRISTMAS CALENDAR'!$J$6:$J$205,$D15)+SUMIFS('DECOR INVENTORY'!$Q$6:$Q$105,'DECOR INVENTORY'!$O$6:$O$105,$D15)+SUMIFS('DECORATING PLAN'!$I$6:$I$65,'DECORATING PLAN'!$G$6:$G$65,$D15)+SUMIFS('TABLESCAPE + FLORALS'!$S$6:$S$65,'TABLESCAPE + FLORALS'!$Q$6:$Q$65,$D15)+SUMIFS('TRAVEL PLAN'!$N$6:$N$45,'TRAVEL PLAN'!$L$6:$L$45,$D15)+SUMIFS('VENDORS + APPOINTMENTS'!$Q$6:$Q$65,'VENDORS + APPOINTMENTS'!$L$6:$L$65,$D15)+SUMIFS('EVENTS + WARDROBE'!$O$6:$O$65,'EVENTS + WARDROBE'!$M$6:$M$65,$D15)+SUMIFS('GROCERY LIST'!$M$6:$M$205,'GROCERY LIST'!$K$6:$K$205,$D15)+SUMIFS('MEAL + BAKING PLAN'!$R$6:$R$155,'MEAL + BAKING PLAN'!$P$6:$P$155,$D15)+SUMIFS('TRADITIONS + BUCKET LIST'!$J$6:$J$85,'TRADITIONS + BUCKET LIST'!$H$6:$H$85,$D15)-SUMIFS('RETURNS + EXCHANGES'!$R$6:$R$65,'RETURNS + EXCHANGES'!$K$6:$K$65,$D15)) | H15: =IF($D15="","",$E15-$G15) | I15: =IF($D15="","",IF($E15=0,0,$G15/$E15)) | J15: =IF($D15="","",IF(AND($E15=0,$G15=0),"NOT SET",IF($G15>$E15,"OVER BUDGET",IF($G15=$E15,"AT BUDGET",IF(AND($E15>0,$G15/$E15>=Set_WarnThreshold),"NEAR LIMIT","ON TRACK"))))) | K15: EXAMPLE FIGURE — type your own over it | L15: =IF(AND($C15="Yes",$D15<>"",OR(N($E15)>0,N($G15)>0)),$E15+(100-ROW())/10000,"") | M15: =IF($B15="",0,IF(COUNTIF('MASTER BUDGET'!$B$6:$B$25,$B15)>1,1,0))
B16: B-011 | C16: Yes | D16: Photography | E16: 850 | F16: =IF($D16="","",SUMIFS('CARDS + MAIL'!$I$6:$I$155,'CARDS + MAIL'!$H$6:$H$155,$D16)+SUMIFS('DONATIONS + GIVING'!$G$6:$G$65,'DONATIONS + GIVING'!$F$6:$F$65,$D16)+SUMIFS('GIFT PLANNER'!$Q$6:$Q$205,'GIFT PLANNER'!$G$6:$G$205,$D16)+SUMIFS('STOCKING STUFFERS'!$J$6:$J$155,'STOCKING STUFFERS'!$F$6:$F$155,$D16)+SUMIFS('CHRISTMAS CALENDAR'!$K$6:$K$205,'CHRISTMAS CALENDAR'!$J$6:$J$205,$D16)+SUMIFS('DECOR INVENTORY'!$P$6:$P$105,'DECOR INVENTORY'!$O$6:$O$105,$D16)+SUMIFS('DECORATING PLAN'!$H$6:$H$65,'DECORATING PLAN'!$G$6:$G$65,$D16)+SUMIFS('TABLESCAPE + FLORALS'!$R$6:$R$65,'TABLESCAPE + FLORALS'!$Q$6:$Q$65,$D16)+SUMIFS('TRAVEL PLAN'!$M$6:$M$45,'TRAVEL PLAN'!$L$6:$L$45,$D16)+SUMIFS('VENDORS + APPOINTMENTS'!$M$6:$M$65,'VENDORS + APPOINTMENTS'!$L$6:$L$65,$D16)+SUMIFS('EVENTS + WARDROBE'!$N$6:$N$65,'EVENTS + WARDROBE'!$M$6:$M$65,$D16)+SUMIFS('GROCERY LIST'!$L$6:$L$205,'GROCERY LIST'!$K$6:$K$205,$D16)+SUMIFS('MEAL + BAKING PLAN'!$Q$6:$Q$155,'MEAL + BAKING PLAN'!$P$6:$P$155,$D16)+SUMIFS('TRADITIONS + BUCKET LIST'!$I$6:$I$85,'TRADITIONS + BUCKET LIST'!$H$6:$H$85,$D16)) | G16: =IF($D16="","",SUMIFS('CARDS + MAIL'!$J$6:$J$155,'CARDS + MAIL'!$H$6:$H$155,$D16)+SUMIFS('DONATIONS + GIVING'!$H$6:$H$65,'DONATIONS + GIVING'!$F$6:$F$65,$D16)+SUMIFS('GIFT PLANNER'!$R$6:$R$205,'GIFT PLANNER'!$G$6:$G$205,$D16)+SUMIFS('STOCKING STUFFERS'!$K$6:$K$155,'STOCKING STUFFERS'!$F$6:$F$155,$D16)+SUMIFS('CHRISTMAS CALENDAR'!$L$6:$L$205,'CHRISTMAS CALENDAR'!$J$6:$J$205,$D16)+SUMIFS('DECOR INVENTORY'!$Q$6:$Q$105,'DECOR INVENTORY'!$O$6:$O$105,$D16)+SUMIFS('DECORATING PLAN'!$I$6:$I$65,'DECORATING PLAN'!$G$6:$G$65,$D16)+SUMIFS('TABLESCAPE + FLORALS'!$S$6:$S$65,'TABLESCAPE + FLORALS'!$Q$6:$Q$65,$D16)+SUMIFS('TRAVEL PLAN'!$N$6:$N$45,'TRAVEL PLAN'!$L$6:$L$45,$D16)+SUMIFS('VENDORS + APPOINTMENTS'!$Q$6:$Q$65,'VENDORS + APPOINTMENTS'!$L$6:$L$65,$D16)+SUMIFS('EVENTS + WARDROBE'!$O$6:$O$65,'EVENTS + WARDROBE'!$M$6:$M$65,$D16)+SUMIFS('GROCERY LIST'!$M$6:$M$205,'GROCERY LIST'!$K$6:$K$205,$D16)+SUMIFS('MEAL + BAKING PLAN'!$R$6:$R$155,'MEAL + BAKING PLAN'!$P$6:$P$155,$D16)+SUMIFS('TRADITIONS + BUCKET LIST'!$J$6:$J$85,'TRADITIONS + BUCKET LIST'!$H$6:$H$85,$D16)-SUMIFS('RETURNS + EXCHANGES'!$R$6:$R$65,'RETURNS + EXCHANGES'!$K$6:$K$65,$D16)) | H16: =IF($D16="","",$E16-$G16) | I16: =IF($D16="","",IF($E16=0,0,$G16/$E16)) | J16: =IF($D16="","",IF(AND($E16=0,$G16=0),"NOT SET",IF($G16>$E16,"OVER BUDGET",IF($G16=$E16,"AT BUDGET",IF(AND($E16>0,$G16/$E16>=Set_WarnThreshold),"NEAR LIMIT","ON TRACK"))))) | K16: EXAMPLE FIGURE — type your own over it | L16: =IF(AND($C16="Yes",$D16<>"",OR(N($E16)>0,N($G16)>0)),$E16+(100-ROW())/10000,"") | M16: =IF($B16="",0,IF(COUNTIF('MASTER BUDGET'!$B$6:$B$25,$B16)>1,1,0))
B17: B-012 | C17: Yes | D17: Other | E17: 200 | F17: =IF($D17="","",SUMIFS('CARDS + MAIL'!$I$6:$I$155,'CARDS + MAIL'!$H$6:$H$155,$D17)+SUMIFS('DONATIONS + GIVING'!$G$6:$G$65,'DONATIONS + GIVING'!$F$6:$F$65,$D17)+SUMIFS('GIFT PLANNER'!$Q$6:$Q$205,'GIFT PLANNER'!$G$6:$G$205,$D17)+SUMIFS('STOCKING STUFFERS'!$J$6:$J$155,'STOCKING STUFFERS'!$F$6:$F$155,$D17)+SUMIFS('CHRISTMAS CALENDAR'!$K$6:$K$205,'CHRISTMAS CALENDAR'!$J$6:$J$205,$D17)+SUMIFS('DECOR INVENTORY'!$P$6:$P$105,'DECOR INVENTORY'!$O$6:$O$105,$D17)+SUMIFS('DECORATING PLAN'!$H$6:$H$65,'DECORATING PLAN'!$G$6:$G$65,$D17)+SUMIFS('TABLESCAPE + FLORALS'!$R$6:$R$65,'TABLESCAPE + FLORALS'!$Q$6:$Q$65,$D17)+SUMIFS('TRAVEL PLAN'!$M$6:$M$45,'TRAVEL PLAN'!$L$6:$L$45,$D17)+SUMIFS('VENDORS + APPOINTMENTS'!$M$6:$M$65,'VENDORS + APPOINTMENTS'!$L$6:$L$65,$D17)+SUMIFS('EVENTS + WARDROBE'!$N$6:$N$65,'EVENTS + WARDROBE'!$M$6:$M$65,$D17)+SUMIFS('GROCERY LIST'!$L$6:$L$205,'GROCERY LIST'!$K$6:$K$205,$D17)+SUMIFS('MEAL + BAKING PLAN'!$Q$6:$Q$155,'MEAL + BAKING PLAN'!$P$6:$P$155,$D17)+SUMIFS('TRADITIONS + BUCKET LIST'!$I$6:$I$85,'TRADITIONS + BUCKET LIST'!$H$6:$H$85,$D17)) | G17: =IF($D17="","",SUMIFS('CARDS + MAIL'!$J$6:$J$155,'CARDS + MAIL'!$H$6:$H$155,$D17)+SUMIFS('DONATIONS + GIVING'!$H$6:$H$65,'DONATIONS + GIVING'!$F$6:$F$65,$D17)+SUMIFS('GIFT PLANNER'!$R$6:$R$205,'GIFT PLANNER'!$G$6:$G$205,$D17)+SUMIFS('STOCKING STUFFERS'!$K$6:$K$155,'STOCKING STUFFERS'!$F$6:$F$155,$D17)+SUMIFS('CHRISTMAS CALENDAR'!$L$6:$L$205,'CHRISTMAS CALENDAR'!$J$6:$J$205,$D17)+SUMIFS('DECOR INVENTORY'!$Q$6:$Q$105,'DECOR INVENTORY'!$O$6:$O$105,$D17)+SUMIFS('DECORATING PLAN'!$I$6:$I$65,'DECORATING PLAN'!$G$6:$G$65,$D17)+SUMIFS('TABLESCAPE + FLORALS'!$S$6:$S$65,'TABLESCAPE + FLORALS'!$Q$6:$Q$65,$D17)+SUMIFS('TRAVEL PLAN'!$N$6:$N$45,'TRAVEL PLAN'!$L$6:$L$45,$D17)+SUMIFS('VENDORS + APPOINTMENTS'!$Q$6:$Q$65,'VENDORS + APPOINTMENTS'!$L$6:$L$65,$D17)+SUMIFS('EVENTS + WARDROBE'!$O$6:$O$65,'EVENTS + WARDROBE'!$M$6:$M$65,$D17)+SUMIFS('GROCERY LIST'!$M$6:$M$205,'GROCERY LIST'!$K$6:$K$205,$D17)+SUMIFS('MEAL + BAKING PLAN'!$R$6:$R$155,'MEAL + BAKING PLAN'!$P$6:$P$155,$D17)+SUMIFS('TRADITIONS + BUCKET LIST'!$J$6:$J$85,'TRADITIONS + BUCKET LIST'!$H$6:$H$85,$D17)-SUMIFS('RETURNS + EXCHANGES'!$R$6:$R$65,'RETURNS + EXCHANGES'!$K$6:$K$65,$D17)) | H17: =IF($D17="","",$E17-$G17) | I17: =IF($D17="","",IF($E17=0,0,$G17/$E17)) | J17: =IF($D17="","",IF(AND($E17=0,$G17=0),"NOT SET",IF($G17>$E17,"OVER BUDGET",IF($G17=$E17,"AT BUDGET",IF(AND($E17>0,$G17/$E17>=Set_WarnThreshold),"NEAR LIMIT","ON TRACK"))))) | K17: EXAMPLE FIGURE — type your own over it | L17: =IF(AND($C17="Yes",$D17<>"",OR(N($E17)>0,N($G17)>0)),$E17+(100-ROW())/10000,"") | M17: =IF($B17="",0,IF(COUNTIF('MASTER BUDGET'!$B$6:$B$25,$B17)>1,1,0))
F18: =IF($D18="","",SUMIFS('CARDS + MAIL'!$I$6:$I$155,'CARDS + MAIL'!$H$6:$H$155,$D18)+SUMIFS('DONATIONS + GIVING'!$G$6:$G$65,'DONATIONS + GIVING'!$F$6:$F$65,$D18)+SUMIFS('GIFT PLANNER'!$Q$6:$Q$205,'GIFT PLANNER'!$G$6:$G$205,$D18)+SUMIFS('STOCKING STUFFERS'!$J$6:$J$155,'STOCKING STUFFERS'!$F$6:$F$155,$D18)+SUMIFS('CHRISTMAS CALENDAR'!$K$6:$K$205,'CHRISTMAS CALENDAR'!$J$6:$J$205,$D18)+SUMIFS('DECOR INVENTORY'!$P$6:$P$105,'DECOR INVENTORY'!$O$6:$O$105,$D18)+SUMIFS('DECORATING PLAN'!$H$6:$H$65,'DECORATING PLAN'!$G$6:$G$65,$D18)+SUMIFS('TABLESCAPE + FLORALS'!$R$6:$R$65,'TABLESCAPE + FLORALS'!$Q$6:$Q$65,$D18)+SUMIFS('TRAVEL PLAN'!$M$6:$M$45,'TRAVEL PLAN'!$L$6:$L$45,$D18)+SUMIFS('VENDORS + APPOINTMENTS'!$M$6:$M$65,'VENDORS + APPOINTMENTS'!$L$6:$L$65,$D18)+SUMIFS('EVENTS + WARDROBE'!$N$6:$N$65,'EVENTS + WARDROBE'!$M$6:$M$65,$D18)+SUMIFS('GROCERY LIST'!$L$6:$L$205,'GROCERY LIST'!$K$6:$K$205,$D18)+SUMIFS('MEAL + BAKING PLAN'!$Q$6:$Q$155,'MEAL + BAKING PLAN'!$P$6:$P$155,$D18)+SUMIFS('TRADITIONS + BUCKET LIST'!$I$6:$I$85,'TRADITIONS + BUCKET LIST'!$H$6:$H$85,$D18)) | G18: =IF($D18="","",SUMIFS('CARDS + MAIL'!$J$6:$J$155,'CARDS + MAIL'!$H$6:$H$155,$D18)+SUMIFS('DONATIONS + GIVING'!$H$6:$H$65,'DONATIONS + GIVING'!$F$6:$F$65,$D18)+SUMIFS('GIFT PLANNER'!$R$6:$R$205,'GIFT PLANNER'!$G$6:$G$205,$D18)+SUMIFS('STOCKING STUFFERS'!$K$6:$K$155,'STOCKING STUFFERS'!$F$6:$F$155,$D18)+SUMIFS('CHRISTMAS CALENDAR'!$L$6:$L$205,'CHRISTMAS CALENDAR'!$J$6:$J$205,$D18)+SUMIFS('DECOR INVENTORY'!$Q$6:$Q$105,'DECOR INVENTORY'!$O$6:$O$105,$D18)+SUMIFS('DECORATING PLAN'!$I$6:$I$65,'DECORATING PLAN'!$G$6:$G$65,$D18)+SUMIFS('TABLESCAPE + FLORALS'!$S$6:$S$65,'TABLESCAPE + FLORALS'!$Q$6:$Q$65,$D18)+SUMIFS('TRAVEL PLAN'!$N$6:$N$45,'TRAVEL PLAN'!$L$6:$L$45,$D18)+SUMIFS('VENDORS + APPOINTMENTS'!$Q$6:$Q$65,'VENDORS + APPOINTMENTS'!$L$6:$L$65,$D18)+SUMIFS('EVENTS + WARDROBE'!$O$6:$O$65,'EVENTS + WARDROBE'!$M$6:$M$65,$D18)+SUMIFS('GROCERY LIST'!$M$6:$M$205,'GROCERY LIST'!$K$6:$K$205,$D18)+SUMIFS('MEAL + BAKING PLAN'!$R$6:$R$155,'MEAL + BAKING PLAN'!$P$6:$P$155,$D18)+SUMIFS('TRADITIONS + BUCKET LIST'!$J$6:$J$85,'TRADITIONS + BUCKET LIST'!$H$6:$H$85,$D18)-SUMIFS('RETURNS + EXCHANGES'!$R$6:$R$65,'RETURNS + EXCHANGES'!$K$6:$K$65,$D18)) | H18: =IF($D18="","",$E18-$G18) | I18: =IF($D18="","",IF($E18=0,0,$G18/$E18)) | J18: =IF($D18="","",IF(AND($E18=0,$G18=0),"NOT SET",IF($G18>$E18,"OVER BUDGET",IF($G18=$E18,"AT BUDGET",IF(AND($E18>0,$G18/$E18>=Set_WarnThreshold),"NEAR LIMIT","ON TRACK"))))) | L18: =IF(AND($C18="Yes",$D18<>"",OR(N($E18)>0,N($G18)>0)),$E18+(100-ROW())/10000,"") | M18: =IF($B18="",0,IF(COUNTIF('MASTER BUDGET'!$B$6:$B$25,$B18)>1,1,0))
F19: =IF($D19="","",SUMIFS('CARDS + MAIL'!$I$6:$I$155,'CARDS + MAIL'!$H$6:$H$155,$D19)+SUMIFS('DONATIONS + GIVING'!$G$6:$G$65,'DONATIONS + GIVING'!$F$6:$F$65,$D19)+SUMIFS('GIFT PLANNER'!$Q$6:$Q$205,'GIFT PLANNER'!$G$6:$G$205,$D19)+SUMIFS('STOCKING STUFFERS'!$J$6:$J$155,'STOCKING STUFFERS'!$F$6:$F$155,$D19)+SUMIFS('CHRISTMAS CALENDAR'!$K$6:$K$205,'CHRISTMAS CALENDAR'!$J$6:$J$205,$D19)+SUMIFS('DECOR INVENTORY'!$P$6:$P$105,'DECOR INVENTORY'!$O$6:$O$105,$D19)+SUMIFS('DECORATING PLAN'!$H$6:$H$65,'DECORATING PLAN'!$G$6:$G$65,$D19)+SUMIFS('TABLESCAPE + FLORALS'!$R$6:$R$65,'TABLESCAPE + FLORALS'!$Q$6:$Q$65,$D19)+SUMIFS('TRAVEL PLAN'!$M$6:$M$45,'TRAVEL PLAN'!$L$6:$L$45,$D19)+SUMIFS('VENDORS + APPOINTMENTS'!$M$6:$M$65,'VENDORS + APPOINTMENTS'!$L$6:$L$65,$D19)+SUMIFS('EVENTS + WARDROBE'!$N$6:$N$65,'EVENTS + WARDROBE'!$M$6:$M$65,$D19)+SUMIFS('GROCERY LIST'!$L$6:$L$205,'GROCERY LIST'!$K$6:$K$205,$D19)+SUMIFS('MEAL + BAKING PLAN'!$Q$6:$Q$155,'MEAL + BAKING PLAN'!$P$6:$P$155,$D19)+SUMIFS('TRADITIONS + BUCKET LIST'!$I$6:$I$85,'TRADITIONS + BUCKET LIST'!$H$6:$H$85,$D19)) | G19: =IF($D19="","",SUMIFS('CARDS + MAIL'!$J$6:$J$155,'CARDS + MAIL'!$H$6:$H$155,$D19)+SUMIFS('DONATIONS + GIVING'!$H$6:$H$65,'DONATIONS + GIVING'!$F$6:$F$65,$D19)+SUMIFS('GIFT PLANNER'!$R$6:$R$205,'GIFT PLANNER'!$G$6:$G$205,$D19)+SUMIFS('STOCKING STUFFERS'!$K$6:$K$155,'STOCKING STUFFERS'!$F$6:$F$155,$D19)+SUMIFS('CHRISTMAS CALENDAR'!$L$6:$L$205,'CHRISTMAS CALENDAR'!$J$6:$J$205,$D19)+SUMIFS('DECOR INVENTORY'!$Q$6:$Q$105,'DECOR INVENTORY'!$O$6:$O$105,$D19)+SUMIFS('DECORATING PLAN'!$I$6:$I$65,'DECORATING PLAN'!$G$6:$G$65,$D19)+SUMIFS('TABLESCAPE + FLORALS'!$S$6:$S$65,'TABLESCAPE + FLORALS'!$Q$6:$Q$65,$D19)+SUMIFS('TRAVEL PLAN'!$N$6:$N$45,'TRAVEL PLAN'!$L$6:$L$45,$D19)+SUMIFS('VENDORS + APPOINTMENTS'!$Q$6:$Q$65,'VENDORS + APPOINTMENTS'!$L$6:$L$65,$D19)+SUMIFS('EVENTS + WARDROBE'!$O$6:$O$65,'EVENTS + WARDROBE'!$M$6:$M$65,$D19)+SUMIFS('GROCERY LIST'!$M$6:$M$205,'GROCERY LIST'!$K$6:$K$205,$D19)+SUMIFS('MEAL + BAKING PLAN'!$R$6:$R$155,'MEAL + BAKING PLAN'!$P$6:$P$155,$D19)+SUMIFS('TRADITIONS + BUCKET LIST'!$J$6:$J$85,'TRADITIONS + BUCKET LIST'!$H$6:$H$85,$D19)-SUMIFS('RETURNS + EXCHANGES'!$R$6:$R$65,'RETURNS + EXCHANGES'!$K$6:$K$65,$D19)) | H19: =IF($D19="","",$E19-$G19) | I19: =IF($D19="","",IF($E19=0,0,$G19/$E19)) | J19: =IF($D19="","",IF(AND($E19=0,$G19=0),"NOT SET",IF($G19>$E19,"OVER BUDGET",IF($G19=$E19,"AT BUDGET",IF(AND($E19>0,$G19/$E19>=Set_WarnThreshold),"NEAR LIMIT","ON TRACK"))))) | L19: =IF(AND($C19="Yes",$D19<>"",OR(N($E19)>0,N($G19)>0)),$E19+(100-ROW())/10000,"") | M19: =IF($B19="",0,IF(COUNTIF('MASTER BUDGET'!$B$6:$B$25,$B19)>1,1,0))
F20: =IF($D20="","",SUMIFS('CARDS + MAIL'!$I$6:$I$155,'CARDS + MAIL'!$H$6:$H$155,$D20)+SUMIFS('DONATIONS + GIVING'!$G$6:$G$65,'DONATIONS + GIVING'!$F$6:$F$65,$D20)+SUMIFS('GIFT PLANNER'!$Q$6:$Q$205,'GIFT PLANNER'!$G$6:$G$205,$D20)+SUMIFS('STOCKING STUFFERS'!$J$6:$J$155,'STOCKING STUFFERS'!$F$6:$F$155,$D20)+SUMIFS('CHRISTMAS CALENDAR'!$K$6:$K$205,'CHRISTMAS CALENDAR'!$J$6:$J$205,$D20)+SUMIFS('DECOR INVENTORY'!$P$6:$P$105,'DECOR INVENTORY'!$O$6:$O$105,$D20)+SUMIFS('DECORATING PLAN'!$H$6:$H$65,'DECORATING PLAN'!$G$6:$G$65,$D20)+SUMIFS('TABLESCAPE + FLORALS'!$R$6:$R$65,'TABLESCAPE + FLORALS'!$Q$6:$Q$65,$D20)+SUMIFS('TRAVEL PLAN'!$M$6:$M$45,'TRAVEL PLAN'!$L$6:$L$45,$D20)+SUMIFS('VENDORS + APPOINTMENTS'!$M$6:$M$65,'VENDORS + APPOINTMENTS'!$L$6:$L$65,$D20)+SUMIFS('EVENTS + WARDROBE'!$N$6:$N$65,'EVENTS + WARDROBE'!$M$6:$M$65,$D20)+SUMIFS('GROCERY LIST'!$L$6:$L$205,'GROCERY LIST'!$K$6:$K$205,$D20)+SUMIFS('MEAL + BAKING PLAN'!$Q$6:$Q$155,'MEAL + BAKING PLAN'!$P$6:$P$155,$D20)+SUMIFS('TRADITIONS + BUCKET LIST'!$I$6:$I$85,'TRADITIONS + BUCKET LIST'!$H$6:$H$85,$D20)) | G20: =IF($D20="","",SUMIFS('CARDS + MAIL'!$J$6:$J$155,'CARDS + MAIL'!$H$6:$H$155,$D20)+SUMIFS('DONATIONS + GIVING'!$H$6:$H$65,'DONATIONS + GIVING'!$F$6:$F$65,$D20)+SUMIFS('GIFT PLANNER'!$R$6:$R$205,'GIFT PLANNER'!$G$6:$G$205,$D20)+SUMIFS('STOCKING STUFFERS'!$K$6:$K$155,'STOCKING STUFFERS'!$F$6:$F$155,$D20)+SUMIFS('CHRISTMAS CALENDAR'!$L$6:$L$205,'CHRISTMAS CALENDAR'!$J$6:$J$205,$D20)+SUMIFS('DECOR INVENTORY'!$Q$6:$Q$105,'DECOR INVENTORY'!$O$6:$O$105,$D20)+SUMIFS('DECORATING PLAN'!$I$6:$I$65,'DECORATING PLAN'!$G$6:$G$65,$D20)+SUMIFS('TABLESCAPE + FLORALS'!$S$6:$S$65,'TABLESCAPE + FLORALS'!$Q$6:$Q$65,$D20)+SUMIFS('TRAVEL PLAN'!$N$6:$N$45,'TRAVEL PLAN'!$L$6:$L$45,$D20)+SUMIFS('VENDORS + APPOINTMENTS'!$Q$6:$Q$65,'VENDORS + APPOINTMENTS'!$L$6:$L$65,$D20)+SUMIFS('EVENTS + WARDROBE'!$O$6:$O$65,'EVENTS + WARDROBE'!$M$6:$M$65,$D20)+SUMIFS('GROCERY LIST'!$M$6:$M$205,'GROCERY LIST'!$K$6:$K$205,$D20)+SUMIFS('MEAL + BAKING PLAN'!$R$6:$R$155,'MEAL + BAKING PLAN'!$P$6:$P$155,$D20)+SUMIFS('TRADITIONS + BUCKET LIST'!$J$6:$J$85,'TRADITIONS + BUCKET LIST'!$H$6:$H$85,$D20)-SUMIFS('RETURNS + EXCHANGES'!$R$6:$R$65,'RETURNS + EXCHANGES'!$K$6:$K$65,$D20)) | H20: =IF($D20="","",$E20-$G20) | I20: =IF($D20="","",IF($E20=0,0,$G20/$E20)) | J20: =IF($D20="","",IF(AND($E20=0,$G20=0),"NOT SET",IF($G20>$E20,"OVER BUDGET",IF($G20=$E20,"AT BUDGET",IF(AND($E20>0,$G20/$E20>=Set_WarnThreshold),"NEAR LIMIT","ON TRACK"))))) | L20: =IF(AND($C20="Yes",$D20<>"",OR(N($E20)>0,N($G20)>0)),$E20+(100-ROW())/10000,"") | M20: =IF($B20="",0,IF(COUNTIF('MASTER BUDGET'!$B$6:$B$25,$B20)>1,1,0))
F21: =IF($D21="","",SUMIFS('CARDS + MAIL'!$I$6:$I$155,'CARDS + MAIL'!$H$6:$H$155,$D21)+SUMIFS('DONATIONS + GIVING'!$G$6:$G$65,'DONATIONS + GIVING'!$F$6:$F$65,$D21)+SUMIFS('GIFT PLANNER'!$Q$6:$Q$205,'GIFT PLANNER'!$G$6:$G$205,$D21)+SUMIFS('STOCKING STUFFERS'!$J$6:$J$155,'STOCKING STUFFERS'!$F$6:$F$155,$D21)+SUMIFS('CHRISTMAS CALENDAR'!$K$6:$K$205,'CHRISTMAS CALENDAR'!$J$6:$J$205,$D21)+SUMIFS('DECOR INVENTORY'!$P$6:$P$105,'DECOR INVENTORY'!$O$6:$O$105,$D21)+SUMIFS('DECORATING PLAN'!$H$6:$H$65,'DECORATING PLAN'!$G$6:$G$65,$D21)+SUMIFS('TABLESCAPE + FLORALS'!$R$6:$R$65,'TABLESCAPE + FLORALS'!$Q$6:$Q$65,$D21)+SUMIFS('TRAVEL PLAN'!$M$6:$M$45,'TRAVEL PLAN'!$L$6:$L$45,$D21)+SUMIFS('VENDORS + APPOINTMENTS'!$M$6:$M$65,'VENDORS + APPOINTMENTS'!$L$6:$L$65,$D21)+SUMIFS('EVENTS + WARDROBE'!$N$6:$N$65,'EVENTS + WARDROBE'!$M$6:$M$65,$D21)+SUMIFS('GROCERY LIST'!$L$6:$L$205,'GROCERY LIST'!$K$6:$K$205,$D21)+SUMIFS('MEAL + BAKING PLAN'!$Q$6:$Q$155,'MEAL + BAKING PLAN'!$P$6:$P$155,$D21)+SUMIFS('TRADITIONS + BUCKET LIST'!$I$6:$I$85,'TRADITIONS + BUCKET LIST'!$H$6:$H$85,$D21)) | G21: =IF($D21="","",SUMIFS('CARDS + MAIL'!$J$6:$J$155,'CARDS + MAIL'!$H$6:$H$155,$D21)+SUMIFS('DONATIONS + GIVING'!$H$6:$H$65,'DONATIONS + GIVING'!$F$6:$F$65,$D21)+SUMIFS('GIFT PLANNER'!$R$6:$R$205,'GIFT PLANNER'!$G$6:$G$205,$D21)+SUMIFS('STOCKING STUFFERS'!$K$6:$K$155,'STOCKING STUFFERS'!$F$6:$F$155,$D21)+SUMIFS('CHRISTMAS CALENDAR'!$L$6:$L$205,'CHRISTMAS CALENDAR'!$J$6:$J$205,$D21)+SUMIFS('DECOR INVENTORY'!$Q$6:$Q$105,'DECOR INVENTORY'!$O$6:$O$105,$D21)+SUMIFS('DECORATING PLAN'!$I$6:$I$65,'DECORATING PLAN'!$G$6:$G$65,$D21)+SUMIFS('TABLESCAPE + FLORALS'!$S$6:$S$65,'TABLESCAPE + FLORALS'!$Q$6:$Q$65,$D21)+SUMIFS('TRAVEL PLAN'!$N$6:$N$45,'TRAVEL PLAN'!$L$6:$L$45,$D21)+SUMIFS('VENDORS + APPOINTMENTS'!$Q$6:$Q$65,'VENDORS + APPOINTMENTS'!$L$6:$L$65,$D21)+SUMIFS('EVENTS + WARDROBE'!$O$6:$O$65,'EVENTS + WARDROBE'!$M$6:$M$65,$D21)+SUMIFS('GROCERY LIST'!$M$6:$M$205,'GROCERY LIST'!$K$6:$K$205,$D21)+SUMIFS('MEAL + BAKING PLAN'!$R$6:$R$155,'MEAL + BAKING PLAN'!$P$6:$P$155,$D21)+SUMIFS('TRADITIONS + BUCKET LIST'!$J$6:$J$85,'TRADITIONS + BUCKET LIST'!$H$6:$H$85,$D21)-SUMIFS('RETURNS + EXCHANGES'!$R$6:$R$65,'RETURNS + EXCHANGES'!$K$6:$K$65,$D21)) | H21: =IF($D21="","",$E21-$G21) | I21: =IF($D21="","",IF($E21=0,0,$G21/$E21)) | J21: =IF($D21="","",IF(AND($E21=0,$G21=0),"NOT SET",IF($G21>$E21,"OVER BUDGET",IF($G21=$E21,"AT BUDGET",IF(AND($E21>0,$G21/$E21>=Set_WarnThreshold),"NEAR LIMIT","ON TRACK"))))) | L21: =IF(AND($C21="Yes",$D21<>"",OR(N($E21)>0,N($G21)>0)),$E21+(100-ROW())/10000,"") | M21: =IF($B21="",0,IF(COUNTIF('MASTER BUDGET'!$B$6:$B$25,$B21)>1,1,0))
F22: =IF($D22="","",SUMIFS('CARDS + MAIL'!$I$6:$I$155,'CARDS + MAIL'!$H$6:$H$155,$D22)+SUMIFS('DONATIONS + GIVING'!$G$6:$G$65,'DONATIONS + GIVING'!$F$6:$F$65,$D22)+SUMIFS('GIFT PLANNER'!$Q$6:$Q$205,'GIFT PLANNER'!$G$6:$G$205,$D22)+SUMIFS('STOCKING STUFFERS'!$J$6:$J$155,'STOCKING STUFFERS'!$F$6:$F$155,$D22)+SUMIFS('CHRISTMAS CALENDAR'!$K$6:$K$205,'CHRISTMAS CALENDAR'!$J$6:$J$205,$D22)+SUMIFS('DECOR INVENTORY'!$P$6:$P$105,'DECOR INVENTORY'!$O$6:$O$105,$D22)+SUMIFS('DECORATING PLAN'!$H$6:$H$65,'DECORATING PLAN'!$G$6:$G$65,$D22)+SUMIFS('TABLESCAPE + FLORALS'!$R$6:$R$65,'TABLESCAPE + FLORALS'!$Q$6:$Q$65,$D22)+SUMIFS('TRAVEL PLAN'!$M$6:$M$45,'TRAVEL PLAN'!$L$6:$L$45,$D22)+SUMIFS('VENDORS + APPOINTMENTS'!$M$6:$M$65,'VENDORS + APPOINTMENTS'!$L$6:$L$65,$D22)+SUMIFS('EVENTS + WARDROBE'!$N$6:$N$65,'EVENTS + WARDROBE'!$M$6:$M$65,$D22)+SUMIFS('GROCERY LIST'!$L$6:$L$205,'GROCERY LIST'!$K$6:$K$205,$D22)+SUMIFS('MEAL + BAKING PLAN'!$Q$6:$Q$155,'MEAL + BAKING PLAN'!$P$6:$P$155,$D22)+SUMIFS('TRADITIONS + BUCKET LIST'!$I$6:$I$85,'TRADITIONS + BUCKET LIST'!$H$6:$H$85,$D22)) | G22: =IF($D22="","",SUMIFS('CARDS + MAIL'!$J$6:$J$155,'CARDS + MAIL'!$H$6:$H$155,$D22)+SUMIFS('DONATIONS + GIVING'!$H$6:$H$65,'DONATIONS + GIVING'!$F$6:$F$65,$D22)+SUMIFS('GIFT PLANNER'!$R$6:$R$205,'GIFT PLANNER'!$G$6:$G$205,$D22)+SUMIFS('STOCKING STUFFERS'!$K$6:$K$155,'STOCKING STUFFERS'!$F$6:$F$155,$D22)+SUMIFS('CHRISTMAS CALENDAR'!$L$6:$L$205,'CHRISTMAS CALENDAR'!$J$6:$J$205,$D22)+SUMIFS('DECOR INVENTORY'!$Q$6:$Q$105,'DECOR INVENTORY'!$O$6:$O$105,$D22)+SUMIFS('DECORATING PLAN'!$I$6:$I$65,'DECORATING PLAN'!$G$6:$G$65,$D22)+SUMIFS('TABLESCAPE + FLORALS'!$S$6:$S$65,'TABLESCAPE + FLORALS'!$Q$6:$Q$65,$D22)+SUMIFS('TRAVEL PLAN'!$N$6:$N$45,'TRAVEL PLAN'!$L$6:$L$45,$D22)+SUMIFS('VENDORS + APPOINTMENTS'!$Q$6:$Q$65,'VENDORS + APPOINTMENTS'!$L$6:$L$65,$D22)+SUMIFS('EVENTS + WARDROBE'!$O$6:$O$65,'EVENTS + WARDROBE'!$M$6:$M$65,$D22)+SUMIFS('GROCERY LIST'!$M$6:$M$205,'GROCERY LIST'!$K$6:$K$205,$D22)+SUMIFS('MEAL + BAKING PLAN'!$R$6:$R$155,'MEAL + BAKING PLAN'!$P$6:$P$155,$D22)+SUMIFS('TRADITIONS + BUCKET LIST'!$J$6:$J$85,'TRADITIONS + BUCKET LIST'!$H$6:$H$85,$D22)-SUMIFS('RETURNS + EXCHANGES'!$R$6:$R$65,'RETURNS + EXCHANGES'!$K$6:$K$65,$D22)) | H22: =IF($D22="","",$E22-$G22) | I22: =IF($D22="","",IF($E22=0,0,$G22/$E22)) | J22: =IF($D22="","",IF(AND($E22=0,$G22=0),"NOT SET",IF($G22>$E22,"OVER BUDGET",IF($G22=$E22,"AT BUDGET",IF(AND($E22>0,$G22/$E22>=Set_WarnThreshold),"NEAR LIMIT","ON TRACK"))))) | L22: =IF(AND($C22="Yes",$D22<>"",OR(N($E22)>0,N($G22)>0)),$E22+(100-ROW())/10000,"") | M22: =IF($B22="",0,IF(COUNTIF('MASTER BUDGET'!$B$6:$B$25,$B22)>1,1,0))
F23: =IF($D23="","",SUMIFS('CARDS + MAIL'!$I$6:$I$155,'CARDS + MAIL'!$H$6:$H$155,$D23)+SUMIFS('DONATIONS + GIVING'!$G$6:$G$65,'DONATIONS + GIVING'!$F$6:$F$65,$D23)+SUMIFS('GIFT PLANNER'!$Q$6:$Q$205,'GIFT PLANNER'!$G$6:$G$205,$D23)+SUMIFS('STOCKING STUFFERS'!$J$6:$J$155,'STOCKING STUFFERS'!$F$6:$F$155,$D23)+SUMIFS('CHRISTMAS CALENDAR'!$K$6:$K$205,'CHRISTMAS CALENDAR'!$J$6:$J$205,$D23)+SUMIFS('DECOR INVENTORY'!$P$6:$P$105,'DECOR INVENTORY'!$O$6:$O$105,$D23)+SUMIFS('DECORATING PLAN'!$H$6:$H$65,'DECORATING PLAN'!$G$6:$G$65,$D23)+SUMIFS('TABLESCAPE + FLORALS'!$R$6:$R$65,'TABLESCAPE + FLORALS'!$Q$6:$Q$65,$D23)+SUMIFS('TRAVEL PLAN'!$M$6:$M$45,'TRAVEL PLAN'!$L$6:$L$45,$D23)+SUMIFS('VENDORS + APPOINTMENTS'!$M$6:$M$65,'VENDORS + APPOINTMENTS'!$L$6:$L$65,$D23)+SUMIFS('EVENTS + WARDROBE'!$N$6:$N$65,'EVENTS + WARDROBE'!$M$6:$M$65,$D23)+SUMIFS('GROCERY LIST'!$L$6:$L$205,'GROCERY LIST'!$K$6:$K$205,$D23)+SUMIFS('MEAL + BAKING PLAN'!$Q$6:$Q$155,'MEAL + BAKING PLAN'!$P$6:$P$155,$D23)+SUMIFS('TRADITIONS + BUCKET LIST'!$I$6:$I$85,'TRADITIONS + BUCKET LIST'!$H$6:$H$85,$D23)) | G23: =IF($D23="","",SUMIFS('CARDS + MAIL'!$J$6:$J$155,'CARDS + MAIL'!$H$6:$H$155,$D23)+SUMIFS('DONATIONS + GIVING'!$H$6:$H$65,'DONATIONS + GIVING'!$F$6:$F$65,$D23)+SUMIFS('GIFT PLANNER'!$R$6:$R$205,'GIFT PLANNER'!$G$6:$G$205,$D23)+SUMIFS('STOCKING STUFFERS'!$K$6:$K$155,'STOCKING STUFFERS'!$F$6:$F$155,$D23)+SUMIFS('CHRISTMAS CALENDAR'!$L$6:$L$205,'CHRISTMAS CALENDAR'!$J$6:$J$205,$D23)+SUMIFS('DECOR INVENTORY'!$Q$6:$Q$105,'DECOR INVENTORY'!$O$6:$O$105,$D23)+SUMIFS('DECORATING PLAN'!$I$6:$I$65,'DECORATING PLAN'!$G$6:$G$65,$D23)+SUMIFS('TABLESCAPE + FLORALS'!$S$6:$S$65,'TABLESCAPE + FLORALS'!$Q$6:$Q$65,$D23)+SUMIFS('TRAVEL PLAN'!$N$6:$N$45,'TRAVEL PLAN'!$L$6:$L$45,$D23)+SUMIFS('VENDORS + APPOINTMENTS'!$Q$6:$Q$65,'VENDORS + APPOINTMENTS'!$L$6:$L$65,$D23)+SUMIFS('EVENTS + WARDROBE'!$O$6:$O$65,'EVENTS + WARDROBE'!$M$6:$M$65,$D23)+SUMIFS('GROCERY LIST'!$M$6:$M$205,'GROCERY LIST'!$K$6:$K$205,$D23)+SUMIFS('MEAL + BAKING PLAN'!$R$6:$R$155,'MEAL + BAKING PLAN'!$P$6:$P$155,$D23)+SUMIFS('TRADITIONS + BUCKET LIST'!$J$6:$J$85,'TRADITIONS + BUCKET LIST'!$H$6:$H$85,$D23)-SUMIFS('RETURNS + EXCHANGES'!$R$6:$R$65,'RETURNS + EXCHANGES'!$K$6:$K$65,$D23)) | H23: =IF($D23="","",$E23-$G23) | I23: =IF($D23="","",IF($E23=0,0,$G23/$E23)) | J23: =IF($D23="","",IF(AND($E23=0,$G23=0),"NOT SET",IF($G23>$E23,"OVER BUDGET",IF($G23=$E23,"AT BUDGET",IF(AND($E23>0,$G23/$E23>=Set_WarnThreshold),"NEAR LIMIT","ON TRACK"))))) | L23: =IF(AND($C23="Yes",$D23<>"",OR(N($E23)>0,N($G23)>0)),$E23+(100-ROW())/10000,"") | M23: =IF($B23="",0,IF(COUNTIF('MASTER BUDGET'!$B$6:$B$25,$B23)>1,1,0))
F24: =IF($D24="","",SUMIFS('CARDS + MAIL'!$I$6:$I$155,'CARDS + MAIL'!$H$6:$H$155,$D24)+SUMIFS('DONATIONS + GIVING'!$G$6:$G$65,'DONATIONS + GIVING'!$F$6:$F$65,$D24)+SUMIFS('GIFT PLANNER'!$Q$6:$Q$205,'GIFT PLANNER'!$G$6:$G$205,$D24)+SUMIFS('STOCKING STUFFERS'!$J$6:$J$155,'STOCKING STUFFERS'!$F$6:$F$155,$D24)+SUMIFS('CHRISTMAS CALENDAR'!$K$6:$K$205,'CHRISTMAS CALENDAR'!$J$6:$J$205,$D24)+SUMIFS('DECOR INVENTORY'!$P$6:$P$105,'DECOR INVENTORY'!$O$6:$O$105,$D24)+SUMIFS('DECORATING PLAN'!$H$6:$H$65,'DECORATING PLAN'!$G$6:$G$65,$D24)+SUMIFS('TABLESCAPE + FLORALS'!$R$6:$R$65,'TABLESCAPE + FLORALS'!$Q$6:$Q$65,$D24)+SUMIFS('TRAVEL PLAN'!$M$6:$M$45,'TRAVEL PLAN'!$L$6:$L$45,$D24)+SUMIFS('VENDORS + APPOINTMENTS'!$M$6:$M$65,'VENDORS + APPOINTMENTS'!$L$6:$L$65,$D24)+SUMIFS('EVENTS + WARDROBE'!$N$6:$N$65,'EVENTS + WARDROBE'!$M$6:$M$65,$D24)+SUMIFS('GROCERY LIST'!$L$6:$L$205,'GROCERY LIST'!$K$6:$K$205,$D24)+SUMIFS('MEAL + BAKING PLAN'!$Q$6:$Q$155,'MEAL + BAKING PLAN'!$P$6:$P$155,$D24)+SUMIFS('TRADITIONS + BUCKET LIST'!$I$6:$I$85,'TRADITIONS + BUCKET LIST'!$H$6:$H$85,$D24)) | G24: =IF($D24="","",SUMIFS('CARDS + MAIL'!$J$6:$J$155,'CARDS + MAIL'!$H$6:$H$155,$D24)+SUMIFS('DONATIONS + GIVING'!$H$6:$H$65,'DONATIONS + GIVING'!$F$6:$F$65,$D24)+SUMIFS('GIFT PLANNER'!$R$6:$R$205,'GIFT PLANNER'!$G$6:$G$205,$D24)+SUMIFS('STOCKING STUFFERS'!$K$6:$K$155,'STOCKING STUFFERS'!$F$6:$F$155,$D24)+SUMIFS('CHRISTMAS CALENDAR'!$L$6:$L$205,'CHRISTMAS CALENDAR'!$J$6:$J$205,$D24)+SUMIFS('DECOR INVENTORY'!$Q$6:$Q$105,'DECOR INVENTORY'!$O$6:$O$105,$D24)+SUMIFS('DECORATING PLAN'!$I$6:$I$65,'DECORATING PLAN'!$G$6:$G$65,$D24)+SUMIFS('TABLESCAPE + FLORALS'!$S$6:$S$65,'TABLESCAPE + FLORALS'!$Q$6:$Q$65,$D24)+SUMIFS('TRAVEL PLAN'!$N$6:$N$45,'TRAVEL PLAN'!$L$6:$L$45,$D24)+SUMIFS('VENDORS + APPOINTMENTS'!$Q$6:$Q$65,'VENDORS + APPOINTMENTS'!$L$6:$L$65,$D24)+SUMIFS('EVENTS + WARDROBE'!$O$6:$O$65,'EVENTS + WARDROBE'!$M$6:$M$65,$D24)+SUMIFS('GROCERY LIST'!$M$6:$M$205,'GROCERY LIST'!$K$6:$K$205,$D24)+SUMIFS('MEAL + BAKING PLAN'!$R$6:$R$155,'MEAL + BAKING PLAN'!$P$6:$P$155,$D24)+SUMIFS('TRADITIONS + BUCKET LIST'!$J$6:$J$85,'TRADITIONS + BUCKET LIST'!$H$6:$H$85,$D24)-SUMIFS('RETURNS + EXCHANGES'!$R$6:$R$65,'RETURNS + EXCHANGES'!$K$6:$K$65,$D24)) | H24: =IF($D24="","",$E24-$G24) | I24: =IF($D24="","",IF($E24=0,0,$G24/$E24)) | J24: =IF($D24="","",IF(AND($E24=0,$G24=0),"NOT SET",IF($G24>$E24,"OVER BUDGET",IF($G24=$E24,"AT BUDGET",IF(AND($E24>0,$G24/$E24>=Set_WarnThreshold),"NEAR LIMIT","ON TRACK"))))) | L24: =IF(AND($C24="Yes",$D24<>"",OR(N($E24)>0,N($G24)>0)),$E24+(100-ROW())/10000,"") | M24: =IF($B24="",0,IF(COUNTIF('MASTER BUDGET'!$B$6:$B$25,$B24)>1,1,0))
F25: =IF($D25="","",SUMIFS('CARDS + MAIL'!$I$6:$I$155,'CARDS + MAIL'!$H$6:$H$155,$D25)+SUMIFS('DONATIONS + GIVING'!$G$6:$G$65,'DONATIONS + GIVING'!$F$6:$F$65,$D25)+SUMIFS('GIFT PLANNER'!$Q$6:$Q$205,'GIFT PLANNER'!$G$6:$G$205,$D25)+SUMIFS('STOCKING STUFFERS'!$J$6:$J$155,'STOCKING STUFFERS'!$F$6:$F$155,$D25)+SUMIFS('CHRISTMAS CALENDAR'!$K$6:$K$205,'CHRISTMAS CALENDAR'!$J$6:$J$205,$D25)+SUMIFS('DECOR INVENTORY'!$P$6:$P$105,'DECOR INVENTORY'!$O$6:$O$105,$D25)+SUMIFS('DECORATING PLAN'!$H$6:$H$65,'DECORATING PLAN'!$G$6:$G$65,$D25)+SUMIFS('TABLESCAPE + FLORALS'!$R$6:$R$65,'TABLESCAPE + FLORALS'!$Q$6:$Q$65,$D25)+SUMIFS('TRAVEL PLAN'!$M$6:$M$45,'TRAVEL PLAN'!$L$6:$L$45,$D25)+SUMIFS('VENDORS + APPOINTMENTS'!$M$6:$M$65,'VENDORS + APPOINTMENTS'!$L$6:$L$65,$D25)+SUMIFS('EVENTS + WARDROBE'!$N$6:$N$65,'EVENTS + WARDROBE'!$M$6:$M$65,$D25)+SUMIFS('GROCERY LIST'!$L$6:$L$205,'GROCERY LIST'!$K$6:$K$205,$D25)+SUMIFS('MEAL + BAKING PLAN'!$Q$6:$Q$155,'MEAL + BAKING PLAN'!$P$6:$P$155,$D25)+SUMIFS('TRADITIONS + BUCKET LIST'!$I$6:$I$85,'TRADITIONS + BUCKET LIST'!$H$6:$H$85,$D25)) | G25: =IF($D25="","",SUMIFS('CARDS + MAIL'!$J$6:$J$155,'CARDS + MAIL'!$H$6:$H$155,$D25)+SUMIFS('DONATIONS + GIVING'!$H$6:$H$65,'DONATIONS + GIVING'!$F$6:$F$65,$D25)+SUMIFS('GIFT PLANNER'!$R$6:$R$205,'GIFT PLANNER'!$G$6:$G$205,$D25)+SUMIFS('STOCKING STUFFERS'!$K$6:$K$155,'STOCKING STUFFERS'!$F$6:$F$155,$D25)+SUMIFS('CHRISTMAS CALENDAR'!$L$6:$L$205,'CHRISTMAS CALENDAR'!$J$6:$J$205,$D25)+SUMIFS('DECOR INVENTORY'!$Q$6:$Q$105,'DECOR INVENTORY'!$O$6:$O$105,$D25)+SUMIFS('DECORATING PLAN'!$I$6:$I$65,'DECORATING PLAN'!$G$6:$G$65,$D25)+SUMIFS('TABLESCAPE + FLORALS'!$S$6:$S$65,'TABLESCAPE + FLORALS'!$Q$6:$Q$65,$D25)+SUMIFS('TRAVEL PLAN'!$N$6:$N$45,'TRAVEL PLAN'!$L$6:$L$45,$D25)+SUMIFS('VENDORS + APPOINTMENTS'!$Q$6:$Q$65,'VENDORS + APPOINTMENTS'!$L$6:$L$65,$D25)+SUMIFS('EVENTS + WARDROBE'!$O$6:$O$65,'EVENTS + WARDROBE'!$M$6:$M$65,$D25)+SUMIFS('GROCERY LIST'!$M$6:$M$205,'GROCERY LIST'!$K$6:$K$205,$D25)+SUMIFS('MEAL + BAKING PLAN'!$R$6:$R$155,'MEAL + BAKING PLAN'!$P$6:$P$155,$D25)+SUMIFS('TRADITIONS + BUCKET LIST'!$J$6:$J$85,'TRADITIONS + BUCKET LIST'!$H$6:$H$85,$D25)-SUMIFS('RETURNS + EXCHANGES'!$R$6:$R$65,'RETURNS + EXCHANGES'!$K$6:$K$65,$D25)) | H25: =IF($D25="","",$E25-$G25) | I25: =IF($D25="","",IF($E25=0,0,$G25/$E25)) | J25: =IF($D25="","",IF(AND($E25=0,$G25=0),"NOT SET",IF($G25>$E25,"OVER BUDGET",IF($G25=$E25,"AT BUDGET",IF(AND($E25>0,$G25/$E25>=Set_WarnThreshold),"NEAR LIMIT","ON TRACK"))))) | L25: =IF(AND($C25="Yes",$D25<>"",OR(N($E25)>0,N($G25)>0)),$E25+(100-ROW())/10000,"") | M25: =IF($B25="",0,IF(COUNTIF('MASTER BUDGET'!$B$6:$B$25,$B25)>1,1,0))

Sheet GIFT PLANNER
B1: Dashboard | D1: Start here | E1: Calendar | G1: Budget | H1: All sheets
B2: GIFT PLANNER
B3: Every gift from first idea to wrapped and under the tree.
B4: Cream cells are yours to fill in · pale green cells calculate themselves · amber rows are examples you can delete
B5: Gift ID | C5: Person ID | D5: Recipient | E5: Active? | F5: Gift / item | G5: Budget category | H5: Priority | I5: Idea from | J5: Link or SKU | K5: Store | L5: Qty | M5: Unit price | N5: Discount | O5: Ship (planned) | P5: Tax (planned) | Q5: Planned cost | R5: Actual cost | S5: Status | T5: Purchased? | U5: Order ID | V5: Delivery | W5: Arrived? | X5: Hidden where | Y5: Gift type | Z5: Wrapped? | AA5: Tag / card? | AB5: Bought on | AC5: Return by | AD5: Duplicate key | AE5: Duplicate? | AF5: Notes | AG5: QA · duplicate ID | AH5: QA · budget mapping | AI5: QA · Person ID exists | AJ5: QA · Order ID exists
B6: G-001 | C6: P-001 | D6: =IF($B6="","",IF($C6="","",IFERROR(IF(INDEX('PEOPLE + BUDGETS'!$C$6:$C$105,MATCH($C6,'PEOPLE + BUDGETS'!$B$6:$B$105,0))="","",INDEX('PEOPLE + BUDGETS'!$C$6:$C$105,MATCH($C6,'PEOPLE + BUDGETS'!$B$6:$B$105,0))),""))) | E6: =IF($B6="","",IF(OR($S6="Cancelled",$S6="Returned"),"No",IFERROR(INDEX('PEOPLE + BUDGETS'!$O$6:$O$105,MATCH($C6,'PEOPLE + BUDGETS'!$B$6:$B$105,0)),"Yes"))) | F6: Hand-thrown stoneware jug | G6: Gifts | H6: Must | I6: Her own wish list | K6: Levens Pottery | L6: 1 | M6: 145 | N6: 0 | O6: 12 | P6: 18.85 | Q6: =IF($B6="","",ROUND(MAX(0,$L6*$M6-$N6)+$O6+$P6,2)) | R6: 175.85 | S6: Purchased | T6: =IF($B6="","",IF($S6="Purchased","Yes","No")) | U6: O-001 | V6: Ship to home | W6: =IF($B6="","",IF($U6="","—",IF($U6="","",IFERROR(IF(INDEX('ONLINE ORDERS'!$M$6:$M$155,MATCH($U6,'ONLINE ORDERS'!$B$6:$B$155,0))="","",INDEX('ONLINE ORDERS'!$M$6:$M$155,MATCH($U6,'ONLINE ORDERS'!$B$6:$B$155,0))),"")))) | X6: Cedar chest, guest room | Y6: Physical | Z6: No | AA6: No | AB6: 46340 | AC6: 46401 | AD6: =IF($F6="","",LOWER(TRIM($C6&"|"&TRIM($F6)))) | AE6: =IF($AD6="","",IF(COUNTIF('GIFT PLANNER'!$AD$6:$AD$205,$AD6)>1,"CHECK DUPLICATE","")) | AF6: EXAMPLE — DELETE ME | AG6: =IF($B6="",0,IF(COUNTIF('GIFT PLANNER'!$B$6:$B$205,$B6)>1,1,0)) | AH6: =IF(OR(N($Q6)>0,N($R6)>0),IF($G6="",1,IF(COUNTIF('MASTER BUDGET'!$D$6:$D$25,$G6)=0,1,0)),0) | AI6: =IF($C6="",0,IF(COUNTIF('PEOPLE + BUDGETS'!$B$6:$B$105,$C6)=0,1,0)) | AJ6: =IF($U6="",0,IF(COUNTIF('ONLINE ORDERS'!$B$6:$B$155,$U6)=0,1,0))
B7: G-002 | C7: P-002 | D7: =IF($B7="","",IF($C7="","",IFERROR(IF(INDEX('PEOPLE + BUDGETS'!$C$6:$C$105,MATCH($C7,'PEOPLE + BUDGETS'!$B$6:$B$105,0))="","",INDEX('PEOPLE + BUDGETS'!$C$6:$C$105,MATCH($C7,'PEOPLE + BUDGETS'!$B$6:$B$105,0))),""))) | E7: =IF($B7="","",IF(OR($S7="Cancelled",$S7="Returned"),"No",IFERROR(INDEX('PEOPLE + BUDGETS'!$O$6:$O$105,MATCH($C7,'PEOPLE + BUDGETS'!$B$6:$B$105,0)),"Yes"))) | F7: Chart of the Western Isles, framed | G7: Gifts | H7: Should | I7: Overheard in October | K7: Marine Charts Co. | L7: 1 | M7: 220 | N7: 20 | O7: 0 | P7: 26 | Q7: =IF($B7="","",ROUND(MAX(0,$L7*$M7-$N7)+$O7+$P7,2)) | S7: In Cart | T7: =IF($B7="","",IF($S7="Purchased","Yes","No")) | V7: Store pickup | W7: =IF($B7="","",IF($U7="","—",IF($U7="","",IFERROR(IF(INDEX('ONLINE ORDERS'!$M$6:$M$155,MATCH($U7,'ONLINE ORDERS'!$B$6:$B$155,0))="","",INDEX('ONLINE ORDERS'!$M$6:$M$155,MATCH($U7,'ONLINE ORDERS'!$B$6:$B$155,0))),"")))) | Y7: Physical | Z7: No | AA7: No | AD7: =IF($F7="","",LOWER(TRIM($C7&"|"&TRIM($F7)))) | AE7: =IF($AD7="","",IF(COUNTIF('GIFT PLANNER'!$AD$6:$AD$205,$AD7)>1,"CHECK DUPLICATE","")) | AF7: EXAMPLE — DELETE ME | AG7: =IF($B7="",0,IF(COUNTIF('GIFT PLANNER'!$B$6:$B$205,$B7)>1,1,0)) | AH7: =IF(OR(N($Q7)>0,N($R7)>0),IF($G7="",1,IF(COUNTIF('MASTER BUDGET'!$D$6:$D$25,$G7)=0,1,0)),0) | AI7: =IF($C7="",0,IF(COUNTIF('PEOPLE + BUDGETS'!$B$6:$B$105,$C7)=0,1,0)) | AJ7: =IF($U7="",0,IF(COUNTIF('ONLINE ORDERS'!$B$6:$B$155,$U7)=0,1,0))
B8: G-003 | C8: P-003 | D8: =IF($B8="","",IF($C8="","",IFERROR(IF(INDEX('PEOPLE + BUDGETS'!$C$6:$C$105,MATCH($C8,'PEOPLE + BUDGETS'!$B$6:$B$105,0))="","",INDEX('PEOPLE + BUDGETS'!$C$6:$C$105,MATCH($C8,'PEOPLE + BUDGETS'!$B$6:$B$105,0))),""))) | E8: =IF($B8="","",IF(OR($S8="Cancelled",$S8="Returned"),"No",IFERROR(INDEX('PEOPLE + BUDGETS'!$O$6:$O$105,MATCH($C8,'PEOPLE + BUDGETS'!$B$6:$B$105,0)),"Yes"))) | F8: Winter swimming membership | G8: Gifts | H8: Could | I8: Her cold-water habit | K8: Lido Society | L8: 1 | M8: 96 | N8: 0 | O8: 0 | P8: 0 | Q8: =IF($B8="","",ROUND(MAX(0,$L8*$M8-$N8)+$O8+$P8,2)) | R8: 96 | S8: Purchased | T8: =IF($B8="","",IF($S8="Purchased","Yes","No")) | V8: Digital delivery | W8: =IF($B8="","",IF($U8="","—",IF($U8="","",IFERROR(IF(INDEX('ONLINE ORDERS'!$M$6:$M$155,MATCH($U8,'ONLINE ORDERS'!$B$6:$B$155,0))="","",INDEX('ONLINE ORDERS'!$M$6:$M$155,MATCH($U8,'ONLINE ORDERS'!$B$6:$B$155,0))),"")))) | Y8: Experience | Z8: No | AA8: Yes | AB8: 46346 | AD8: =IF($F8="","",LOWER(TRIM($C8&"|"&TRIM($F8)))) | AE8: =IF($AD8="","",IF(COUNTIF('GIFT PLANNER'!$AD$6:$AD$205,$AD8)>1,"CHECK DUPLICATE","")) | AF8: EXAMPLE — DELETE ME | AG8: =IF($B8="",0,IF(COUNTIF('GIFT PLANNER'!$B$6:$B$205,$B8)>1,1,0)) | AH8: =IF(OR(N($Q8)>0,N($R8)>0),IF($G8="",1,IF(COUNTIF('MASTER BUDGET'!$D$6:$D$25,$G8)=0,1,0)),0) | AI8: =IF($C8="",0,IF(COUNTIF('PEOPLE + BUDGETS'!$B$6:$B$105,$C8)=0,1,0)) | AJ8: =IF($U8="",0,IF(COUNTIF('ONLINE ORDERS'!$B$6:$B$155,$U8)=0,1,0))
D9: =IF($B9="","",IF($C9="","",IFERROR(IF(INDEX('PEOPLE + BUDGETS'!$C$6:$C$105,MATCH($C9,'PEOPLE + BUDGETS'!$B$6:$B$105,0))="","",INDEX('PEOPLE + BUDGETS'!$C$6:$C$105,MATCH($C9,'PEOPLE + BUDGETS'!$B$6:$B$105,0))),""))) | E9: =IF($B9="","",IF(OR($S9="Cancelled",$S9="Returned"),"No",IFERROR(INDEX('PEOPLE + BUDGETS'!$O$6:$O$105,MATCH($C9,'PEOPLE + BUDGETS'!$B$6:$B$105,0)),"Yes"))) | Q9: =IF($B9="","",ROUND(MAX(0,$L9*$M9-$N9)+$O9+$P9,2)) | T9: =IF($B9="","",IF($S9="Purchased","Yes","No")) | W9: =IF($B9="","",IF($U9="","—",IF($U9="","",IFERROR(IF(INDEX('ONLINE ORDERS'!$M$6:$M$155,MATCH($U9,'ONLINE ORDERS'!$B$6:$B$155,0))="","",INDEX('ONLINE ORDERS'!$M$6:$M$155,MATCH($U9,'ONLINE ORDERS'!$B$6:$B$155,0))),"")))) | AD9: =IF($F9="","",LOWER(TRIM($C9&"|"&TRIM($F9)))) | AE9: =IF($AD9="","",IF(COUNTIF('GIFT PLANNER'!$AD$6:$AD$205,$AD9)>1,"CHECK DUPLICATE","")) | AG9: =IF($B9="",0,IF(COUNTIF('GIFT PLANNER'!$B$6:$B$205,$B9)>1,1,0)) | AH9: =IF(OR(N($Q9)>0,N($R9)>0),IF($G9="",1,IF(COUNTIF('MASTER BUDGET'!$D$6:$D$25,$G9)=0,1,0)),0) | AI9: =IF($C9="",0,IF(COUNTIF('PEOPLE + BUDGETS'!$B$6:$B$105,$C9)=0,1,0)) | AJ9: =IF($U9="",0,IF(COUNTIF('ONLINE ORDERS'!$B$6:$B$155,$U9)=0,1,0))
D10: =IF($B10="","",IF($C10="","",IFERROR(IF(INDEX('PEOPLE + BUDGETS'!$C$6:$C$105,MATCH($C10,'PEOPLE + BUDGETS'!$B$6:$B$105,0))="","",INDEX('PEOPLE + BUDGETS'!$C$6:$C$105,MATCH($C10,'PEOPLE + BUDGETS'!$B$6:$B$105,0))),""))) | E10: =IF($B10="","",IF(OR($S10="Cancelled",$S10="Returned"),"No",IFERROR(INDEX('PEOPLE + BUDGETS'!$O$6:$O$105,MATCH($C10,'PEOPLE + BUDGETS'!$B$6:$B$105,0)),"Yes"))) | Q10: =IF($B10="","",ROUND(MAX(0,$L10*$M10-$N10)+$O10+$P10,2)) | T10: =IF($B10="","",IF($S10="Purchased","Yes","No")) | W10: =IF($B10="","",IF($U10="","—",IF($U10="","",IFERROR(IF(INDEX('ONLINE ORDERS'!$M$6:$M$155,MATCH($U10,'ONLINE ORDERS'!$B$6:$B$155,0))="","",INDEX('ONLINE ORDERS'!$M$6:$M$155,MATCH($U10,'ONLINE ORDERS'!$B$6:$B$155,0))),"")))) | AD10: =IF($F10="","",LOWER(TRIM($C10&"|"&TRIM($F10)))) | AE10: =IF($AD10="","",IF(COUNTIF('GIFT PLANNER'!$AD$6:$AD$205,$AD10)>1,"CHECK DUPLICATE","")) | AG10: =IF($B10="",0,IF(COUNTIF('GIFT PLANNER'!$B$6:$B$205,$B10)>1,1,0)) | AH10: =IF(OR(N($Q10)>0,N($R10)>0),IF($G10="",1,IF(COUNTIF('MASTER BUDGET'!$D$6:$D$25,$G10)=0,1,0)),0) | AI10: =IF($C10="",0,IF(COUNTIF('PEOPLE + BUDGETS'!$B$6:$B$105,$C10)=0,1,0)) | AJ10: =IF($U10="",0,IF(COUNTIF('ONLINE ORDERS'!$B$6:$B$155,$U10)=0,1,0))
D11: =IF($B11="","",IF($C11="","",IFERROR(IF(INDEX('PEOPLE + BUDGETS'!$C$6:$C$105,MATCH($C11,'PEOPLE + BUDGETS'!$B$6:$B$105,0))="","",INDEX('PEOPLE + BUDGETS'!$C$6:$C$105,MATCH($C11,'PEOPLE + BUDGETS'!$B$6:$B$105,0))),""))) | E11: =IF($B11="","",IF(OR($S11="Cancelled",$S11="Returned"),"No",IFERROR(INDEX('PEOPLE + BUDGETS'!$O$6:$O$105,MATCH($C11,'PEOPLE + BUDGETS'!$B$6:$B$105,0)),"Yes"))) | Q11: =IF($B11="","",ROUND(MAX(0,$L11*$M11-$N11)+$O11+$P11,2)) | T11: =IF($B11="","",IF($S11="Purchased","Yes","No")) | W11: =IF($B11="","",IF($U11="","—",IF($U11="","",IFERROR(IF(INDEX('ONLINE ORDERS'!$M$6:$M$155,MATCH($U11,'ONLINE ORDERS'!$B$6:$B$155,0))="","",INDEX('ONLINE ORDERS'!$M$6:$M$155,MATCH($U11,'ONLINE ORDERS'!$B$6:$B$155,0))),"")))) | AD11: =IF($F11="","",LOWER(TRIM($C11&"|"&TRIM($F11)))) | AE11: =IF($AD11="","",IF(COUNTIF('GIFT PLANNER'!$AD$6:$AD$205,$AD11)>1,"CHECK DUPLICATE","")) | AG11: =IF($B11="",0,IF(COUNTIF('GIFT PLANNER'!$B$6:$B$205,$B11)>1,1,0)) | AH11: =IF(OR(N($Q11)>0,N($R11)>0),IF($G11="",1,IF(COUNTIF('MASTER BUDGET'!$D$6:$D$25,$G11)=0,1,0)),0) | AI11: =IF($C11="",0,IF(COUNTIF('PEOPLE + BUDGETS'!$B$6:$B$105,$C11)=0,1,0)) | AJ11: =IF($U11="",0,IF(COUNTIF('ONLINE ORDERS'!$B$6:$B$155,$U11)=0,1,0))
D12: =IF($B12="","",IF($C12="","",IFERROR(IF(INDEX('PEOPLE + BUDGETS'!$C$6:$C$105,MATCH($C12,'PEOPLE + BUDGETS'!$B$6:$B$105,0))="","",INDEX('PEOPLE + BUDGETS'!$C$6:$C$105,MATCH($C12,'PEOPLE + BUDGETS'!$B$6:$B$105,0))),""))) | E12: =IF($B12="","",IF(OR($S12="Cancelled",$S12="Returned"),"No",IFERROR(INDEX('PEOPLE + BUDGETS'!$O$6:$O$105,MATCH($C12,'PEOPLE + BUDGETS'!$B$6:$B$105,0)),"Yes"))) | Q12: =IF($B12="","",ROUND(MAX(0,$L12*$M12-$N12)+$O12+$P12,2)) | T12: =IF($B12="","",IF($S12="Purchased","Yes","No")) | W12: =IF($B12="","",IF($U12="","—",IF($U12="","",IFERROR(IF(INDEX('ONLINE ORDERS'!$M$6:$M$155,MATCH($U12,'ONLINE ORDERS'!$B$6:$B$155,0))="","",INDEX('ONLINE ORDERS'!$M$6:$M$155,MATCH($U12,'ONLINE ORDERS'!$B$6:$B$155,0))),"")))) | AD12: =IF($F12="","",LOWER(TRIM($C12&"|"&TRIM($F12)))) | AE12: =IF($AD12="","",IF(COUNTIF('GIFT PLANNER'!$AD$6:$AD$205,$AD12)>1,"CHECK DUPLICATE","")) | AG12: =IF($B12="",0,IF(COUNTIF('GIFT PLANNER'!$B$6:$B$205,$B12)>1,1,0)) | AH12: =IF(OR(N($Q12)>0,N($R12)>0),IF($G12="",1,IF(COUNTIF('MASTER BUDGET'!$D$6:$D$25,$G12)=0,1,0)),0) | AI12: =IF($C12="",0,IF(COUNTIF('PEOPLE + BUDGETS'!$B$6:$B$105,$C12)=0,1,0)) | AJ12: =IF($U12="",0,IF(COUNTIF('ONLINE ORDERS'!$B$6:$B$155,$U12)=0,1,0))
D13: =IF($B13="","",IF($C13="","",IFERROR(IF(INDEX('PEOPLE + BUDGETS'!$C$6:$C$105,MATCH($C13,'PEOPLE + BUDGETS'!$B$6:$B$105,0))="","",INDEX('PEOPLE + BUDGETS'!$C$6:$C$105,MATCH($C13,'PEOPLE + BUDGETS'!$B$6:$B$105,0))),""))) | E13: =IF($B13="","",IF(OR($S13="Cancelled",$S13="Returned"),"No",IFERROR(INDEX('PEOPLE + BUDGETS'!$O$6:$O$105,MATCH($C13,'PEOPLE + BUDGETS'!$B$6:$B$105,0)),"Yes"))) | Q13: =IF($B13="","",ROUND(MAX(0,$L13*$M13-$N13)+$O13+$P13,2)) | T13: =IF($B13="","",IF($S13="Purchased","Yes","No")) | W13: =IF($B13="","",IF($U13="","—",IF($U13="","",IFERROR(IF(INDEX('ONLINE ORDERS'!$M$6:$M$155,MATCH($U13,'ONLINE ORDERS'!$B$6:$B$155,0))="","",INDEX('ONLINE ORDERS'!$M$6:$M$155,MATCH($U13,'ONLINE ORDERS'!$B$6:$B$155,0))),"")))) | AD13: =IF($F13="","",LOWER(TRIM($C13&"|"&TRIM($F13)))) | AE13: =IF($AD13="","",IF(COUNTIF('GIFT PLANNER'!$AD$6:$AD$205,$AD13)>1,"CHECK DUPLICATE","")) | AG13: =IF($B13="",0,IF(COUNTIF('GIFT PLANNER'!$B$6:$B$205,$B13)>1,1,0)) | AH13: =IF(OR(N($Q13)>0,N($R13)>0),IF($G13="",1,IF(COUNTIF('MASTER BUDGET'!$D$6:$D$25,$G13)=0,1,0)),0) | AI13: =IF($C13="",0,IF(COUNTIF('PEOPLE + BUDGETS'!$B$6:$B$105,$C13)=0,1,0)) | AJ13: =IF($U13="",0,IF(COUNTIF('ONLINE ORDERS'!$B$6:$B$155,$U13)=0,1,0))
D14: =IF($B14="","",IF($C14="","",IFERROR(IF(INDEX('PEOPLE + BUDGETS'!$C$6:$C$105,MATCH($C14,'PEOPLE + BUDGETS'!$B$6:$B$105,0))="","",INDEX('PEOPLE + BUDGETS'!$C$6:$C$105,MATCH($C14,'PEOPLE + BUDGETS'!$B$6:$B$105,0))),""))) | E14: =IF($B14="","",IF(OR($S14="Cancelled",$S14="Returned"),"No",IFERROR(INDEX('PEOPLE + BUDGETS'!$O$6:$O$105,MATCH($C14,'PEOPLE + BUDGETS'!$B$6:$B$105,0)),"Yes"))) | Q14: =IF($B14="","",ROUND(MAX(0,$L14*$M14-$N14)+$O14+$P14,2)) | T14: =IF($B14="","",IF($S14="Purchased","Yes","No")) | W14: =IF($B14="","",IF($U14="","—",IF($U14="","",IFERROR(IF(INDEX('ONLINE ORDERS'!$M$6:$M$155,MATCH($U14,'ONLINE ORDERS'!$B$6:$B$155,0))="","",INDEX('ONLINE ORDERS'!$M$6:$M$155,MATCH($U14,'ONLINE ORDERS'!$B$6:$B$155,0))),"")))) | AD14: =IF($F14="","",LOWER(TRIM($C14&"|"&TRIM($F14)))) | AE14: =IF($AD14="","",IF(COUNTIF('GIFT PLANNER'!$AD$6:$AD$205,$AD14)>1,"CHECK DUPLICATE","")) | AG14: =IF($B14="",0,IF(COUNTIF('GIFT PLANNER'!$B$6:$B$205,$B14)>1,1,0)) | AH14: =IF(OR(N($Q14)>0,N($R14)>0),IF($G14="",1,IF(COUNTIF('MASTER BUDGET'!$D$6:$D$25,$G14)=0,1,0)),0) | AI14: =IF($C14="",0,IF(COUNTIF('PEOPLE + BUDGETS'!$B$6:$B$105,$C14)=0,1,0)) | AJ14: =IF($U14="",0,IF(COUNTIF('ONLINE ORDERS'!$B$6:$B$155,$U14)=0,1,0))
D15: =IF($B15="","",IF($C15="","",IFERROR(IF(INDEX('PEOPLE + BUDGETS'!$C$6:$C$105,MATCH($C15,'PEOPLE + BUDGETS'!$B$6:$B$105,0))="","",INDEX('PEOPLE + BUDGETS'!$C$6:$C$105,MATCH($C15,'PEOPLE + BUDGETS'!$B$6:$B$105,0))),""))) | E15: =IF($B15="","",IF(OR($S15="Cancelled",$S15="Returned"),"No",IFERROR(INDEX('PEOPLE + BUDGETS'!$O$6:$O$105,MATCH($C15,'PEOPLE + BUDGETS'!$B$6:$B$105,0)),"Yes"))) | Q15: =IF($B15="","",ROUND(MAX(0,$L15*$M15-$N15)+$O15+$P15,2)) | T15: =IF($B15="","",IF($S15="Purchased","Yes","No")) | W15: =IF($B15="","",IF($U15="","—",IF($U15="","",IFERROR(IF(INDEX('ONLINE ORDERS'!$M$6:$M$155,MATCH($U15,'ONLINE ORDERS'!$B$6:$B$155,0))="","",INDEX('ONLINE ORDERS'!$M$6:$M$155,MATCH($U15,'ONLINE ORDERS'!$B$6:$B$155,0))),"")))) | AD15: =IF($F15="","",LOWER(TRIM($C15&"|"&TRIM($F15)))) | AE15: =IF($AD15="","",IF(COUNTIF('GIFT PLANNER'!$AD$6:$AD$205,$AD15)>1,"CHECK DUPLICATE","")) | AG15: =IF($B15="",0,IF(COUNTIF('GIFT PLANNER'!$B$6:$B$205,$B15)>1,1,0)) | AH15: =IF(OR(N($Q15)>0,N($R15)>0),IF($G15="",1,IF(COUNTIF('MASTER BUDGET'!$D$6:$D$25,$G15)=0,1,0)),0) | AI15: =IF($C15="",0,IF(COUNTIF('PEOPLE + BUDGETS'!$B$6:$B$105,$C15)=0,1,0)) | AJ15: =IF($U15="",0,IF(COUNTIF('ONLINE ORDERS'!$B$6:$B$155,$U15)=0,1,0))
D16: =IF($B16="","",IF($C16="","",IFERROR(IF(INDEX('PEOPLE + BUDGETS'!$C$6:$C$105,MATCH($C16,'PEOPLE + BUDGETS'!$B$6:$B$105,0))="","",INDEX('PEOPLE + BUDGETS'!$C$6:$C$105,MATCH($C16,'PEOPLE + BUDGETS'!$B$6:$B$105,0))),""))) | E16: =IF($B16="","",IF(OR($S16="Cancelled",$S16="Returned"),"No",IFERROR(INDEX('PEOPLE + BUDGETS'!$O$6:$O$105,MATCH($C16,'PEOPLE + BUDGETS'!$B$6:$B$105,0)),"Yes"))) | Q16: =IF($B16="","",ROUND(MAX(0,$L16*$M16-$N16)+$O16+$P16,2)) | T16: =IF($B16="","",IF($S16="Purchased","Yes","No")) | W16: =IF($B16="","",IF($U16="","—",IF($U16="","",IFERROR(IF(INDEX('ONLINE ORDERS'!$M$6:$M$155,MATCH($U16,'ONLINE ORDERS'!$B$6:$B$155,0))="","",INDEX('ONLINE ORDERS'!$M$6:$M$155,MATCH($U16,'ONLINE ORDERS'!$B$6:$B$155,0))),"")))) | AD16: =IF($F16="","",LOWER(TRIM($C16&"|"&TRIM($F16)))) | AE16: =IF($AD16="","",IF(COUNTIF('GIFT PLANNER'!$AD$6:$AD$205,$AD16)>1,"CHECK DUPLICATE","")) | AG16: =IF($B16="",0,IF(COUNTIF('GIFT PLANNER'!$B$6:$B$205,$B16)>1,1,0)) | AH16: =IF(OR(N($Q16)>0,N($R16)>0),IF($G16="",1,IF(COUNTIF('MASTER BUDGET'!$D$6:$D$25,$G16)=0,1,0)),0) | AI16: =IF($C16="",0,IF(COUNTIF('PEOPLE + BUDGETS'!$B$6:$B$105,$C16)=0,1,0)) | AJ16: =IF($U16="",0,IF(COUNTIF('ONLINE ORDERS'!$B$6:$B$155,$U16)=0,1,0))
D17: =IF($B17="","",IF($C17="","",IFERROR(IF(INDEX('PEOPLE + BUDGETS'!$C$6:$C$105,MATCH($C17,'PEOPLE + BUDGETS'!$B$6:$B$105,0))="","",INDEX('PEOPLE + BUDGETS'!$C$6:$C$105,MATCH($C17,'PEOPLE + BUDGETS'!$B$6:$B$105,0))),""))) | E17: =IF($B17="","",IF(OR($S17="Cancelled",$S17="Returned"),"No",IFERROR(INDEX('PEOPLE + BUDGETS'!$O$6:$O$105,MATCH($C17,'PEOPLE + BUDGETS'!$B$6:$B$105,0)),"Yes"))) | Q17: =IF($B17="","",ROUND(MAX(0,$L17*$M17-$N17)+$O17+$P17,2)) | T17: =IF($B17="","",IF($S17="Purchased","Yes","No")) | W17: =IF($B17="","",IF($U17="","—",IF($U17="","",IFERROR(IF(INDEX('ONLINE ORDERS'!$M$6:$M$155,MATCH($U17,'ONLINE ORDERS'!$B$6:$B$155,0))="","",INDEX('ONLINE ORDERS'!$M$6:$M$155,MATCH($U17,'ONLINE ORDERS'!$B$6:$B$155,0))),"")))) | AD17: =IF($F17="","",LOWER(TRIM($C17&"|"&TRIM($F17)))) | AE17: =IF($AD17="","",IF(COUNTIF('GIFT PLANNER'!$AD$6:$AD$205,$AD17)>1,"CHECK DUPLICATE","")) | AG17: =IF($B17="",0,IF(COUNTIF('GIFT PLANNER'!$B$6:$B$205,$B17)>1,1,0)) | AH17: =IF(OR(N($Q17)>0,N($R17)>0),IF($G17="",1,IF(COUNTIF('MASTER BUDGET'!$D$6:$D$25,$G17)=0,1,0)),0) | AI17: =IF($C17="",0,IF(COUNTIF('PEOPLE + BUDGETS'!$B$6:$B$105,$C17)=0,1,0)) | AJ17: =IF($U17="",0,IF(COUNTIF('ONLINE ORDERS'!$B$6:$B$155,$U17)=0,1,0))
D18: =IF($B18="","",IF($C18="","",IFERROR(IF(INDEX('PEOPLE + BUDGETS'!$C$6:$C$105,MATCH($C18,'PEOPLE + BUDGETS'!$B$6:$B$105,0))="","",INDEX('PEOPLE + BUDGETS'!$C$6:$C$105,MATCH($C18,'PEOPLE + BUDGETS'!$B$6:$B$105,0))),""))) | E18: =IF($B18="","",IF(OR($S18="Cancelled",$S18="Returned"),"No",IFERROR(INDEX('PEOPLE + BUDGETS'!$O$6:$O$105,MATCH($C18,'PEOPLE + BUDGETS'!$B$6:$B$105,0)),"Yes"))) | Q18: =IF($B18="","",ROUND(MAX(0,$L18*$M18-$N18)+$O18+$P18,2)) | T18: =IF($B18="","",IF($S18="Purchased","Yes","No")) | W18: =IF($B18="","",IF($U18="","—",IF($U18="","",IFERROR(IF(INDEX('ONLINE ORDERS'!$M$6:$M$155,MATCH($U18,'ONLINE ORDERS'!$B$6:$B$155,0))="","",INDEX('ONLINE ORDERS'!$M$6:$M$155,MATCH($U18,'ONLINE ORDERS'!$B$6:$B$155,0))),"")))) | AD18: =IF($F18="","",LOWER(TRIM($C18&"|"&TRIM($F18)))) | AE18: =IF($AD18="","",IF(COUNTIF('GIFT PLANNER'!$AD$6:$AD$205,$AD18)>1,"CHECK DUPLICATE","")) | AG18: =IF($B18="",0,IF(COUNTIF('GIFT PLANNER'!$B$6:$B$205,$B18)>1,1,0)) | AH18: =IF(OR(N($Q18)>0,N($R18)>0),IF($G18="",1,IF(COUNTIF('MASTER BUDGET'!$D$6:$D$25,$G18)=0,1,0)),0) | AI18: =IF($C18="",0,IF(COUNTIF('PEOPLE + BUDGETS'!$B$6:$B$105,$C18)=0,1,0)) | AJ18: =IF($U18="",0,IF(COUNTIF('ONLINE ORDERS'!$B$6:$B$155,$U18)=0,1,0))
D19: =IF($B19="","",IF($C19="","",IFERROR(IF(INDEX('PEOPLE + BUDGETS'!$C$6:$C$105,MATCH($C19,'PEOPLE + BUDGETS'!$B$6:$B$105,0))="","",INDEX('PEOPLE + BUDGETS'!$C$6:$C$105,MATCH($C19,'PEOPLE + BUDGETS'!$B$6:$B$105,0))),""))) | E19: =IF($B19="","",IF(OR($S19="Cancelled",$S19="Returned"),"No",IFERROR(INDEX('PEOPLE + BUDGETS'!$O$6:$O$105,MATCH($C19,'PEOPLE + BUDGETS'!$B$6:$B$105,0)),"Yes"))) | Q19: =IF($B19="","",ROUND(MAX(0,$L19*$M19-$N19)+$O19+$P19,2)) | T19: =IF($B19="","",IF($S19="Purchased","Yes","No")) | W19: =IF($B19="","",IF($U19="","—",IF($U19="","",IFERROR(IF(INDEX('ONLINE ORDERS'!$M$6:$M$155,MATCH($U19,'ONLINE ORDERS'!$B$6:$B$155,0))="","",INDEX('ONLINE ORDERS'!$M$6:$M$155,MATCH($U19,'ONLINE ORDERS'!$B$6:$B$155,0))),"")))) | AD19: =IF($F19="","",LOWER(TRIM($C19&"|"&TRIM($F19)))) | AE19: =IF($AD19="","",IF(COUNTIF('GIFT PLANNER'!$AD$6:$AD$205,$AD19)>1,"CHECK DUPLICATE","")) | AG19: =IF($B19="",0,IF(COUNTIF('GIFT PLANNER'!$B$6:$B$205,$B19)>1,1,0)) | AH19: =IF(OR(N($Q19)>0,N($R19)>0),IF($G19="",1,IF(COUNTIF('MASTER BUDGET'!$D$6:$D$25,$G19)=0,1,0)),0) | AI19: =IF($C19="",0,IF(COUNTIF('PEOPLE + BUDGETS'!$B$6:$B$105,$C19)=0,1,0)) | AJ19: =IF($U19="",0,IF(COUNTIF('ONLINE ORDERS'!$B$6:$B$155,$U19)=0,1,0))
D20: =IF($B20="","",IF($C20="","",IFERROR(IF(INDEX('PEOPLE + BUDGETS'!$C$6:$C$105,MATCH($C20,'PEOPLE + BUDGETS'!$B$6:$B$105,0))="","",INDEX('PEOPLE + BUDGETS'!$C$6:$C$105,MATCH($C20,'PEOPLE + BUDGETS'!$B$6:$B$105,0))),""))) | E20: =IF($B20="","",IF(OR($S20="Cancelled",$S20="Returned"),"No",IFERROR(INDEX('PEOPLE + BUDGETS'!$O$6:$O$105,MATCH($C20,'PEOPLE + BUDGETS'!$B$6:$B$105,0)),"Yes"))) | Q20: =IF($B20="","",ROUND(MAX(0,$L20*$M20-$N20)+$O20+$P20,2)) | T20: =IF($B20="","",IF($S20="Purchased","Yes","No")) | W20: =IF($B20="","",IF($U20="","—",IF($U20="","",IFERROR(IF(INDEX('ONLINE ORDERS'!$M$6:$M$155,MATCH($U20,'ONLINE ORDERS'!$B$6:$B$155,0))="","",INDEX('ONLINE ORDERS'!$M$6:$M$155,MATCH($U20,'ONLINE ORDERS'!$B$6:$B$155,0))),"")))) | AD20: =IF($F20="","",LOWER(TRIM($C20&"|"&TRIM($F20)))) | AE20: =IF($AD20="","",IF(COUNTIF('GIFT PLANNER'!$AD$6:$AD$205,$AD20)>1,"CHECK DUPLICATE","")) | AG20: =IF($B20="",0,IF(COUNTIF('GIFT PLANNER'!$B$6:$B$205,$B20)>1,1,0)) | AH20: =IF(OR(N($Q20)>0,N($R20)>0),IF($G20="",1,IF(COUNTIF('MASTER BUDGET'!$D$6:$D$25,$G20)=0,1,0)),0) | AI20: =IF($C20="",0,IF(COUNTIF('PEOPLE + BUDGETS'!$B$6:$B$105,$C20)=0,1,0)) | AJ20: =IF($U20="",0,IF(COUNTIF('ONLINE ORDERS'!$B$6:$B$155,$U20)=0,1,0))
... D205: =IF($B205="","",IF($C205="","",IFERROR(IF(INDEX('PEOPLE + BUDGETS'!$C$6:$C$105,MATCH($C205,'PEOPLE + BUDGETS'!$B$6:$B$105,0))="","",INDEX('PEOPLE + BUDGETS'!$C$6:$C$105,MATCH($C205,'PEOPLE + BUDGETS'!$B$6:$B$105,0))),""))) | E205: =IF($B205="","",IF(OR($S205="Cancelled",$S205="Returned"),"No",IFERROR(INDEX('PEOPLE + BUDGETS'!$O$6:$O$105,MATCH($C205,'PEOPLE + BUDGETS'!$B$6:$B$105,0)),"Yes"))) | Q205: =IF($B205="","",ROUND(MAX(0,$L205*$M205-$N205)+$O205+$P205,2)) | T205: =IF($B205="","",IF($S205="Purchased","Yes","No")) | W205: =IF($B205="","",IF($U205="","—",IF($U205="","",IFERROR(IF(INDEX('ONLINE ORDERS'!$M$6:$M$155,MATCH($U205,'ONLINE ORDERS'!$B$6:$B$155,0))="","",INDEX('ONLINE ORDERS'!$M$6:$M$155,MATCH($U205,'ONLINE ORDERS'!$B$6:$B$155,0))),"")))) | AD205: =IF($F205="","",LOWER(TRIM($C205&"|"&TRIM($F205)))) | AE205: =IF($AD205="","",IF(COUNTIF('GIFT PLANNER'!$AD$6:$AD$205,$AD205)>1,"CHECK DUPLICATE","")) | AG205: =IF($B205="",0,IF(COUNTIF('GIFT PLANNER'!$B$6:$B$205,$B205)>1,1,0)) | AH205: =IF(OR(N($Q205)>0,N($R205)>0),IF($G205="",1,IF(COUNTIF('MASTER BUDGET'!$D$6:$D$25,$G205)=0,1,0)),0) | AI205: =IF($C205="",0,IF(COUNTIF('PEOPLE + BUDGETS'!$B$6:$B$105,$C205)=0,1,0)) | AJ205: =IF($U205="",0,IF(COUNTIF('ONLINE ORDERS'!$B$6:$B$155,$U205)=0,1,0))

Sheet STOCKING STUFFERS
B1: Dashboard | D1: Start here | E1: Calendar | F1: Budget | G1: All sheets
B2: STOCKING STUFFERS
B3: The small things, kept to a number you decided in advance.
B4: Cream cells are yours to fill in · pale green cells calculate themselves · amber rows are examples you can delete
B5: Item ID | C5: Person ID | D5: Recipient | E5: Item | F5: Budget category | G5: Store | H5: Qty | I5: Unit price | J5: Planned cost | K5: Actual cost | L5: Status | M5: In the stocking? | N5: Notes | O5: QA · duplicate ID | P5: QA · budget mapping | Q5: QA · Person ID exists
B6: S-001 | C6: P-001 | D6: =IF($B6="","",IF($C6="","",IFERROR(IF(INDEX('PEOPLE + BUDGETS'!$C$6:$C$105,MATCH($C6,'PEOPLE + BUDGETS'!$B$6:$B$105,0))="","",INDEX('PEOPLE + BUDGETS'!$C$6:$C$105,MATCH($C6,'PEOPLE + BUDGETS'!$B$6:$B$105,0))),""))) | E6: Seville marmalade, small jar | F6: Stockings | G6: The Deli | H6: 1 | I6: 9.5 | J6: =IF($B6="","",ROUND($H6*$I6,2)) | K6: 9.5 | L6: Purchased | M6: Yes | N6: EXAMPLE — DELETE ME | O6: =IF($B6="",0,IF(COUNTIF('STOCKING STUFFERS'!$B$6:$B$155,$B6)>1,1,0)) | P6: =IF(OR(N($J6)>0,N($K6)>0),IF($F6="",1,IF(COUNTIF('MASTER BUDGET'!$D$6:$D$25,$F6)=0,1,0)),0) | Q6: =IF($C6="",0,IF(COUNTIF('PEOPLE + BUDGETS'!$B$6:$B$105,$C6)=0,1,0))
B7: S-002 | C7: P-002 | D7: =IF($B7="","",IF($C7="","",IFERROR(IF(INDEX('PEOPLE + BUDGETS'!$C$6:$C$105,MATCH($C7,'PEOPLE + BUDGETS'!$B$6:$B$105,0))="","",INDEX('PEOPLE + BUDGETS'!$C$6:$C$105,MATCH($C7,'PEOPLE + BUDGETS'!$B$6:$B$105,0))),""))) | E7: Pocket notebook, oxblood | F7: Stockings | G7: Papeterie | H7: 2 | I7: 14 | J7: =IF($B7="","",ROUND($H7*$I7,2)) | L7: Idea | M7: No | N7: EXAMPLE — DELETE ME | O7: =IF($B7="",0,IF(COUNTIF('STOCKING STUFFERS'!$B$6:$B$155,$B7)>1,1,0)) | P7: =IF(OR(N($J7)>0,N($K7)>0),IF($F7="",1,IF(COUNTIF('MASTER BUDGET'!$D$6:$D$25,$F7)=0,1,0)),0) | Q7: =IF($C7="",0,IF(COUNTIF('PEOPLE + BUDGETS'!$B$6:$B$105,$C7)=0,1,0))
B8: S-003 | C8: P-003 | D8: =IF($B8="","",IF($C8="","",IFERROR(IF(INDEX('PEOPLE + BUDGETS'!$C$6:$C$105,MATCH($C8,'PEOPLE + BUDGETS'!$B$6:$B$105,0))="","",INDEX('PEOPLE + BUDGETS'!$C$6:$C$105,MATCH($C8,'PEOPLE + BUDGETS'!$B$6:$B$105,0))),""))) | E8: Beeswax hand balm | F8: Stockings | G8: Apothecary Row | H8: 1 | I8: 18 | J8: =IF($B8="","",ROUND($H8*$I8,2)) | L8: In Cart | M8: No | N8: EXAMPLE — DELETE ME | O8: =IF($B8="",0,IF(COUNTIF('STOCKING STUFFERS'!$B$6:$B$155,$B8)>1,1,0)) | P8: =IF(OR(N($J8)>0,N($K8)>0),IF($F8="",1,IF(COUNTIF('MASTER BUDGET'!$D$6:$D$25,$F8)=0,1,0)),0) | Q8: =IF($C8="",0,IF(COUNTIF('PEOPLE + BUDGETS'!$B$6:$B$105,$C8)=0,1,0))
D9: =IF($B9="","",IF($C9="","",IFERROR(IF(INDEX('PEOPLE + BUDGETS'!$C$6:$C$105,MATCH($C9,'PEOPLE + BUDGETS'!$B$6:$B$105,0))="","",INDEX('PEOPLE + BUDGETS'!$C$6:$C$105,MATCH($C9,'PEOPLE + BUDGETS'!$B$6:$B$105,0))),""))) | J9: =IF($B9="","",ROUND($H9*$I9,2)) | O9: =IF($B9="",0,IF(COUNTIF('STOCKING STUFFERS'!$B$6:$B$155,$B9)>1,1,0)) | P9: =IF(OR(N($J9)>0,N($K9)>0),IF($F9="",1,IF(COUNTIF('MASTER BUDGET'!$D$6:$D$25,$F9)=0,1,0)),0) | Q9: =IF($C9="",0,IF(COUNTIF('PEOPLE + BUDGETS'!$B$6:$B$105,$C9)=0,1,0))
D10: =IF($B10="","",IF($C10="","",IFERROR(IF(INDEX('PEOPLE + BUDGETS'!$C$6:$C$105,MATCH($C10,'PEOPLE + BUDGETS'!$B$6:$B$105,0))="","",INDEX('PEOPLE + BUDGETS'!$C$6:$C$105,MATCH($C10,'PEOPLE + BUDGETS'!$B$6:$B$105,0))),""))) | J10: =IF($B10="","",ROUND($H10*$I10,2)) | O10: =IF($B10="",0,IF(COUNTIF('STOCKING STUFFERS'!$B$6:$B$155,$B10)>1,1,0)) | P10: =IF(OR(N($J10)>0,N($K10)>0),IF($F10="",1,IF(COUNTIF('MASTER BUDGET'!$D$6:$D$25,$F10)=0,1,0)),0) | Q10: =IF($C10="",0,IF(COUNTIF('PEOPLE + BUDGETS'!$B$6:$B$105,$C10)=0,1,0))
D11: =IF($B11="","",IF($C11="","",IFERROR(IF(INDEX('PEOPLE + BUDGETS'!$C$6:$C$105,MATCH($C11,'PEOPLE + BUDGETS'!$B$6:$B$105,0))="","",INDEX('PEOPLE + BUDGETS'!$C$6:$C$105,MATCH($C11,'PEOPLE + BUDGETS'!$B$6:$B$105,0))),""))) | J11: =IF($B11="","",ROUND($H11*$I11,2)) | O11: =IF($B11="",0,IF(COUNTIF('STOCKING STUFFERS'!$B$6:$B$155,$B11)>1,1,0)) | P11: =IF(OR(N($J11)>0,N($K11)>0),IF($F11="",1,IF(COUNTIF('MASTER BUDGET'!$D$6:$D$25,$F11)=0,1,0)),0) | Q11: =IF($C11="",0,IF(COUNTIF('PEOPLE + BUDGETS'!$B$6:$B$105,$C11)=0,1,0))
D12: =IF($B12="","",IF($C12="","",IFERROR(IF(INDEX('PEOPLE + BUDGETS'!$C$6:$C$105,MATCH($C12,'PEOPLE + BUDGETS'!$B$6:$B$105,0))="","",INDEX('PEOPLE + BUDGETS'!$C$6:$C$105,MATCH($C12,'PEOPLE + BUDGETS'!$B$6:$B$105,0))),""))) | J12: =IF($B12="","",ROUND($H12*$I12,2)) | O12: =IF($B12="",0,IF(COUNTIF('STOCKING STUFFERS'!$B$6:$B$155,$B12)>1,1,0)) | P12: =IF(OR(N($J12)>0,N($K12)>0),IF($F12="",1,IF(COUNTIF('MASTER BUDGET'!$D$6:$D$25,$F12)=0,1,0)),0) | Q12: =IF($C12="",0,IF(COUNTIF('PEOPLE + BUDGETS'!$B$6:$B$105,$C12)=0,1,0))
D13: =IF($B13="","",IF($C13="","",IFERROR(IF(INDEX('PEOPLE + BUDGETS'!$C$6:$C$105,MATCH($C13,'PEOPLE + BUDGETS'!$B$6:$B$105,0))="","",INDEX('PEOPLE + BUDGETS'!$C$6:$C$105,MATCH($C13,'PEOPLE + BUDGETS'!$B$6:$B$105,0))),""))) | J13: =IF($B13="","",ROUND($H13*$I13,2)) | O13: =IF($B13="",0,IF(COUNTIF('STOCKING STUFFERS'!$B$6:$B$155,$B13)>1,1,0)) | P13: =IF(OR(N($J13)>0,N($K13)>0),IF($F13="",1,IF(COUNTIF('MASTER BUDGET'!$D$6:$D$25,$F13)=0,1,0)),0) | Q13: =IF($C13="",0,IF(COUNTIF('PEOPLE + BUDGETS'!$B$6:$B$105,$C13)=0,1,0))
D14: =IF($B14="","",IF($C14="","",IFERROR(IF(INDEX('PEOPLE + BUDGETS'!$C$6:$C$105,MATCH($C14,'PEOPLE + BUDGETS'!$B$6:$B$105,0))="","",INDEX('PEOPLE + BUDGETS'!$C$6:$C$105,MATCH($C14,'PEOPLE + BUDGETS'!$B$6:$B$105,0))),""))) | J14: =IF($B14="","",ROUND($H14*$I14,2)) | O14: =IF($B14="",0,IF(COUNTIF('STOCKING STUFFERS'!$B$6:$B$155,$B14)>1,1,0)) | P14: =IF(OR(N($J14)>0,N($K14)>0),IF($F14="",1,IF(COUNTIF('MASTER BUDGET'!$D$6:$D$25,$F14)=0,1,0)),0) | Q14: =IF($C14="",0,IF(COUNTIF('PEOPLE + BUDGETS'!$B$6:$B$105,$C14)=0,1,0))
D15: =IF($B15="","",IF($C15="","",IFERROR(IF(INDEX('PEOPLE + BUDGETS'!$C$6:$C$105,MATCH($C15,'PEOPLE + BUDGETS'!$B$6:$B$105,0))="","",INDEX('PEOPLE + BUDGETS'!$C$6:$C$105,MATCH($C15,'PEOPLE + BUDGETS'!$B$6:$B$105,0))),""))) | J15: =IF($B15="","",ROUND($H15*$I15,2)) | O15: =IF($B15="",0,IF(COUNTIF('STOCKING STUFFERS'!$B$6:$B$155,$B15)>1,1,0)) | P15: =IF(OR(N($J15)>0,N($K15)>0),IF($F15="",1,IF(COUNTIF('MASTER BUDGET'!$D$6:$D$25,$F15)=0,1,0)),0) | Q15: =IF($C15="",0,IF(COUNTIF('PEOPLE + BUDGETS'!$B$6:$B$105,$C15)=0,1,0))
D16: =IF($B16="","",IF($C16="","",IFERROR(IF(INDEX('PEOPLE + BUDGETS'!$C$6:$C$105,MATCH($C16,'PEOPLE + BUDGETS'!$B$6:$B$105,0))="","",INDEX('PEOPLE + BUDGETS'!$C$6:$C$105,MATCH($C16,'PEOPLE + BUDGETS'!$B$6:$B$105,0))),""))) | J16: =IF($B16="","",ROUND($H16*$I16,2)) | O16: =IF($B16="",0,IF(COUNTIF('STOCKING STUFFERS'!$B$6:$B$155,$B16)>1,1,0)) | P16: =IF(OR(N($J16)>0,N($K16)>0),IF($F16="",1,IF(COUNTIF('MASTER BUDGET'!$D$6:$D$25,$F16)=0,1,0)),0) | Q16: =IF($C16="",0,IF(COUNTIF('PEOPLE + BUDGETS'!$B$6:$B$105,$C16)=0,1,0))
D17: =IF($B17="","",IF($C17="","",IFERROR(IF(INDEX('PEOPLE + BUDGETS'!$C$6:$C$105,MATCH($C17,'PEOPLE + BUDGETS'!$B$6:$B$105,0))="","",INDEX('PEOPLE + BUDGETS'!$C$6:$C$105,MATCH($C17,'PEOPLE + BUDGETS'!$B$6:$B$105,0))),""))) | J17: =IF($B17="","",ROUND($H17*$I17,2)) | O17: =IF($B17="",0,IF(COUNTIF('STOCKING STUFFERS'!$B$6:$B$155,$B17)>1,1,0)) | P17: =IF(OR(N($J17)>0,N($K17)>0),IF($F17="",1,IF(COUNTIF('MASTER BUDGET'!$D$6:$D$25,$F17)=0,1,0)),0) | Q17: =IF($C17="",0,IF(COUNTIF('PEOPLE + BUDGETS'!$B$6:$B$105,$C17)=0,1,0))
D18: =IF($B18="","",IF($C18="","",IFERROR(IF(INDEX('PEOPLE + BUDGETS'!$C$6:$C$105,MATCH($C18,'PEOPLE + BUDGETS'!$B$6:$B$105,0))="","",INDEX('PEOPLE + BUDGETS'!$C$6:$C$105,MATCH($C18,'PEOPLE + BUDGETS'!$B$6:$B$105,0))),""))) | J18: =IF($B18="","",ROUND($H18*$I18,2)) | O18: =IF($B18="",0,IF(COUNTIF('STOCKING STUFFERS'!$B$6:$B$155,$B18)>1,1,0)) | P18: =IF(OR(N($J18)>0,N($K18)>0),IF($F18="",1,IF(COUNTIF('MASTER BUDGET'!$D$6:$D$25,$F18)=0,1,0)),0) | Q18: =IF($C18="",0,IF(COUNTIF('PEOPLE + BUDGETS'!$B$6:$B$105,$C18)=0,1,0))
D19: =IF($B19="","",IF($C19="","",IFERROR(IF(INDEX('PEOPLE + BUDGETS'!$C$6:$C$105,MATCH($C19,'PEOPLE + BUDGETS'!$B$6:$B$105,0))="","",INDEX('PEOPLE + BUDGETS'!$C$6:$C$105,MATCH($C19,'PEOPLE + BUDGETS'!$B$6:$B$105,0))),""))) | J19: =IF($B19="","",ROUND($H19*$I19,2)) | O19: =IF($B19="",0,IF(COUNTIF('STOCKING STUFFERS'!$B$6:$B$155,$B19)>1,1,0)) | P19: =IF(OR(N($J19)>0,N($K19)>0),IF($F19="",1,IF(COUNTIF('MASTER BUDGET'!$D$6:$D$25,$F19)=0,1,0)),0) | Q19: =IF($C19="",0,IF(COUNTIF('PEOPLE + BUDGETS'!$B$6:$B$105,$C19)=0,1,0))
D20: =IF($B20="","",IF($C20="","",IFERROR(IF(INDEX('PEOPLE + BUDGETS'!$C$6:$C$105,MATCH($C20,'PEOPLE + BUDGETS'!$B$6:$B$105,0))="","",INDEX('PEOPLE + BUDGETS'!$C$6:$C$105,MATCH($C20,'PEOPLE + BUDGETS'!$B$6:$B$105,0))),""))) | J20: =IF($B20="","",ROUND($H20*$I20,2)) | O20: =IF($B20="",0,IF(COUNTIF('STOCKING STUFFERS'!$B$6:$B$155,$B20)>1,1,0)) | P20: =IF(OR(N($J20)>0,N($K20)>0),IF($F20="",1,IF(COUNTIF('MASTER BUDGET'!$D$6:$D$25,$F20)=0,1,0)),0) | Q20: =IF($C20="",0,IF(COUNTIF('PEOPLE + BUDGETS'!$B$6:$B$105,$C20)=0,1,0))
... D155: =IF($B155="","",IF($C155="","",IFERROR(IF(INDEX('PEOPLE + BUDGETS'!$C$6:$C$105,MATCH($C155,'PEOPLE + BUDGETS'!$B$6:$B$105,0))="","",INDEX('PEOPLE + BUDGETS'!$C$6:$C$105,MATCH($C155,'PEOPLE + BUDGETS'!$B$6:$B$105,0))),""))) | J155: =IF($B155="","",ROUND($H155*$I155,2)) | O155: =IF($B155="",0,IF(COUNTIF('STOCKING STUFFERS'!$B$6:$B$155,$B155)>1,1,0)) | P155: =IF(OR(N($J155)>0,N($K155)>0),IF($F155="",1,IF(COUNTIF('MASTER BUDGET'!$D$6:$D$25,$F155)=0,1,0)),0) | Q155: =IF($C155="",0,IF(COUNTIF('PEOPLE + BUDGETS'!$B$6:$B$105,$C155)=0,1,0))

Sheet ONLINE ORDERS
B1: Dashboard | D1: Start here | E1: Calendar | F1: Budget | G1: All sheets
B2: ONLINE ORDERS
B3: What is on its way, when it should arrive, and what still needs chasing.
B4: Cream cells are yours to fill in · pale green cells calculate themselves · amber rows are examples you can delete
B5: Order ID | C5: Store | D5: Ordered | E5: Expected | F5: Person ID | G5: Recipient | H5: Items | I5: Order total | J5: Tracking number or link | K5: Status | L5: Arrived on | M5: Arrived? | N5: Issue | O5: Return by | P5: Refund expected | Q5: Refund received? | R5: Attention | S5: Return window | T5: Notes | U5: QA · duplicate ID | V5: QA · Person ID exists
B6: O-001 | C6: Levens Pottery | D6: 46340 | E6: 46354 | F6: P-001 | G6: =IF($B6="","",IF($F6="","",IFERROR(IF(INDEX('PEOPLE + BUDGETS'!$C$6:$C$105,MATCH($F6,'PEOPLE + BUDGETS'!$B$6:$B$105,0))="","",INDEX('PEOPLE + BUDGETS'!$C$6:$C$105,MATCH($F6,'PEOPLE + BUDGETS'!$B$6:$B$105,0))),""))) | H6: Stoneware jug | I6: 175.85 | J6: RM-4471-2290-GB | K6: Arrived | L6: 46352 | M6: =IF($B6="","",IF(OR($K6="Arrived",$L6<>""),"Yes","No")) | N6: None | O6: 46401 | Q6: No | R6: =IF($B6="","",IF(OR($K6="Cancelled",$K6="Returned"),"CLOSED",IF($M6="Yes","ARRIVED",IF($E6="","MISSING DATE",IF($E6<TODAY(),"LATE",IF(AND($J6="",$E6-TODAY()<=Set_ShipWindow),"NO TRACKING","ON TRACK")))))) | S6: =IF($B6="","",IF($O6="","—",IF($O6<TODAY(),"CLOSED",IF($O6-TODAY()<=7,"CLOSING SOON","OPEN")))) | T6: EXAMPLE — DELETE ME | U6: =IF($B6="",0,IF(COUNTIF('ONLINE ORDERS'!$B$6:$B$155,$B6)>1,1,0)) | V6: =IF($F6="",0,IF(COUNTIF('PEOPLE + BUDGETS'!$B$6:$B$105,$F6)=0,1,0))
B7: O-002 | C7: Marine Charts Co. | D7: 46356 | E7: 46364 | F7: P-002 | G7: =IF($B7="","",IF($F7="","",IFERROR(IF(INDEX('PEOPLE + BUDGETS'!$C$6:$C$105,MATCH($F7,'PEOPLE + BUDGETS'!$B$6:$B$105,0))="","",INDEX('PEOPLE + BUDGETS'!$C$6:$C$105,MATCH($F7,'PEOPLE + BUDGETS'!$B$6:$B$105,0))),""))) | H7: Framed chart | I7: 226 | K7: Ordered | M7: =IF($B7="","",IF(OR($K7="Arrived",$L7<>""),"Yes","No")) | N7: None | Q7: No | R7: =IF($B7="","",IF(OR($K7="Cancelled",$K7="Returned"),"CLOSED",IF($M7="Yes","ARRIVED",IF($E7="","MISSING DATE",IF($E7<TODAY(),"LATE",IF(AND($J7="",$E7-TODAY()<=Set_ShipWindow),"NO TRACKING","ON TRACK")))))) | S7: =IF($B7="","",IF($O7="","—",IF($O7<TODAY(),"CLOSED",IF($O7-TODAY()<=7,"CLOSING SOON","OPEN")))) | T7: EXAMPLE — DELETE ME | U7: =IF($B7="",0,IF(COUNTIF('ONLINE ORDERS'!$B$6:$B$155,$B7)>1,1,0)) | V7: =IF($F7="",0,IF(COUNTIF('PEOPLE + BUDGETS'!$B$6:$B$105,$F7)=0,1,0))
B8: O-003 | C8: Linen House | D8: 46344 | E8: 46356 | G8: =IF($B8="","",IF($F8="","",IFERROR(IF(INDEX('PEOPLE + BUDGETS'!$C$6:$C$105,MATCH($F8,'PEOPLE + BUDGETS'!$B$6:$B$105,0))="","",INDEX('PEOPLE + BUDGETS'!$C$6:$C$105,MATCH($F8,'PEOPLE + BUDGETS'!$B$6:$B$105,0))),""))) | H8: Damask tablecloth, 3m | I8: 240 | J8: DPD-88120344 | K8: Delayed | M8: =IF($B8="","",IF(OR($K8="Arrived",$L8<>""),"Yes","No")) | N8: Late | O8: 46386 | P8: 240 | Q8: No | R8: =IF($B8="","",IF(OR($K8="Cancelled",$K8="Returned"),"CLOSED",IF($M8="Yes","ARRIVED",IF($E8="","MISSING DATE",IF($E8<TODAY(),"LATE",IF(AND($J8="",$E8-TODAY()<=Set_ShipWindow),"NO TRACKING","ON TRACK")))))) | S8: =IF($B8="","",IF($O8="","—",IF($O8<TODAY(),"CLOSED",IF($O8-TODAY()<=7,"CLOSING SOON","OPEN")))) | T8: EXAMPLE — DELETE ME | U8: =IF($B8="",0,IF(COUNTIF('ONLINE ORDERS'!$B$6:$B$155,$B8)>1,1,0)) | V8: =IF($F8="",0,IF(COUNTIF('PEOPLE + BUDGETS'!$B$6:$B$105,$F8)=0,1,0))
G9: =IF($B9="","",IF($F9="","",IFERROR(IF(INDEX('PEOPLE + BUDGETS'!$C$6:$C$105,MATCH($F9,'PEOPLE + BUDGETS'!$B$6:$B$105,0))="","",INDEX('PEOPLE + BUDGETS'!$C$6:$C$105,MATCH($F9,'PEOPLE + BUDGETS'!$B$6:$B$105,0))),""))) | M9: =IF($B9="","",IF(OR($K9="Arrived",$L9<>""),"Yes","No")) | R9: =IF($B9="","",IF(OR($K9="Cancelled",$K9="Returned"),"CLOSED",IF($M9="Yes","ARRIVED",IF($E9="","MISSING DATE",IF($E9<TODAY(),"LATE",IF(AND($J9="",$E9-TODAY()<=Set_ShipWindow),"NO TRACKING","ON TRACK")))))) | S9: =IF($B9="","",IF($O9="","—",IF($O9<TODAY(),"CLOSED",IF($O9-TODAY()<=7,"CLOSING SOON","OPEN")))) | U9: =IF($B9="",0,IF(COUNTIF('ONLINE ORDERS'!$B$6:$B$155,$B9)>1,1,0)) | V9: =IF($F9="",0,IF(COUNTIF('PEOPLE + BUDGETS'!$B$6:$B$105,$F9)=0,1,0))
G10: =IF($B10="","",IF($F10="","",IFERROR(IF(INDEX('PEOPLE + BUDGETS'!$C$6:$C$105,MATCH($F10,'PEOPLE + BUDGETS'!$B$6:$B$105,0))="","",INDEX('PEOPLE + BUDGETS'!$C$6:$C$105,MATCH($F10,'PEOPLE + BUDGETS'!$B$6:$B$105,0))),""))) | M10: =IF($B10="","",IF(OR($K10="Arrived",$L10<>""),"Yes","No")) | R10: =IF($B10="","",IF(OR($K10="Cancelled",$K10="Returned"),"CLOSED",IF($M10="Yes","ARRIVED",IF($E10="","MISSING DATE",IF($E10<TODAY(),"LATE",IF(AND($J10="",$E10-TODAY()<=Set_ShipWindow),"NO TRACKING","ON TRACK")))))) | S10: =IF($B10="","",IF($O10="","—",IF($O10<TODAY(),"CLOSED",IF($O10-TODAY()<=7,"CLOSING SOON","OPEN")))) | U10: =IF($B10="",0,IF(COUNTIF('ONLINE ORDERS'!$B$6:$B$155,$B10)>1,1,0)) | V10: =IF($F10="",0,IF(COUNTIF('PEOPLE + BUDGETS'!$B$6:$B$105,$F10)=0,1,0))
G11: =IF($B11="","",IF($F11="","",IFERROR(IF(INDEX('PEOPLE + BUDGETS'!$C$6:$C$105,MATCH($F11,'PEOPLE + BUDGETS'!$B$6:$B$105,0))="","",INDEX('PEOPLE + BUDGETS'!$C$6:$C$105,MATCH($F11,'PEOPLE + BUDGETS'!$B$6:$B$105,0))),""))) | M11: =IF($B11="","",IF(OR($K11="Arrived",$L11<>""),"Yes","No")) | R11: =IF($B11="","",IF(OR($K11="Cancelled",$K11="Returned"),"CLOSED",IF($M11="Yes","ARRIVED",IF($E11="","MISSING DATE",IF($E11<TODAY(),"LATE",IF(AND($J11="",$E11-TODAY()<=Set_ShipWindow),"NO TRACKING","ON TRACK")))))) | S11: =IF($B11="","",IF($O11="","—",IF($O11<TODAY(),"CLOSED",IF($O11-TODAY()<=7,"CLOSING SOON","OPEN")))) | U11: =IF($B11="",0,IF(COUNTIF('ONLINE ORDERS'!$B$6:$B$155,$B11)>1,1,0)) | V11: =IF($F11="",0,IF(COUNTIF('PEOPLE + BUDGETS'!$B$6:$B$105,$F11)=0,1,0))
G12: =IF($B12="","",IF($F12="","",IFERROR(IF(INDEX('PEOPLE + BUDGETS'!$C$6:$C$105,MATCH($F12,'PEOPLE + BUDGETS'!$B$6:$B$105,0))="","",INDEX('PEOPLE + BUDGETS'!$C$6:$C$105,MATCH($F12,'PEOPLE + BUDGETS'!$B$6:$B$105,0))),""))) | M12: =IF($B12="","",IF(OR($K12="Arrived",$L12<>""),"Yes","No")) | R12: =IF($B12="","",IF(OR($K12="Cancelled",$K12="Returned"),"CLOSED",IF($M12="Yes","ARRIVED",IF($E12="","MISSING DATE",IF($E12<TODAY(),"LATE",IF(AND($J12="",$E12-TODAY()<=Set_ShipWindow),"NO TRACKING","ON TRACK")))))) | S12: =IF($B12="","",IF($O12="","—",IF($O12<TODAY(),"CLOSED",IF($O12-TODAY()<=7,"CLOSING SOON","OPEN")))) | U12: =IF($B12="",0,IF(COUNTIF('ONLINE ORDERS'!$B$6:$B$155,$B12)>1,1,0)) | V12: =IF($F12="",0,IF(COUNTIF('PEOPLE + BUDGETS'!$B$6:$B$105,$F12)=0,1,0))
G13: =IF($B13="","",IF($F13="","",IFERROR(IF(INDEX('PEOPLE + BUDGETS'!$C$6:$C$105,MATCH($F13,'PEOPLE + BUDGETS'!$B$6:$B$105,0))="","",INDEX('PEOPLE + BUDGETS'!$C$6:$C$105,MATCH($F13,'PEOPLE + BUDGETS'!$B$6:$B$105,0))),""))) | M13: =IF($B13="","",IF(OR($K13="Arrived",$L13<>""),"Yes","No")) | R13: =IF($B13="","",IF(OR($K13="Cancelled",$K13="Returned"),"CLOSED",IF($M13="Yes","ARRIVED",IF($E13="","MISSING DATE",IF($E13<TODAY(),"LATE",IF(AND($J13="",$E13-TODAY()<=Set_ShipWindow),"NO TRACKING","ON TRACK")))))) | S13: =IF($B13="","",IF($O13="","—",IF($O13<TODAY(),"CLOSED",IF($O13-TODAY()<=7,"CLOSING SOON","OPEN")))) | U13: =IF($B13="",0,IF(COUNTIF('ONLINE ORDERS'!$B$6:$B$155,$B13)>1,1,0)) | V13: =IF($F13="",0,IF(COUNTIF('PEOPLE + BUDGETS'!$B$6:$B$105,$F13)=0,1,0))
G14: =IF($B14="","",IF($F14="","",IFERROR(IF(INDEX('PEOPLE + BUDGETS'!$C$6:$C$105,MATCH($F14,'PEOPLE + BUDGETS'!$B$6:$B$105,0))="","",INDEX('PEOPLE + BUDGETS'!$C$6:$C$105,MATCH($F14,'PEOPLE + BUDGETS'!$B$6:$B$105,0))),""))) | M14: =IF($B14="","",IF(OR($K14="Arrived",$L14<>""),"Yes","No")) | R14: =IF($B14="","",IF(OR($K14="Cancelled",$K14="Returned"),"CLOSED",IF($M14="Yes","ARRIVED",IF($E14="","MISSING DATE",IF($E14<TODAY(),"LATE",IF(AND($J14="",$E14-TODAY()<=Set_ShipWindow),"NO TRACKING","ON TRACK")))))) | S14: =IF($B14="","",IF($O14="","—",IF($O14<TODAY(),"CLOSED",IF($O14-TODAY()<=7,"CLOSING SOON","OPEN")))) | U14: =IF($B14="",0,IF(COUNTIF('ONLINE ORDERS'!$B$6:$B$155,$B14)>1,1,0)) | V14: =IF($F14="",0,IF(COUNTIF('PEOPLE + BUDGETS'!$B$6:$B$105,$F14)=0,1,0))
G15: =IF($B15="","",IF($F15="","",IFERROR(IF(INDEX('PEOPLE + BUDGETS'!$C$6:$C$105,MATCH($F15,'PEOPLE + BUDGETS'!$B$6:$B$105,0))="","",INDEX('PEOPLE + BUDGETS'!$C$6:$C$105,MATCH($F15,'PEOPLE + BUDGETS'!$B$6:$B$105,0))),""))) | M15: =IF($B15="","",IF(OR($K15="Arrived",$L15<>""),"Yes","No")) | R15: =IF($B15="","",IF(OR($K15="Cancelled",$K15="Returned"),"CLOSED",IF($M15="Yes","ARRIVED",IF($E15="","MISSING DATE",IF($E15<TODAY(),"LATE",IF(AND($J15="",$E15-TODAY()<=Set_ShipWindow),"NO TRACKING","ON TRACK")))))) | S15: =IF($B15="","",IF($O15="","—",IF($O15<TODAY(),"CLOSED",IF($O15-TODAY()<=7,"CLOSING SOON","OPEN")))) | U15: =IF($B15="",0,IF(COUNTIF('ONLINE ORDERS'!$B$6:$B$155,$B15)>1,1,0)) | V15: =IF($F15="",0,IF(COUNTIF('PEOPLE + BUDGETS'!$B$6:$B$105,$F15)=0,1,0))
G16: =IF($B16="","",IF($F16="","",IFERROR(IF(INDEX('PEOPLE + BUDGETS'!$C$6:$C$105,MATCH($F16,'PEOPLE + BUDGETS'!$B$6:$B$105,0))="","",INDEX('PEOPLE + BUDGETS'!$C$6:$C$105,MATCH($F16,'PEOPLE + BUDGETS'!$B$6:$B$105,0))),""))) | M16: =IF($B16="","",IF(OR($K16="Arrived",$L16<>""),"Yes","No")) | R16: =IF($B16="","",IF(OR($K16="Cancelled",$K16="Returned"),"CLOSED",IF($M16="Yes","ARRIVED",IF($E16="","MISSING DATE",IF($E16<TODAY(),"LATE",IF(AND($J16="",$E16-TODAY()<=Set_ShipWindow),"NO TRACKING","ON TRACK")))))) | S16: =IF($B16="","",IF($O16="","—",IF($O16<TODAY(),"CLOSED",IF($O16-TODAY()<=7,"CLOSING SOON","OPEN")))) | U16: =IF($B16="",0,IF(COUNTIF('ONLINE ORDERS'!$B$6:$B$155,$B16)>1,1,0)) | V16: =IF($F16="",0,IF(COUNTIF('PEOPLE + BUDGETS'!$B$6:$B$105,$F16)=0,1,0))
G17: =IF($B17="","",IF($F17="","",IFERROR(IF(INDEX('PEOPLE + BUDGETS'!$C$6:$C$105,MATCH($F17,'PEOPLE + BUDGETS'!$B$6:$B$105,0))="","",INDEX('PEOPLE + BUDGETS'!$C$6:$C$105,MATCH($F17,'PEOPLE + BUDGETS'!$B$6:$B$105,0))),""))) | M17: =IF($B17="","",IF(OR($K17="Arrived",$L17<>""),"Yes","No")) | R17: =IF($B17="","",IF(OR($K17="Cancelled",$K17="Returned"),"CLOSED",IF($M17="Yes","ARRIVED",IF($E17="","MISSING DATE",IF($E17<TODAY(),"LATE",IF(AND($J17="",$E17-TODAY()<=Set_ShipWindow),"NO TRACKING","ON TRACK")))))) | S17: =IF($B17="","",IF($O17="","—",IF($O17<TODAY(),"CLOSED",IF($O17-TODAY()<=7,"CLOSING SOON","OPEN")))) | U17: =IF($B17="",0,IF(COUNTIF('ONLINE ORDERS'!$B$6:$B$155,$B17)>1,1,0)) | V17: =IF($F17="",0,IF(COUNTIF('PEOPLE + BUDGETS'!$B$6:$B$105,$F17)=0,1,0))
G18: =IF($B18="","",IF($F18="","",IFERROR(IF(INDEX('PEOPLE + BUDGETS'!$C$6:$C$105,MATCH($F18,'PEOPLE + BUDGETS'!$B$6:$B$105,0))="","",INDEX('PEOPLE + BUDGETS'!$C$6:$C$105,MATCH($F18,'PEOPLE + BUDGETS'!$B$6:$B$105,0))),""))) | M18: =IF($B18="","",IF(OR($K18="Arrived",$L18<>""),"Yes","No")) | R18: =IF($B18="","",IF(OR($K18="Cancelled",$K18="Returned"),"CLOSED",IF($M18="Yes","ARRIVED",IF($E18="","MISSING DATE",IF($E18<TODAY(),"LATE",IF(AND($J18="",$E18-TODAY()<=Set_ShipWindow),"NO TRACKING","ON TRACK")))))) | S18: =IF($B18="","",IF($O18="","—",IF($O18<TODAY(),"CLOSED",IF($O18-TODAY()<=7,"CLOSING SOON","OPEN")))) | U18: =IF($B18="",0,IF(COUNTIF('ONLINE ORDERS'!$B$6:$B$155,$B18)>1,1,0)) | V18: =IF($F18="",0,IF(COUNTIF('PEOPLE + BUDGETS'!$B$6:$B$105,$F18)=0,1,0))
G19: =IF($B19="","",IF($F19="","",IFERROR(IF(INDEX('PEOPLE + BUDGETS'!$C$6:$C$105,MATCH($F19,'PEOPLE + BUDGETS'!$B$6:$B$105,0))="","",INDEX('PEOPLE + BUDGETS'!$C$6:$C$105,MATCH($F19,'PEOPLE + BUDGETS'!$B$6:$B$105,0))),""))) | M19: =IF($B19="","",IF(OR($K19="Arrived",$L19<>""),"Yes","No")) | R19: =IF($B19="","",IF(OR($K19="Cancelled",$K19="Returned"),"CLOSED",IF($M19="Yes","ARRIVED",IF($E19="","MISSING DATE",IF($E19<TODAY(),"LATE",IF(AND($J19="",$E19-TODAY()<=Set_ShipWindow),"NO TRACKING","ON TRACK")))))) | S19: =IF($B19="","",IF($O19="","—",IF($O19<TODAY(),"CLOSED",IF($O19-TODAY()<=7,"CLOSING SOON","OPEN")))) | U19: =IF($B19="",0,IF(COUNTIF('ONLINE ORDERS'!$B$6:$B$155,$B19)>1,1,0)) | V19: =IF($F19="",0,IF(COUNTIF('PEOPLE + BUDGETS'!$B$6:$B$105,$F19)=0,1,0))
G20: =IF($B20="","",IF($F20="","",IFERROR(IF(INDEX('PEOPLE + BUDGETS'!$C$6:$C$105,MATCH($F20,'PEOPLE + BUDGETS'!$B$6:$B$105,0))="","",INDEX('PEOPLE + BUDGETS'!$C$6:$C$105,MATCH($F20,'PEOPLE + BUDGETS'!$B$6:$B$105,0))),""))) | M20: =IF($B20="","",IF(OR($K20="Arrived",$L20<>""),"Yes","No")) | R20: =IF($B20="","",IF(OR($K20="Cancelled",$K20="Returned"),"CLOSED",IF($M20="Yes","ARRIVED",IF($E20="","MISSING DATE",IF($E20<TODAY(),"LATE",IF(AND($J20="",$E20-TODAY()<=Set_ShipWindow),"NO TRACKING","ON TRACK")))))) | S20: =IF($B20="","",IF($O20="","—",IF($O20<TODAY(),"CLOSED",IF($O20-TODAY()<=7,"CLOSING SOON","OPEN")))) | U20: =IF($B20="",0,IF(COUNTIF('ONLINE ORDERS'!$B$6:$B$155,$B20)>1,1,0)) | V20: =IF($F20="",0,IF(COUNTIF('PEOPLE + BUDGETS'!$B$6:$B$105,$F20)=0,1,0))
... G155: =IF($B155="","",IF($F155="","",IFERROR(IF(INDEX('PEOPLE + BUDGETS'!$C$6:$C$105,MATCH($F155,'PEOPLE + BUDGETS'!$B$6:$B$105,0))="","",INDEX('PEOPLE + BUDGETS'!$C$6:$C$105,MATCH($F155,'PEOPLE + BUDGETS'!$B$6:$B$105,0))),""))) | M155: =IF($B155="","",IF(OR($K155="Arrived",$L155<>""),"Yes","No")) | R155: =IF($B155="","",IF(OR($K155="Cancelled",$K155="Returned"),"CLOSED",IF($M155="Yes","ARRIVED",IF($E155="","MISSING DATE",IF($E155<TODAY(),"LATE",IF(AND($J155="",$E155-TODAY()<=Set_ShipWindow),"NO TRACKING","ON TRACK")))))) | S155: =IF($B155="","",IF($O155="","—",IF($O155<TODAY(),"CLOSED",IF($O155-TODAY()<=7,"CLOSING SOON","OPEN")))) | U155: =IF($B155="",0,IF(COUNTIF('ONLINE ORDERS'!$B$6:$B$155,$B155)>1,1,0)) | V155: =IF($F155="",0,IF(COUNTIF('PEOPLE + BUDGETS'!$B$6:$B$105,$F155)=0,1,0))
B157: Orders do not add to the budget. A gift's actual cost is the single record of what you spent, so counting the order as well would double it.

Sheet RETURNS + EXCHANGES
B1: Dashboard | D1: Start here | F1: Calendar | G1: Budget | H1: All sheets
B2: RETURNS + EXCHANGES
B3: What went back, what you are owed, and what has actually landed.
B4: Cream cells are yours to fill in · pale green cells calculate themselves · amber rows are examples you can delete
B5: Return ID | C5: Order ID | D5: Gift ID | E5: Store (if bought in a shop) | F5: Store | G5: Recipient | H5: Item (if bought in a shop) | I5: Item | J5: Reason | K5: Budget category | L5: Sent back | M5: Return by | N5: Status | O5: Refund expected | P5: Refund received? | Q5: Amount received | R5: Counted refund | S5: Attention | T5: Notes | U5: QA · duplicate ID | V5: QA · Order ID exists | W5: QA · Gift ID exists
B6: R-001 | C6: O-003 | F6: =IF($B6="","",IF($C6="",$E6,IF($C6="","",IFERROR(IF(INDEX('ONLINE ORDERS'!$C$6:$C$155,MATCH($C6,'ONLINE ORDERS'!$B$6:$B$155,0))="","",INDEX('ONLINE ORDERS'!$C$6:$C$155,MATCH($C6,'ONLINE ORDERS'!$B$6:$B$155,0))),"")))) | G6: =IF($B6="","",IF($C6="","",IFERROR(IF(INDEX('ONLINE ORDERS'!$G$6:$G$155,MATCH($C6,'ONLINE ORDERS'!$B$6:$B$155,0))="","",INDEX('ONLINE ORDERS'!$G$6:$G$155,MATCH($C6,'ONLINE ORDERS'!$B$6:$B$155,0))),""))) | I6: =IF($B6="","",IF($C6="",$H6,IF($C6="","",IFERROR(IF(INDEX('ONLINE ORDERS'!$H$6:$H$155,MATCH($C6,'ONLINE ORDERS'!$B$6:$B$155,0))="","",INDEX('ONLINE ORDERS'!$H$6:$H$155,MATCH($C6,'ONLINE ORDERS'!$B$6:$B$155,0))),"")))) | J6: Damaged | K6: Hosting | L6: 46358 | M6: =IF($B6="","",IF($C6="","",IFERROR(IF(INDEX('ONLINE ORDERS'!$O$6:$O$155,MATCH($C6,'ONLINE ORDERS'!$B$6:$B$155,0))="","",INDEX('ONLINE ORDERS'!$O$6:$O$155,MATCH($C6,'ONLINE ORDERS'!$B$6:$B$155,0))),""))) | N6: In transit | O6: 240 | P6: No | R6: =IF($B6="","",IF($P6="Yes",IF($Q6="",$O6,$Q6),0)) | S6: =IF($B6="","",IF($P6="Yes","SETTLED",IF($M6<>"",IF($M6<TODAY(),"WINDOW CLOSED",IF($M6-TODAY()<=7,"RETURN THIS WEEK","AWAITING REFUND")),"AWAITING REFUND"))) | T6: EXAMPLE — DELETE ME · a refund you are still owed does not change what you have spent | U6: =IF($B6="",0,IF(COUNTIF('RETURNS + EXCHANGES'!$B$6:$B$65,$B6)>1,1,0)) | V6: =IF($C6="",0,IF(COUNTIF('ONLINE ORDERS'!$B$6:$B$155,$C6)=0,1,0)) | W6: =IF($D6="",0,IF(COUNTIF('GIFT PLANNER'!$B$6:$B$205,$D6)=0,1,0))
B7: R-002 | E7: Apothecary Row | F7: =IF($B7="","",IF($C7="",$E7,IF($C7="","",IFERROR(IF(INDEX('ONLINE ORDERS'!$C$6:$C$155,MATCH($C7,'ONLINE ORDERS'!$B$6:$B$155,0))="","",INDEX('ONLINE ORDERS'!$C$6:$C$155,MATCH($C7,'ONLINE ORDERS'!$B$6:$B$155,0))),"")))) | G7: =IF($B7="","",IF($C7="","",IFERROR(IF(INDEX('ONLINE ORDERS'!$G$6:$G$155,MATCH($C7,'ONLINE ORDERS'!$B$6:$B$155,0))="","",INDEX('ONLINE ORDERS'!$G$6:$G$155,MATCH($C7,'ONLINE ORDERS'!$B$6:$B$155,0))),""))) | H7: Brass candlesticks, pair | I7: =IF($B7="","",IF($C7="",$H7,IF($C7="","",IFERROR(IF(INDEX('ONLINE ORDERS'!$H$6:$H$155,MATCH($C7,'ONLINE ORDERS'!$B$6:$B$155,0))="","",INDEX('ONLINE ORDERS'!$H$6:$H$155,MATCH($C7,'ONLINE ORDERS'!$B$6:$B$155,0))),"")))) | J7: Wrong item | K7: Decorations | L7: 46355 | M7: =IF($B7="","",IF($C7="","",IFERROR(IF(INDEX('ONLINE ORDERS'!$O$6:$O$155,MATCH($C7,'ONLINE ORDERS'!$B$6:$B$155,0))="","",INDEX('ONLINE ORDERS'!$O$6:$O$155,MATCH($C7,'ONLINE ORDERS'!$B$6:$B$155,0))),""))) | N7: Refunded | O7: 120 | P7: Yes | Q7: 120 | R7: =IF($B7="","",IF($P7="Yes",IF($Q7="",$O7,$Q7),0)) | S7: =IF($B7="","",IF($P7="Yes","SETTLED",IF($M7<>"",IF($M7<TODAY(),"WINDOW CLOSED",IF($M7-TODAY()<=7,"RETURN THIS WEEK","AWAITING REFUND")),"AWAITING REFUND"))) | T7: EXAMPLE — DELETE ME · bought in a shop, so there is no order to look up | U7: =IF($B7="",0,IF(COUNTIF('RETURNS + EXCHANGES'!$B$6:$B$65,$B7)>1,1,0)) | V7: =IF($C7="",0,IF(COUNTIF('ONLINE ORDERS'!$B$6:$B$155,$C7)=0,1,0)) | W7: =IF($D7="",0,IF(COUNTIF('GIFT PLANNER'!$B$6:$B$205,$D7)=0,1,0))
B8: R-003 | C8: O-003 | F8: =IF($B8="","",IF($C8="",$E8,IF($C8="","",IFERROR(IF(INDEX('ONLINE ORDERS'!$C$6:$C$155,MATCH($C8,'ONLINE ORDERS'!$B$6:$B$155,0))="","",INDEX('ONLINE ORDERS'!$C$6:$C$155,MATCH($C8,'ONLINE ORDERS'!$B$6:$B$155,0))),"")))) | G8: =IF($B8="","",IF($C8="","",IFERROR(IF(INDEX('ONLINE ORDERS'!$G$6:$G$155,MATCH($C8,'ONLINE ORDERS'!$B$6:$B$155,0))="","",INDEX('ONLINE ORDERS'!$G$6:$G$155,MATCH($C8,'ONLINE ORDERS'!$B$6:$B$155,0))),""))) | I8: =IF($B8="","",IF($C8="",$H8,IF($C8="","",IFERROR(IF(INDEX('ONLINE ORDERS'!$H$6:$H$155,MATCH($C8,'ONLINE ORDERS'!$B$6:$B$155,0))="","",INDEX('ONLINE ORDERS'!$H$6:$H$155,MATCH($C8,'ONLINE ORDERS'!$B$6:$B$155,0))),"")))) | J8: Wrong item | K8: Hosting | M8: =IF($B8="","",IF($C8="","",IFERROR(IF(INDEX('ONLINE ORDERS'!$O$6:$O$155,MATCH($C8,'ONLINE ORDERS'!$B$6:$B$155,0))="","",INDEX('ONLINE ORDERS'!$O$6:$O$155,MATCH($C8,'ONLINE ORDERS'!$B$6:$B$155,0))),""))) | N8: To return | O8: 60 | P8: No | R8: =IF($B8="","",IF($P8="Yes",IF($Q8="",$O8,$Q8),0)) | S8: =IF($B8="","",IF($P8="Yes","SETTLED",IF($M8<>"",IF($M8<TODAY(),"WINDOW CLOSED",IF($M8-TODAY()<=7,"RETURN THIS WEEK","AWAITING REFUND")),"AWAITING REFUND"))) | T8: EXAMPLE — DELETE ME · the napkins from the same order | U8: =IF($B8="",0,IF(COUNTIF('RETURNS + EXCHANGES'!$B$6:$B$65,$B8)>1,1,0)) | V8: =IF($C8="",0,IF(COUNTIF('ONLINE ORDERS'!$B$6:$B$155,$C8)=0,1,0)) | W8: =IF($D8="",0,IF(COUNTIF('GIFT PLANNER'!$B$6:$B$205,$D8)=0,1,0))
F9: =IF($B9="","",IF($C9="",$E9,IF($C9="","",IFERROR(IF(INDEX('ONLINE ORDERS'!$C$6:$C$155,MATCH($C9,'ONLINE ORDERS'!$B$6:$B$155,0))="","",INDEX('ONLINE ORDERS'!$C$6:$C$155,MATCH($C9,'ONLINE ORDERS'!$B$6:$B$155,0))),"")))) | G9: =IF($B9="","",IF($C9="","",IFERROR(IF(INDEX('ONLINE ORDERS'!$G$6:$G$155,MATCH($C9,'ONLINE ORDERS'!$B$6:$B$155,0))="","",INDEX('ONLINE ORDERS'!$G$6:$G$155,MATCH($C9,'ONLINE ORDERS'!$B$6:$B$155,0))),""))) | I9: =IF($B9="","",IF($C9="",$H9,IF($C9="","",IFERROR(IF(INDEX('ONLINE ORDERS'!$H$6:$H$155,MATCH($C9,'ONLINE ORDERS'!$B$6:$B$155,0))="","",INDEX('ONLINE ORDERS'!$H$6:$H$155,MATCH($C9,'ONLINE ORDERS'!$B$6:$B$155,0))),"")))) | M9: =IF($B9="","",IF($C9="","",IFERROR(IF(INDEX('ONLINE ORDERS'!$O$6:$O$155,MATCH($C9,'ONLINE ORDERS'!$B$6:$B$155,0))="","",INDEX('ONLINE ORDERS'!$O$6:$O$155,MATCH($C9,'ONLINE ORDERS'!$B$6:$B$155,0))),""))) | R9: =IF($B9="","",IF($P9="Yes",IF($Q9="",$O9,$Q9),0)) | S9: =IF($B9="","",IF($P9="Yes","SETTLED",IF($M9<>"",IF($M9<TODAY(),"WINDOW CLOSED",IF($M9-TODAY()<=7,"RETURN THIS WEEK","AWAITING REFUND")),"AWAITING REFUND"))) | U9: =IF($B9="",0,IF(COUNTIF('RETURNS + EXCHANGES'!$B$6:$B$65,$B9)>1,1,0)) | V9: =IF($C9="",0,IF(COUNTIF('ONLINE ORDERS'!$B$6:$B$155,$C9)=0,1,0)) | W9: =IF($D9="",0,IF(COUNTIF('GIFT PLANNER'!$B$6:$B$205,$D9)=0,1,0))
F10: =IF($B10="","",IF($C10="",$E10,IF($C10="","",IFERROR(IF(INDEX('ONLINE ORDERS'!$C$6:$C$155,MATCH($C10,'ONLINE ORDERS'!$B$6:$B$155,0))="","",INDEX('ONLINE ORDERS'!$C$6:$C$155,MATCH($C10,'ONLINE ORDERS'!$B$6:$B$155,0))),"")))) | G10: =IF($B10="","",IF($C10="","",IFERROR(IF(INDEX('ONLINE ORDERS'!$G$6:$G$155,MATCH($C10,'ONLINE ORDERS'!$B$6:$B$155,0))="","",INDEX('ONLINE ORDERS'!$G$6:$G$155,MATCH($C10,'ONLINE ORDERS'!$B$6:$B$155,0))),""))) | I10: =IF($B10="","",IF($C10="",$H10,IF($C10="","",IFERROR(IF(INDEX('ONLINE ORDERS'!$H$6:$H$155,MATCH($C10,'ONLINE ORDERS'!$B$6:$B$155,0))="","",INDEX('ONLINE ORDERS'!$H$6:$H$155,MATCH($C10,'ONLINE ORDERS'!$B$6:$B$155,0))),"")))) | M10: =IF($B10="","",IF($C10="","",IFERROR(IF(INDEX('ONLINE ORDERS'!$O$6:$O$155,MATCH($C10,'ONLINE ORDERS'!$B$6:$B$155,0))="","",INDEX('ONLINE ORDERS'!$O$6:$O$155,MATCH($C10,'ONLINE ORDERS'!$B$6:$B$155,0))),""))) | R10: =IF($B10="","",IF($P10="Yes",IF($Q10="",$O10,$Q10),0)) | S10: =IF($B10="","",IF($P10="Yes","SETTLED",IF($M10<>"",IF($M10<TODAY(),"WINDOW CLOSED",IF($M10-TODAY()<=7,"RETURN THIS WEEK","AWAITING REFUND")),"AWAITING REFUND"))) | U10: =IF($B10="",0,IF(COUNTIF('RETURNS + EXCHANGES'!$B$6:$B$65,$B10)>1,1,0)) | V10: =IF($C10="",0,IF(COUNTIF('ONLINE ORDERS'!$B$6:$B$155,$C10)=0,1,0)) | W10: =IF($D10="",0,IF(COUNTIF('GIFT PLANNER'!$B$6:$B$205,$D10)=0,1,0))
F11: =IF($B11="","",IF($C11="",$E11,IF($C11="","",IFERROR(IF(INDEX('ONLINE ORDERS'!$C$6:$C$155,MATCH($C11,'ONLINE ORDERS'!$B$6:$B$155,0))="","",INDEX('ONLINE ORDERS'!$C$6:$C$155,MATCH($C11,'ONLINE ORDERS'!$B$6:$B$155,0))),"")))) | G11: =IF($B11="","",IF($C11="","",IFERROR(IF(INDEX('ONLINE ORDERS'!$G$6:$G$155,MATCH($C11,'ONLINE ORDERS'!$B$6:$B$155,0))="","",INDEX('ONLINE ORDERS'!$G$6:$G$155,MATCH($C11,'ONLINE ORDERS'!$B$6:$B$155,0))),""))) | I11: =IF($B11="","",IF($C11="",$H11,IF($C11="","",IFERROR(IF(INDEX('ONLINE ORDERS'!$H$6:$H$155,MATCH($C11,'ONLINE ORDERS'!$B$6:$B$155,0))="","",INDEX('ONLINE ORDERS'!$H$6:$H$155,MATCH($C11,'ONLINE ORDERS'!$B$6:$B$155,0))),"")))) | M11: =IF($B11="","",IF($C11="","",IFERROR(IF(INDEX('ONLINE ORDERS'!$O$6:$O$155,MATCH($C11,'ONLINE ORDERS'!$B$6:$B$155,0))="","",INDEX('ONLINE ORDERS'!$O$6:$O$155,MATCH($C11,'ONLINE ORDERS'!$B$6:$B$155,0))),""))) | R11: =IF($B11="","",IF($P11="Yes",IF($Q11="",$O11,$Q11),0)) | S11: =IF($B11="","",IF($P11="Yes","SETTLED",IF($M11<>"",IF($M11<TODAY(),"WINDOW CLOSED",IF($M11-TODAY()<=7,"RETURN THIS WEEK","AWAITING REFUND")),"AWAITING REFUND"))) | U11: =IF($B11="",0,IF(COUNTIF('RETURNS + EXCHANGES'!$B$6:$B$65,$B11)>1,1,0)) | V11: =IF($C11="",0,IF(COUNTIF('ONLINE ORDERS'!$B$6:$B$155,$C11)=0,1,0)) | W11: =IF($D11="",0,IF(COUNTIF('GIFT PLANNER'!$B$6:$B$205,$D11)=0,1,0))
F12: =IF($B12="","",IF($C12="",$E12,IF($C12="","",IFERROR(IF(INDEX('ONLINE ORDERS'!$C$6:$C$155,MATCH($C12,'ONLINE ORDERS'!$B$6:$B$155,0))="","",INDEX('ONLINE ORDERS'!$C$6:$C$155,MATCH($C12,'ONLINE ORDERS'!$B$6:$B$155,0))),"")))) | G12: =IF($B12="","",IF($C12="","",IFERROR(IF(INDEX('ONLINE ORDERS'!$G$6:$G$155,MATCH($C12,'ONLINE ORDERS'!$B$6:$B$155,0))="","",INDEX('ONLINE ORDERS'!$G$6:$G$155,MATCH($C12,'ONLINE ORDERS'!$B$6:$B$155,0))),""))) | I12: =IF($B12="","",IF($C12="",$H12,IF($C12="","",IFERROR(IF(INDEX('ONLINE ORDERS'!$H$6:$H$155,MATCH($C12,'ONLINE ORDERS'!$B$6:$B$155,0))="","",INDEX('ONLINE ORDERS'!$H$6:$H$155,MATCH($C12,'ONLINE ORDERS'!$B$6:$B$155,0))),"")))) | M12: =IF($B12="","",IF($C12="","",IFERROR(IF(INDEX('ONLINE ORDERS'!$O$6:$O$155,MATCH($C12,'ONLINE ORDERS'!$B$6:$B$155,0))="","",INDEX('ONLINE ORDERS'!$O$6:$O$155,MATCH($C12,'ONLINE ORDERS'!$B$6:$B$155,0))),""))) | R12: =IF($B12="","",IF($P12="Yes",IF($Q12="",$O12,$Q12),0)) | S12: =IF($B12="","",IF($P12="Yes","SETTLED",IF($M12<>"",IF($M12<TODAY(),"WINDOW CLOSED",IF($M12-TODAY()<=7,"RETURN THIS WEEK","AWAITING REFUND")),"AWAITING REFUND"))) | U12: =IF($B12="",0,IF(COUNTIF('RETURNS + EXCHANGES'!$B$6:$B$65,$B12)>1,1,0)) | V12: =IF($C12="",0,IF(COUNTIF('ONLINE ORDERS'!$B$6:$B$155,$C12)=0,1,0)) | W12: =IF($D12="",0,IF(COUNTIF('GIFT PLANNER'!$B$6:$B$205,$D12)=0,1,0))
F13: =IF($B13="","",IF($C13="",$E13,IF($C13="","",IFERROR(IF(INDEX('ONLINE ORDERS'!$C$6:$C$155,MATCH($C13,'ONLINE ORDERS'!$B$6:$B$155,0))="","",INDEX('ONLINE ORDERS'!$C$6:$C$155,MATCH($C13,'ONLINE ORDERS'!$B$6:$B$155,0))),"")))) | G13: =IF($B13="","",IF($C13="","",IFERROR(IF(INDEX('ONLINE ORDERS'!$G$6:$G$155,MATCH($C13,'ONLINE ORDERS'!$B$6:$B$155,0))="","",INDEX('ONLINE ORDERS'!$G$6:$G$155,MATCH($C13,'ONLINE ORDERS'!$B$6:$B$155,0))),""))) | I13: =IF($B13="","",IF($C13="",$H13,IF($C13="","",IFERROR(IF(INDEX('ONLINE ORDERS'!$H$6:$H$155,MATCH($C13,'ONLINE ORDERS'!$B$6:$B$155,0))="","",INDEX('ONLINE ORDERS'!$H$6:$H$155,MATCH($C13,'ONLINE ORDERS'!$B$6:$B$155,0))),"")))) | M13: =IF($B13="","",IF($C13="","",IFERROR(IF(INDEX('ONLINE ORDERS'!$O$6:$O$155,MATCH($C13,'ONLINE ORDERS'!$B$6:$B$155,0))="","",INDEX('ONLINE ORDERS'!$O$6:$O$155,MATCH($C13,'ONLINE ORDERS'!$B$6:$B$155,0))),""))) | R13: =IF($B13="","",IF($P13="Yes",IF($Q13="",$O13,$Q13),0)) | S13: =IF($B13="","",IF($P13="Yes","SETTLED",IF($M13<>"",IF($M13<TODAY(),"WINDOW CLOSED",IF($M13-TODAY()<=7,"RETURN THIS WEEK","AWAITING REFUND")),"AWAITING REFUND"))) | U13: =IF($B13="",0,IF(COUNTIF('RETURNS + EXCHANGES'!$B$6:$B$65,$B13)>1,1,0)) | V13: =IF($C13="",0,IF(COUNTIF('ONLINE ORDERS'!$B$6:$B$155,$C13)=0,1,0)) | W13: =IF($D13="",0,IF(COUNTIF('GIFT PLANNER'!$B$6:$B$205,$D13)=0,1,0))
F14: =IF($B14="","",IF($C14="",$E14,IF($C14="","",IFERROR(IF(INDEX('ONLINE ORDERS'!$C$6:$C$155,MATCH($C14,'ONLINE ORDERS'!$B$6:$B$155,0))="","",INDEX('ONLINE ORDERS'!$C$6:$C$155,MATCH($C14,'ONLINE ORDERS'!$B$6:$B$155,0))),"")))) | G14: =IF($B14="","",IF($C14="","",IFERROR(IF(INDEX('ONLINE ORDERS'!$G$6:$G$155,MATCH($C14,'ONLINE ORDERS'!$B$6:$B$155,0))="","",INDEX('ONLINE ORDERS'!$G$6:$G$155,MATCH($C14,'ONLINE ORDERS'!$B$6:$B$155,0))),""))) | I14: =IF($B14="","",IF($C14="",$H14,IF($C14="","",IFERROR(IF(INDEX('ONLINE ORDERS'!$H$6:$H$155,MATCH($C14,'ONLINE ORDERS'!$B$6:$B$155,0))="","",INDEX('ONLINE ORDERS'!$H$6:$H$155,MATCH($C14,'ONLINE ORDERS'!$B$6:$B$155,0))),"")))) | M14: =IF($B14="","",IF($C14="","",IFERROR(IF(INDEX('ONLINE ORDERS'!$O$6:$O$155,MATCH($C14,'ONLINE ORDERS'!$B$6:$B$155,0))="","",INDEX('ONLINE ORDERS'!$O$6:$O$155,MATCH($C14,'ONLINE ORDERS'!$B$6:$B$155,0))),""))) | R14: =IF($B14="","",IF($P14="Yes",IF($Q14="",$O14,$Q14),0)) | S14: =IF($B14="","",IF($P14="Yes","SETTLED",IF($M14<>"",IF($M14<TODAY(),"WINDOW CLOSED",IF($M14-TODAY()<=7,"RETURN THIS WEEK","AWAITING REFUND")),"AWAITING REFUND"))) | U14: =IF($B14="",0,IF(COUNTIF('RETURNS + EXCHANGES'!$B$6:$B$65,$B14)>1,1,0)) | V14: =IF($C14="",0,IF(COUNTIF('ONLINE ORDERS'!$B$6:$B$155,$C14)=0,1,0)) | W14: =IF($D14="",0,IF(COUNTIF('GIFT PLANNER'!$B$6:$B$205,$D14)=0,1,0))
F15: =IF($B15="","",IF($C15="",$E15,IF($C15="","",IFERROR(IF(INDEX('ONLINE ORDERS'!$C$6:$C$155,MATCH($C15,'ONLINE ORDERS'!$B$6:$B$155,0))="","",INDEX('ONLINE ORDERS'!$C$6:$C$155,MATCH($C15,'ONLINE ORDERS'!$B$6:$B$155,0))),"")))) | G15: =IF($B15="","",IF($C15="","",IFERROR(IF(INDEX('ONLINE ORDERS'!$G$6:$G$155,MATCH($C15,'ONLINE ORDERS'!$B$6:$B$155,0))="","",INDEX('ONLINE ORDERS'!$G$6:$G$155,MATCH($C15,'ONLINE ORDERS'!$B$6:$B$155,0))),""))) | I15: =IF($B15="","",IF($C15="",$H15,IF($C15="","",IFERROR(IF(INDEX('ONLINE ORDERS'!$H$6:$H$155,MATCH($C15,'ONLINE ORDERS'!$B$6:$B$155,0))="","",INDEX('ONLINE ORDERS'!$H$6:$H$155,MATCH($C15,'ONLINE ORDERS'!$B$6:$B$155,0))),"")))) | M15: =IF($B15="","",IF($C15="","",IFERROR(IF(INDEX('ONLINE ORDERS'!$O$6:$O$155,MATCH($C15,'ONLINE ORDERS'!$B$6:$B$155,0))="","",INDEX('ONLINE ORDERS'!$O$6:$O$155,MATCH($C15,'ONLINE ORDERS'!$B$6:$B$155,0))),""))) | R15: =IF($B15="","",IF($P15="Yes",IF($Q15="",$O15,$Q15),0)) | S15: =IF($B15="","",IF($P15="Yes","SETTLED",IF($M15<>"",IF($M15<TODAY(),"WINDOW CLOSED",IF($M15-TODAY()<=7,"RETURN THIS WEEK","AWAITING REFUND")),"AWAITING REFUND"))) | U15: =IF($B15="",0,IF(COUNTIF('RETURNS + EXCHANGES'!$B$6:$B$65,$B15)>1,1,0)) | V15: =IF($C15="",0,IF(COUNTIF('ONLINE ORDERS'!$B$6:$B$155,$C15)=0,1,0)) | W15: =IF($D15="",0,IF(COUNTIF('GIFT PLANNER'!$B$6:$B$205,$D15)=0,1,0))
F16: =IF($B16="","",IF($C16="",$E16,IF($C16="","",IFERROR(IF(INDEX('ONLINE ORDERS'!$C$6:$C$155,MATCH($C16,'ONLINE ORDERS'!$B$6:$B$155,0))="","",INDEX('ONLINE ORDERS'!$C$6:$C$155,MATCH($C16,'ONLINE ORDERS'!$B$6:$B$155,0))),"")))) | G16: =IF($B16="","",IF($C16="","",IFERROR(IF(INDEX('ONLINE ORDERS'!$G$6:$G$155,MATCH($C16,'ONLINE ORDERS'!$B$6:$B$155,0))="","",INDEX('ONLINE ORDERS'!$G$6:$G$155,MATCH($C16,'ONLINE ORDERS'!$B$6:$B$155,0))),""))) | I16: =IF($B16="","",IF($C16="",$H16,IF($C16="","",IFERROR(IF(INDEX('ONLINE ORDERS'!$H$6:$H$155,MATCH($C16,'ONLINE ORDERS'!$B$6:$B$155,0))="","",INDEX('ONLINE ORDERS'!$H$6:$H$155,MATCH($C16,'ONLINE ORDERS'!$B$6:$B$155,0))),"")))) | M16: =IF($B16="","",IF($C16="","",IFERROR(IF(INDEX('ONLINE ORDERS'!$O$6:$O$155,MATCH($C16,'ONLINE ORDERS'!$B$6:$B$155,0))="","",INDEX('ONLINE ORDERS'!$O$6:$O$155,MATCH($C16,'ONLINE ORDERS'!$B$6:$B$155,0))),""))) | R16: =IF($B16="","",IF($P16="Yes",IF($Q16="",$O16,$Q16),0)) | S16: =IF($B16="","",IF($P16="Yes","SETTLED",IF($M16<>"",IF($M16<TODAY(),"WINDOW CLOSED",IF($M16-TODAY()<=7,"RETURN THIS WEEK","AWAITING REFUND")),"AWAITING REFUND"))) | U16: =IF($B16="",0,IF(COUNTIF('RETURNS + EXCHANGES'!$B$6:$B$65,$B16)>1,1,0)) | V16: =IF($C16="",0,IF(COUNTIF('ONLINE ORDERS'!$B$6:$B$155,$C16)=0,1,0)) | W16: =IF($D16="",0,IF(COUNTIF('GIFT PLANNER'!$B$6:$B$205,$D16)=0,1,0))
F17: =IF($B17="","",IF($C17="",$E17,IF($C17="","",IFERROR(IF(INDEX('ONLINE ORDERS'!$C$6:$C$155,MATCH($C17,'ONLINE ORDERS'!$B$6:$B$155,0))="","",INDEX('ONLINE ORDERS'!$C$6:$C$155,MATCH($C17,'ONLINE ORDERS'!$B$6:$B$155,0))),"")))) | G17: =IF($B17="","",IF($C17="","",IFERROR(IF(INDEX('ONLINE ORDERS'!$G$6:$G$155,MATCH($C17,'ONLINE ORDERS'!$B$6:$B$155,0))="","",INDEX('ONLINE ORDERS'!$G$6:$G$155,MATCH($C17,'ONLINE ORDERS'!$B$6:$B$155,0))),""))) | I17: =IF($B17="","",IF($C17="",$H17,IF($C17="","",IFERROR(IF(INDEX('ONLINE ORDERS'!$H$6:$H$155,MATCH($C17,'ONLINE ORDERS'!$B$6:$B$155,0))="","",INDEX('ONLINE ORDERS'!$H$6:$H$155,MATCH($C17,'ONLINE ORDERS'!$B$6:$B$155,0))),"")))) | M17: =IF($B17="","",IF($C17="","",IFERROR(IF(INDEX('ONLINE ORDERS'!$O$6:$O$155,MATCH($C17,'ONLINE ORDERS'!$B$6:$B$155,0))="","",INDEX('ONLINE ORDERS'!$O$6:$O$155,MATCH($C17,'ONLINE ORDERS'!$B$6:$B$155,0))),""))) | R17: =IF($B17="","",IF($P17="Yes",IF($Q17="",$O17,$Q17),0)) | S17: =IF($B17="","",IF($P17="Yes","SETTLED",IF($M17<>"",IF($M17<TODAY(),"WINDOW CLOSED",IF($M17-TODAY()<=7,"RETURN THIS WEEK","AWAITING REFUND")),"AWAITING REFUND"))) | U17: =IF($B17="",0,IF(COUNTIF('RETURNS + EXCHANGES'!$B$6:$B$65,$B17)>1,1,0)) | V17: =IF($C17="",0,IF(COUNTIF('ONLINE ORDERS'!$B$6:$B$155,$C17)=0,1,0)) | W17: =IF($D17="",0,IF(COUNTIF('GIFT PLANNER'!$B$6:$B$205,$D17)=0,1,0))
F18: =IF($B18="","",IF($C18="",$E18,IF($C18="","",IFERROR(IF(INDEX('ONLINE ORDERS'!$C$6:$C$155,MATCH($C18,'ONLINE ORDERS'!$B$6:$B$155,0))="","",INDEX('ONLINE ORDERS'!$C$6:$C$155,MATCH($C18,'ONLINE ORDERS'!$B$6:$B$155,0))),"")))) | G18: =IF($B18="","",IF($C18="","",IFERROR(IF(INDEX('ONLINE ORDERS'!$G$6:$G$155,MATCH($C18,'ONLINE ORDERS'!$B$6:$B$155,0))="","",INDEX('ONLINE ORDERS'!$G$6:$G$155,MATCH($C18,'ONLINE ORDERS'!$B$6:$B$155,0))),""))) | I18: =IF($B18="","",IF($C18="",$H18,IF($C18="","",IFERROR(IF(INDEX('ONLINE ORDERS'!$H$6:$H$155,MATCH($C18,'ONLINE ORDERS'!$B$6:$B$155,0))="","",INDEX('ONLINE ORDERS'!$H$6:$H$155,MATCH($C18,'ONLINE ORDERS'!$B$6:$B$155,0))),"")))) | M18: =IF($B18="","",IF($C18="","",IFERROR(IF(INDEX('ONLINE ORDERS'!$O$6:$O$155,MATCH($C18,'ONLINE ORDERS'!$B$6:$B$155,0))="","",INDEX('ONLINE ORDERS'!$O$6:$O$155,MATCH($C18,'ONLINE ORDERS'!$B$6:$B$155,0))),""))) | R18: =IF($B18="","",IF($P18="Yes",IF($Q18="",$O18,$Q18),0)) | S18: =IF($B18="","",IF($P18="Yes","SETTLED",IF($M18<>"",IF($M18<TODAY(),"WINDOW CLOSED",IF($M18-TODAY()<=7,"RETURN THIS WEEK","AWAITING REFUND")),"AWAITING REFUND"))) | U18: =IF($B18="",0,IF(COUNTIF('RETURNS + EXCHANGES'!$B$6:$B$65,$B18)>1,1,0)) | V18: =IF($C18="",0,IF(COUNTIF('ONLINE ORDERS'!$B$6:$B$155,$C18)=0,1,0)) | W18: =IF($D18="",0,IF(COUNTIF('GIFT PLANNER'!$B$6:$B$205,$D18)=0,1,0))
F19: =IF($B19="","",IF($C19="",$E19,IF($C19="","",IFERROR(IF(INDEX('ONLINE ORDERS'!$C$6:$C$155,MATCH($C19,'ONLINE ORDERS'!$B$6:$B$155,0))="","",INDEX('ONLINE ORDERS'!$C$6:$C$155,MATCH($C19,'ONLINE ORDERS'!$B$6:$B$155,0))),"")))) | G19: =IF($B19="","",IF($C19="","",IFERROR(IF(INDEX('ONLINE ORDERS'!$G$6:$G$155,MATCH($C19,'ONLINE ORDERS'!$B$6:$B$155,0))="","",INDEX('ONLINE ORDERS'!$G$6:$G$155,MATCH($C19,'ONLINE ORDERS'!$B$6:$B$155,0))),""))) | I19: =IF($B19="","",IF($C19="",$H19,IF($C19="","",IFERROR(IF(INDEX('ONLINE ORDERS'!$H$6:$H$155,MATCH($C19,'ONLINE ORDERS'!$B$6:$B$155,0))="","",INDEX('ONLINE ORDERS'!$H$6:$H$155,MATCH($C19,'ONLINE ORDERS'!$B$6:$B$155,0))),"")))) | M19: =IF($B19="","",IF($C19="","",IFERROR(IF(INDEX('ONLINE ORDERS'!$O$6:$O$155,MATCH($C19,'ONLINE ORDERS'!$B$6:$B$155,0))="","",INDEX('ONLINE ORDERS'!$O$6:$O$155,MATCH($C19,'ONLINE ORDERS'!$B$6:$B$155,0))),""))) | R19: =IF($B19="","",IF($P19="Yes",IF($Q19="",$O19,$Q19),0)) | S19: =IF($B19="","",IF($P19="Yes","SETTLED",IF($M19<>"",IF($M19<TODAY(),"WINDOW CLOSED",IF($M19-TODAY()<=7,"RETURN THIS WEEK","AWAITING REFUND")),"AWAITING REFUND"))) | U19: =IF($B19="",0,IF(COUNTIF('RETURNS + EXCHANGES'!$B$6:$B$65,$B19)>1,1,0)) | V19: =IF($C19="",0,IF(COUNTIF('ONLINE ORDERS'!$B$6:$B$155,$C19)=0,1,0)) | W19: =IF($D19="",0,IF(COUNTIF('GIFT PLANNER'!$B$6:$B$205,$D19)=0,1,0))
F20: =IF($B20="","",IF($C20="",$E20,IF($C20="","",IFERROR(IF(INDEX('ONLINE ORDERS'!$C$6:$C$155,MATCH($C20,'ONLINE ORDERS'!$B$6:$B$155,0))="","",INDEX('ONLINE ORDERS'!$C$6:$C$155,MATCH($C20,'ONLINE ORDERS'!$B$6:$B$155,0))),"")))) | G20: =IF($B20="","",IF($C20="","",IFERROR(IF(INDEX('ONLINE ORDERS'!$G$6:$G$155,MATCH($C20,'ONLINE ORDERS'!$B$6:$B$155,0))="","",INDEX('ONLINE ORDERS'!$G$6:$G$155,MATCH($C20,'ONLINE ORDERS'!$B$6:$B$155,0))),""))) | I20: =IF($B20="","",IF($C20="",$H20,IF($C20="","",IFERROR(IF(INDEX('ONLINE ORDERS'!$H$6:$H$155,MATCH($C20,'ONLINE ORDERS'!$B$6:$B$155,0))="","",INDEX('ONLINE ORDERS'!$H$6:$H$155,MATCH($C20,'ONLINE ORDERS'!$B$6:$B$155,0))),"")))) | M20: =IF($B20="","",IF($C20="","",IFERROR(IF(INDEX('ONLINE ORDERS'!$O$6:$O$155,MATCH($C20,'ONLINE ORDERS'!$B$6:$B$155,0))="","",INDEX('ONLINE ORDERS'!$O$6:$O$155,MATCH($C20,'ONLINE ORDERS'!$B$6:$B$155,0))),""))) | R20: =IF($B20="","",IF($P20="Yes",IF($Q20="",$O20,$Q20),0)) | S20: =IF($B20="","",IF($P20="Yes","SETTLED",IF($M20<>"",IF($M20<TODAY(),"WINDOW CLOSED",IF($M20-TODAY()<=7,"RETURN THIS WEEK","AWAITING REFUND")),"AWAITING REFUND"))) | U20: =IF($B20="",0,IF(COUNTIF('RETURNS + EXCHANGES'!$B$6:$B$65,$B20)>1,1,0)) | V20: =IF($C20="",0,IF(COUNTIF('ONLINE ORDERS'!$B$6:$B$155,$C20)=0,1,0)) | W20: =IF($D20="",0,IF(COUNTIF('GIFT PLANNER'!$B$6:$B$205,$D20)=0,1,0))
... F65: =IF($B65="","",IF($C65="",$E65,IF($C65="","",IFERROR(IF(INDEX('ONLINE ORDERS'!$C$6:$C$155,MATCH($C65,'ONLINE ORDERS'!$B$6:$B$155,0))="","",INDEX('ONLINE ORDERS'!$C$6:$C$155,MATCH($C65,'ONLINE ORDERS'!$B$6:$B$155,0))),"")))) | G65: =IF($B65="","",IF($C65="","",IFERROR(IF(INDEX('ONLINE ORDERS'!$G$6:$G$155,MATCH($C65,'ONLINE ORDERS'!$B$6:$B$155,0))="","",INDEX('ONLINE ORDERS'!$G$6:$G$155,MATCH($C65,'ONLINE ORDERS'!$B$6:$B$155,0))),""))) | I65: =IF($B65="","",IF($C65="",$H65,IF($C65="","",IFERROR(IF(INDEX('ONLINE ORDERS'!$H$6:$H$155,MATCH($C65,'ONLINE ORDERS'!$B$6:$B$155,0))="","",INDEX('ONLINE ORDERS'!$H$6:$H$155,MATCH($C65,'ONLINE ORDERS'!$B$6:$B$155,0))),"")))) | M65: =IF($B65="","",IF($C65="","",IFERROR(IF(INDEX('ONLINE ORDERS'!$O$6:$O$155,MATCH($C65,'ONLINE ORDERS'!$B$6:$B$155,0))="","",INDEX('ONLINE ORDERS'!$O$6:$O$155,MATCH($C65,'ONLINE ORDERS'!$B$6:$B$155,0))),""))) | R65: =IF($B65="","",IF($P65="Yes",IF($Q65="",$O65,$Q65),0)) | S65: =IF($B65="","",IF($P65="Yes","SETTLED",IF($M65<>"",IF($M65<TODAY(),"WINDOW CLOSED",IF($M65-TODAY()<=7,"RETURN THIS WEEK","AWAITING REFUND")),"AWAITING REFUND"))) | U65: =IF($B65="",0,IF(COUNTIF('RETURNS + EXCHANGES'!$B$6:$B$65,$B65)>1,1,0)) | V65: =IF($C65="",0,IF(COUNTIF('ONLINE ORDERS'!$B$6:$B$155,$C65)=0,1,0)) | W65: =IF($D65="",0,IF(COUNTIF('GIFT PLANNER'!$B$6:$B$205,$D65)=0,1,0))

Sheet CHRISTMAS CALENDAR
B1: Dashboard | D1: Start here | F1: Calendar | G1: Budget | H1: All sheets
B2: CHRISTMAS CALENDAR
B3: Every dated thing in one table: tasks, events, deadlines and the sales worth waiting for.
B4: Cream cells are yours to fill in · pale green cells calculate themselves · amber rows are examples you can delete
B5: Calendar ID | C5: Date | D5: Start | E5: Type | F5: Event or task | G5: Belongs to | H5: Owner | I5: Where | J5: Budget category | K5: Budget cap | L5: Actual cost | M5: Status | N5: Priority | O5: Remind me | P5: Week | Q5: Open? | R5: When | S5: Notes | T5: Next-seven-days key | U5: QA · duplicate ID | V5: QA · budget mapping
B6: K-001 | C6: 46353 | D6: 08:00 | E6: Sale | F6: Linen sale — tablecloth and napkins | G6: Hosting | H6: Me | J6: Hosting | K6: 300 | M6: Complete | N6: Should | P6: =IF($C6="","",WEEKNUM($C6,IF(Set_WeekStart="Monday",2,1))) | Q6: =IF($B6="","",IF(OR($M6="Complete",$M6="Attended",$M6="Skipped",$M6="Cancelled"),"No","Yes")) | R6: =IF($B6="","",IF($Q6="No","COMPLETE",IF($C6="","NO DATE",IF($C6<TODAY(),"OVERDUE",IF($C6-TODAY()<=7,"THIS WEEK","SCHEDULED"))))) | S6: EXAMPLE — DELETE ME | T6: =IF(AND($Q6="Yes",$C6<>"",$C6>=TODAY(),$C6<=TODAY()+7),$C6+ROW()/100000,"") | U6: =IF($B6="",0,IF(COUNTIF('CHRISTMAS CALENDAR'!$B$6:$B$205,$B6)>1,1,0)) | V6: =IF(OR(N($K6)>0,N($L6)>0),IF($J6="",1,IF(COUNTIF('MASTER BUDGET'!$D$6:$D$25,$J6)=0,1,0)),0)
B7: K-002 | C7: 46368 | D7: 19:00 | E7: Event | F7: Neighbours' drinks | G7: Hosting | H7: Me | I7: Number 14 | J7: Events | K7: 80 | M7: Not started | N7: Could | P7: =IF($C7="","",WEEKNUM($C7,IF(Set_WeekStart="Monday",2,1))) | Q7: =IF($B7="","",IF(OR($M7="Complete",$M7="Attended",$M7="Skipped",$M7="Cancelled"),"No","Yes")) | R7: =IF($B7="","",IF($Q7="No","COMPLETE",IF($C7="","NO DATE",IF($C7<TODAY(),"OVERDUE",IF($C7-TODAY()<=7,"THIS WEEK","SCHEDULED"))))) | S7: EXAMPLE — DELETE ME | T7: =IF(AND($Q7="Yes",$C7<>"",$C7>=TODAY(),$C7<=TODAY()+7),$C7+ROW()/100000,"") | U7: =IF($B7="",0,IF(COUNTIF('CHRISTMAS CALENDAR'!$B$6:$B$205,$B7)>1,1,0)) | V7: =IF(OR(N($K7)>0,N($L7)>0),IF($J7="",1,IF(COUNTIF('MASTER BUDGET'!$D$6:$D$25,$J7)=0,1,0)),0)
B8: K-003 | C8: 46374 | E8: Deadline | F8: Last posting date for overseas cards | G8: Cards | H8: Me | M8: Not started | N8: Must | O8: 46371 | P8: =IF($C8="","",WEEKNUM($C8,IF(Set_WeekStart="Monday",2,1))) | Q8: =IF($B8="","",IF(OR($M8="Complete",$M8="Attended",$M8="Skipped",$M8="Cancelled"),"No","Yes")) | R8: =IF($B8="","",IF($Q8="No","COMPLETE",IF($C8="","NO DATE",IF($C8<TODAY(),"OVERDUE",IF($C8-TODAY()<=7,"THIS WEEK","SCHEDULED"))))) | S8: EXAMPLE — DELETE ME | T8: =IF(AND($Q8="Yes",$C8<>"",$C8>=TODAY(),$C8<=TODAY()+7),$C8+ROW()/100000,"") | U8: =IF($B8="",0,IF(COUNTIF('CHRISTMAS CALENDAR'!$B$6:$B$205,$B8)>1,1,0)) | V8: =IF(OR(N($K8)>0,N($L8)>0),IF($J8="",1,IF(COUNTIF('MASTER BUDGET'!$D$6:$D$25,$J8)=0,1,0)),0)
P9: =IF($C9="","",WEEKNUM($C9,IF(Set_WeekStart="Monday",2,1))) | Q9: =IF($B9="","",IF(OR($M9="Complete",$M9="Attended",$M9="Skipped",$M9="Cancelled"),"No","Yes")) | R9: =IF($B9="","",IF($Q9="No","COMPLETE",IF($C9="","NO DATE",IF($C9<TODAY(),"OVERDUE",IF($C9-TODAY()<=7,"THIS WEEK","SCHEDULED"))))) | T9: =IF(AND($Q9="Yes",$C9<>"",$C9>=TODAY(),$C9<=TODAY()+7),$C9+ROW()/100000,"") | U9: =IF($B9="",0,IF(COUNTIF('CHRISTMAS CALENDAR'!$B$6:$B$205,$B9)>1,1,0)) | V9: =IF(OR(N($K9)>0,N($L9)>0),IF($J9="",1,IF(COUNTIF('MASTER BUDGET'!$D$6:$D$25,$J9)=0,1,0)),0)
P10: =IF($C10="","",WEEKNUM($C10,IF(Set_WeekStart="Monday",2,1))) | Q10: =IF($B10="","",IF(OR($M10="Complete",$M10="Attended",$M10="Skipped",$M10="Cancelled"),"No","Yes")) | R10: =IF($B10="","",IF($Q10="No","COMPLETE",IF($C10="","NO DATE",IF($C10<TODAY(),"OVERDUE",IF($C10-TODAY()<=7,"THIS WEEK","SCHEDULED"))))) | T10: =IF(AND($Q10="Yes",$C10<>"",$C10>=TODAY(),$C10<=TODAY()+7),$C10+ROW()/100000,"") | U10: =IF($B10="",0,IF(COUNTIF('CHRISTMAS CALENDAR'!$B$6:$B$205,$B10)>1,1,0)) | V10: =IF(OR(N($K10)>0,N($L10)>0),IF($J10="",1,IF(COUNTIF('MASTER BUDGET'!$D$6:$D$25,$J10)=0,1,0)),0)
P11: =IF($C11="","",WEEKNUM($C11,IF(Set_WeekStart="Monday",2,1))) | Q11: =IF($B11="","",IF(OR($M11="Complete",$M11="Attended",$M11="Skipped",$M11="Cancelled"),"No","Yes")) | R11: =IF($B11="","",IF($Q11="No","COMPLETE",IF($C11="","NO DATE",IF($C11<TODAY(),"OVERDUE",IF($C11-TODAY()<=7,"THIS WEEK","SCHEDULED"))))) | T11: =IF(AND($Q11="Yes",$C11<>"",$C11>=TODAY(),$C11<=TODAY()+7),$C11+ROW()/100000,"") | U11: =IF($B11="",0,IF(COUNTIF('CHRISTMAS CALENDAR'!$B$6:$B$205,$B11)>1,1,0)) | V11: =IF(OR(N($K11)>0,N($L11)>0),IF($J11="",1,IF(COUNTIF('MASTER BUDGET'!$D$6:$D$25,$J11)=0,1,0)),0)
P12: =IF($C12="","",WEEKNUM($C12,IF(Set_WeekStart="Monday",2,1))) | Q12: =IF($B12="","",IF(OR($M12="Complete",$M12="Attended",$M12="Skipped",$M12="Cancelled"),"No","Yes")) | R12: =IF($B12="","",IF($Q12="No","COMPLETE",IF($C12="","NO DATE",IF($C12<TODAY(),"OVERDUE",IF($C12-TODAY()<=7,"THIS WEEK","SCHEDULED"))))) | T12: =IF(AND($Q12="Yes",$C12<>"",$C12>=TODAY(),$C12<=TODAY()+7),$C12+ROW()/100000,"") | U12: =IF($B12="",0,IF(COUNTIF('CHRISTMAS CALENDAR'!$B$6:$B$205,$B12)>1,1,0)) | V12: =IF(OR(N($K12)>0,N($L12)>0),IF($J12="",1,IF(COUNTIF('MASTER BUDGET'!$D$6:$D$25,$J12)=0,1,0)),0)
P13: =IF($C13="","",WEEKNUM($C13,IF(Set_WeekStart="Monday",2,1))) | Q13: =IF($B13="","",IF(OR($M13="Complete",$M13="Attended",$M13="Skipped",$M13="Cancelled"),"No","Yes")) | R13: =IF($B13="","",IF($Q13="No","COMPLETE",IF($C13="","NO DATE",IF($C13<TODAY(),"OVERDUE",IF($C13-TODAY()<=7,"THIS WEEK","SCHEDULED"))))) | T13: =IF(AND($Q13="Yes",$C13<>"",$C13>=TODAY(),$C13<=TODAY()+7),$C13+ROW()/100000,"") | U13: =IF($B13="",0,IF(COUNTIF('CHRISTMAS CALENDAR'!$B$6:$B$205,$B13)>1,1,0)) | V13: =IF(OR(N($K13)>0,N($L13)>0),IF($J13="",1,IF(COUNTIF('MASTER BUDGET'!$D$6:$D$25,$J13)=0,1,0)),0)
P14: =IF($C14="","",WEEKNUM($C14,IF(Set_WeekStart="Monday",2,1))) | Q14: =IF($B14="","",IF(OR($M14="Complete",$M14="Attended",$M14="Skipped",$M14="Cancelled"),"No","Yes")) | R14: =IF($B14="","",IF($Q14="No","COMPLETE",IF($C14="","NO DATE",IF($C14<TODAY(),"OVERDUE",IF($C14-TODAY()<=7,"THIS WEEK","SCHEDULED"))))) | T14: =IF(AND($Q14="Yes",$C14<>"",$C14>=TODAY(),$C14<=TODAY()+7),$C14+ROW()/100000,"") | U14: =IF($B14="",0,IF(COUNTIF('CHRISTMAS CALENDAR'!$B$6:$B$205,$B14)>1,1,0)) | V14: =IF(OR(N($K14)>0,N($L14)>0),IF($J14="",1,IF(COUNTIF('MASTER BUDGET'!$D$6:$D$25,$J14)=0,1,0)),0)
P15: =IF($C15="","",WEEKNUM($C15,IF(Set_WeekStart="Monday",2,1))) | Q15: =IF($B15="","",IF(OR($M15="Complete",$M15="Attended",$M15="Skipped",$M15="Cancelled"),"No","Yes")) | R15: =IF($B15="","",IF($Q15="No","COMPLETE",IF($C15="","NO DATE",IF($C15<TODAY(),"OVERDUE",IF($C15-TODAY()<=7,"THIS WEEK","SCHEDULED"))))) | T15: =IF(AND($Q15="Yes",$C15<>"",$C15>=TODAY(),$C15<=TODAY()+7),$C15+ROW()/100000,"") | U15: =IF($B15="",0,IF(COUNTIF('CHRISTMAS CALENDAR'!$B$6:$B$205,$B15)>1,1,0)) | V15: =IF(OR(N($K15)>0,N($L15)>0),IF($J15="",1,IF(COUNTIF('MASTER BUDGET'!$D$6:$D$25,$J15)=0,1,0)),0)
P16: =IF($C16="","",WEEKNUM($C16,IF(Set_WeekStart="Monday",2,1))) | Q16: =IF($B16="","",IF(OR($M16="Complete",$M16="Attended",$M16="Skipped",$M16="Cancelled"),"No","Yes")) | R16: =IF($B16="","",IF($Q16="No","COMPLETE",IF($C16="","NO DATE",IF($C16<TODAY(),"OVERDUE",IF($C16-TODAY()<=7,"THIS WEEK","SCHEDULED"))))) | T16: =IF(AND($Q16="Yes",$C16<>"",$C16>=TODAY(),$C16<=TODAY()+7),$C16+ROW()/100000,"") | U16: =IF($B16="",0,IF(COUNTIF('CHRISTMAS CALENDAR'!$B$6:$B$205,$B16)>1,1,0)) | V16: =IF(OR(N($K16)>0,N($L16)>0),IF($J16="",1,IF(COUNTIF('MASTER BUDGET'!$D$6:$D$25,$J16)=0,1,0)),0)
P17: =IF($C17="","",WEEKNUM($C17,IF(Set_WeekStart="Monday",2,1))) | Q17: =IF($B17="","",IF(OR($M17="Complete",$M17="Attended",$M17="Skipped",$M17="Cancelled"),"No","Yes")) | R17: =IF($B17="","",IF($Q17="No","COMPLETE",IF($C17="","NO DATE",IF($C17<TODAY(),"OVERDUE",IF($C17-TODAY()<=7,"THIS WEEK","SCHEDULED"))))) | T17: =IF(AND($Q17="Yes",$C17<>"",$C17>=TODAY(),$C17<=TODAY()+7),$C17+ROW()/100000,"") | U17: =IF($B17="",0,IF(COUNTIF('CHRISTMAS CALENDAR'!$B$6:$B$205,$B17)>1,1,0)) | V17: =IF(OR(N($K17)>0,N($L17)>0),IF($J17="",1,IF(COUNTIF('MASTER BUDGET'!$D$6:$D$25,$J17)=0,1,0)),0)
P18: =IF($C18="","",WEEKNUM($C18,IF(Set_WeekStart="Monday",2,1))) | Q18: =IF($B18="","",IF(OR($M18="Complete",$M18="Attended",$M18="Skipped",$M18="Cancelled"),"No","Yes")) | R18: =IF($B18="","",IF($Q18="No","COMPLETE",IF($C18="","NO DATE",IF($C18<TODAY(),"OVERDUE",IF($C18-TODAY()<=7,"THIS WEEK","SCHEDULED"))))) | T18: =IF(AND($Q18="Yes",$C18<>"",$C18>=TODAY(),$C18<=TODAY()+7),$C18+ROW()/100000,"") | U18: =IF($B18="",0,IF(COUNTIF('CHRISTMAS CALENDAR'!$B$6:$B$205,$B18)>1,1,0)) | V18: =IF(OR(N($K18)>0,N($L18)>0),IF($J18="",1,IF(COUNTIF('MASTER BUDGET'!$D$6:$D$25,$J18)=0,1,0)),0)
P19: =IF($C19="","",WEEKNUM($C19,IF(Set_WeekStart="Monday",2,1))) | Q19: =IF($B19="","",IF(OR($M19="Complete",$M19="Attended",$M19="Skipped",$M19="Cancelled"),"No","Yes")) | R19: =IF($B19="","",IF($Q19="No","COMPLETE",IF($C19="","NO DATE",IF($C19<TODAY(),"OVERDUE",IF($C19-TODAY()<=7,"THIS WEEK","SCHEDULED"))))) | T19: =IF(AND($Q19="Yes",$C19<>"",$C19>=TODAY(),$C19<=TODAY()+7),$C19+ROW()/100000,"") | U19: =IF($B19="",0,IF(COUNTIF('CHRISTMAS CALENDAR'!$B$6:$B$205,$B19)>1,1,0)) | V19: =IF(OR(N($K19)>0,N($L19)>0),IF($J19="",1,IF(COUNTIF('MASTER BUDGET'!$D$6:$D$25,$J19)=0,1,0)),0)
P20: =IF($C20="","",WEEKNUM($C20,IF(Set_WeekStart="Monday",2,1))) | Q20: =IF($B20="","",IF(OR($M20="Complete",$M20="Attended",$M20="Skipped",$M20="Cancelled"),"No","Yes")) | R20: =IF($B20="","",IF($Q20="No","COMPLETE",IF($C20="","NO DATE",IF($C20<TODAY(),"OVERDUE",IF($C20-TODAY()<=7,"THIS WEEK","SCHEDULED"))))) | T20: =IF(AND($Q20="Yes",$C20<>"",$C20>=TODAY(),$C20<=TODAY()+7),$C20+ROW()/100000,"") | U20: =IF($B20="",0,IF(COUNTIF('CHRISTMAS CALENDAR'!$B$6:$B$205,$B20)>1,1,0)) | V20: =IF(OR(N($K20)>0,N($L20)>0),IF($J20="",1,IF(COUNTIF('MASTER BUDGET'!$D$6:$D$25,$J20)=0,1,0)),0)
... P205: =IF($C205="","",WEEKNUM($C205,IF(Set_WeekStart="Monday",2,1))) | Q205: =IF($B205="","",IF(OR($M205="Complete",$M205="Attended",$M205="Skipped",$M205="Cancelled"),"No","Yes")) | R205: =IF($B205="","",IF($Q205="No","COMPLETE",IF($C205="","NO DATE",IF($C205<TODAY(),"OVERDUE",IF($C205-TODAY()<=7,"THIS WEEK","SCHEDULED"))))) | T205: =IF(AND($Q205="Yes",$C205<>"",$C205>=TODAY(),$C205<=TODAY()+7),$C205+ROW()/100000,"") | U205: =IF($B205="",0,IF(COUNTIF('CHRISTMAS CALENDAR'!$B$6:$B$205,$B205)>1,1,0)) | V205: =IF(OR(N($K205)>0,N($L205)>0),IF($J205="",1,IF(COUNTIF('MASTER BUDGET'!$D$6:$D$25,$J205)=0,1,0)),0)
B207: The dashboard reads the next seven days from this sheet. Sort by date whenever you like — the IDs are stable.

Sheet VENDORS + APPOINTMENTS
B1: Dashboard | D1: Start here | E1: Calendar | F1: Budget | G1: All sheets
B2: VENDORS + APPOINTMENTS
B3: The people you are booking, what they quoted, and what is still owed.
B4: Cream cells are yours to fill in · pale green cells calculate themselves · amber rows are examples you can delete
B5: Vendor ID | C5: Category | D5: Business | E5: Contact | F5: Phone | G5: Email | H5: Service | I5: Event ID | J5: Appointment | K5: Time | L5: Budget category | M5: Quote | N5: Deposit paid | O5: Balance | P5: Balance due | Q5: Paid to date | R5: Contract or link | S5: Owner | T5: Status | U5: Thank you sent? | V5: Attention | W5: Notes | X5: QA · duplicate ID | Y5: QA · budget mapping | Z5: QA · Event ID exists
B6: V-001 | C6: Florist | D6: Hedgerow & Bough | E6: Marta | F6: 020 7946 0102 | G6: studio@hedgerowbough.example | H6: Mantel garland and two table arrangements | I6: K-002 | J6: 46378 | K6: 10:00 | L6: Hosting | M6: 640 | N6: 200 | O6: =IF($B6="","",MAX(0,$M6-$N6)) | P6: 46376 | Q6: =IF($B6="","",IF($T6="Paid in full",$M6,IF($T6="Complete",$M6,$N6))) | T6: Booked | U6: No | V6: =IF($B6="","",IF($T6="Declined","CLOSED",IF($O6=0,"SETTLED",IF($P6="","BALANCE OPEN",IF($P6<TODAY(),"BALANCE OVERDUE",IF($P6-TODAY()<=7,"BALANCE DUE SOON","BALANCE OPEN")))))) | W6: EXAMPLE — DELETE ME | X6: =IF($B6="",0,IF(COUNTIF('VENDORS + APPOINTMENTS'!$B$6:$B$65,$B6)>1,1,0)) | Y6: =IF(OR(N($M6)>0,N($Q6)>0),IF($L6="",1,IF(COUNTIF('MASTER BUDGET'!$D$6:$D$25,$L6)=0,1,0)),0) | Z6: =IF($I6="",0,IF(COUNTIF('CHRISTMAS CALENDAR'!$B$6:$B$205,$I6)=0,1,0))
B7: V-002 | C7: Cleaner | D7: Fen & Field | E7: Ana | F7: 020 7946 0155 | H7: Deep clean before guests arrive | J7: 46375 | K7: 09:00 | L7: Hosting | M7: 320 | N7: 0 | O7: =IF($B7="","",MAX(0,$M7-$N7)) | P7: 46375 | Q7: =IF($B7="","",IF($T7="Paid in full",$M7,IF($T7="Complete",$M7,$N7))) | T7: Quoted | U7: No | V7: =IF($B7="","",IF($T7="Declined","CLOSED",IF($O7=0,"SETTLED",IF($P7="","BALANCE OPEN",IF($P7<TODAY(),"BALANCE OVERDUE",IF($P7-TODAY()<=7,"BALANCE DUE SOON","BALANCE OPEN")))))) | W7: EXAMPLE — DELETE ME | X7: =IF($B7="",0,IF(COUNTIF('VENDORS + APPOINTMENTS'!$B$6:$B$65,$B7)>1,1,0)) | Y7: =IF(OR(N($M7)>0,N($Q7)>0),IF($L7="",1,IF(COUNTIF('MASTER BUDGET'!$D$6:$D$25,$L7)=0,1,0)),0) | Z7: =IF($I7="",0,IF(COUNTIF('CHRISTMAS CALENDAR'!$B$6:$B$205,$I7)=0,1,0))
B8: V-003 | C8: Photographer | D8: Rowan Frost | E8: Rowan | G8: hello@rowanfrost.example | H8: Family portraits, Boxing Day morning | L8: Photography | M8: 850 | N8: 850 | O8: =IF($B8="","",MAX(0,$M8-$N8)) | Q8: =IF($B8="","",IF($T8="Paid in full",$M8,IF($T8="Complete",$M8,$N8))) | T8: Paid in full | U8: No | V8: =IF($B8="","",IF($T8="Declined","CLOSED",IF($O8=0,"SETTLED",IF($P8="","BALANCE OPEN",IF($P8<TODAY(),"BALANCE OVERDUE",IF($P8-TODAY()<=7,"BALANCE DUE SOON","BALANCE OPEN")))))) | W8: EXAMPLE — DELETE ME | X8: =IF($B8="",0,IF(COUNTIF('VENDORS + APPOINTMENTS'!$B$6:$B$65,$B8)>1,1,0)) | Y8: =IF(OR(N($M8)>0,N($Q8)>0),IF($L8="",1,IF(COUNTIF('MASTER BUDGET'!$D$6:$D$25,$L8)=0,1,0)),0) | Z8: =IF($I8="",0,IF(COUNTIF('CHRISTMAS CALENDAR'!$B$6:$B$205,$I8)=0,1,0))
O9: =IF($B9="","",MAX(0,$M9-$N9)) | Q9: =IF($B9="","",IF($T9="Paid in full",$M9,IF($T9="Complete",$M9,$N9))) | V9: =IF($B9="","",IF($T9="Declined","CLOSED",IF($O9=0,"SETTLED",IF($P9="","BALANCE OPEN",IF($P9<TODAY(),"BALANCE OVERDUE",IF($P9-TODAY()<=7,"BALANCE DUE SOON","BALANCE OPEN")))))) | X9: =IF($B9="",0,IF(COUNTIF('VENDORS + APPOINTMENTS'!$B$6:$B$65,$B9)>1,1,0)) | Y9: =IF(OR(N($M9)>0,N($Q9)>0),IF($L9="",1,IF(COUNTIF('MASTER BUDGET'!$D$6:$D$25,$L9)=0,1,0)),0) | Z9: =IF($I9="",0,IF(COUNTIF('CHRISTMAS CALENDAR'!$B$6:$B$205,$I9)=0,1,0))
O10: =IF($B10="","",MAX(0,$M10-$N10)) | Q10: =IF($B10="","",IF($T10="Paid in full",$M10,IF($T10="Complete",$M10,$N10))) | V10: =IF($B10="","",IF($T10="Declined","CLOSED",IF($O10=0,"SETTLED",IF($P10="","BALANCE OPEN",IF($P10<TODAY(),"BALANCE OVERDUE",IF($P10-TODAY()<=7,"BALANCE DUE SOON","BALANCE OPEN")))))) | X10: =IF($B10="",0,IF(COUNTIF('VENDORS + APPOINTMENTS'!$B$6:$B$65,$B10)>1,1,0)) | Y10: =IF(OR(N($M10)>0,N($Q10)>0),IF($L10="",1,IF(COUNTIF('MASTER BUDGET'!$D$6:$D$25,$L10)=0,1,0)),0) | Z10: =IF($I10="",0,IF(COUNTIF('CHRISTMAS CALENDAR'!$B$6:$B$205,$I10)=0,1,0))
O11: =IF($B11="","",MAX(0,$M11-$N11)) | Q11: =IF($B11="","",IF($T11="Paid in full",$M11,IF($T11="Complete",$M11,$N11))) | V11: =IF($B11="","",IF($T11="Declined","CLOSED",IF($O11=0,"SETTLED",IF($P11="","BALANCE OPEN",IF($P11<TODAY(),"BALANCE OVERDUE",IF($P11-TODAY()<=7,"BALANCE DUE SOON","BALANCE OPEN")))))) | X11: =IF($B11="",0,IF(COUNTIF('VENDORS + APPOINTMENTS'!$B$6:$B$65,$B11)>1,1,0)) | Y11: =IF(OR(N($M11)>0,N($Q11)>0),IF($L11="",1,IF(COUNTIF('MASTER BUDGET'!$D$6:$D$25,$L11)=0,1,0)),0) | Z11: =IF($I11="",0,IF(COUNTIF('CHRISTMAS CALENDAR'!$B$6:$B$205,$I11)=0,1,0))
O12: =IF($B12="","",MAX(0,$M12-$N12)) | Q12: =IF($B12="","",IF($T12="Paid in full",$M12,IF($T12="Complete",$M12,$N12))) | V12: =IF($B12="","",IF($T12="Declined","CLOSED",IF($O12=0,"SETTLED",IF($P12="","BALANCE OPEN",IF($P12<TODAY(),"BALANCE OVERDUE",IF($P12-TODAY()<=7,"BALANCE DUE SOON","BALANCE OPEN")))))) | X12: =IF($B12="",0,IF(COUNTIF('VENDORS + APPOINTMENTS'!$B$6:$B$65,$B12)>1,1,0)) | Y12: =IF(OR(N($M12)>0,N($Q12)>0),IF($L12="",1,IF(COUNTIF('MASTER BUDGET'!$D$6:$D$25,$L12)=0,1,0)),0) | Z12: =IF($I12="",0,IF(COUNTIF('CHRISTMAS CALENDAR'!$B$6:$B$205,$I12)=0,1,0))
O13: =IF($B13="","",MAX(0,$M13-$N13)) | Q13: =IF($B13="","",IF($T13="Paid in full",$M13,IF($T13="Complete",$M13,$N13))) | V13: =IF($B13="","",IF($T13="Declined","CLOSED",IF($O13=0,"SETTLED",IF($P13="","BALANCE OPEN",IF($P13<TODAY(),"BALANCE OVERDUE",IF($P13-TODAY()<=7,"BALANCE DUE SOON","BALANCE OPEN")))))) | X13: =IF($B13="",0,IF(COUNTIF('VENDORS + APPOINTMENTS'!$B$6:$B$65,$B13)>1,1,0)) | Y13: =IF(OR(N($M13)>0,N($Q13)>0),IF($L13="",1,IF(COUNTIF('MASTER BUDGET'!$D$6:$D$25,$L13)=0,1,0)),0) | Z13: =IF($I13="",0,IF(COUNTIF('CHRISTMAS CALENDAR'!$B$6:$B$205,$I13)=0,1,0))
O14: =IF($B14="","",MAX(0,$M14-$N14)) | Q14: =IF($B14="","",IF($T14="Paid in full",$M14,IF($T14="Complete",$M14,$N14))) | V14: =IF($B14="","",IF($T14="Declined","CLOSED",IF($O14=0,"SETTLED",IF($P14="","BALANCE OPEN",IF($P14<TODAY(),"BALANCE OVERDUE",IF($P14-TODAY()<=7,"BALANCE DUE SOON","BALANCE OPEN")))))) | X14: =IF($B14="",0,IF(COUNTIF('VENDORS + APPOINTMENTS'!$B$6:$B$65,$B14)>1,1,0)) | Y14: =IF(OR(N($M14)>0,N($Q14)>0),IF($L14="",1,IF(COUNTIF('MASTER BUDGET'!$D$6:$D$25,$L14)=0,1,0)),0) | Z14: =IF($I14="",0,IF(COUNTIF('CHRISTMAS CALENDAR'!$B$6:$B$205,$I14)=0,1,0))
O15: =IF($B15="","",MAX(0,$M15-$N15)) | Q15: =IF($B15="","",IF($T15="Paid in full",$M15,IF($T15="Complete",$M15,$N15))) | V15: =IF($B15="","",IF($T15="Declined","CLOSED",IF($O15=0,"SETTLED",IF($P15="","BALANCE OPEN",IF($P15<TODAY(),"BALANCE OVERDUE",IF($P15-TODAY()<=7,"BALANCE DUE SOON","BALANCE OPEN")))))) | X15: =IF($B15="",0,IF(COUNTIF('VENDORS + APPOINTMENTS'!$B$6:$B$65,$B15)>1,1,0)) | Y15: =IF(OR(N($M15)>0,N($Q15)>0),IF($L15="",1,IF(COUNTIF('MASTER BUDGET'!$D$6:$D$25,$L15)=0,1,0)),0) | Z15: =IF($I15="",0,IF(COUNTIF('CHRISTMAS CALENDAR'!$B$6:$B$205,$I15)=0,1,0))
O16: =IF($B16="","",MAX(0,$M16-$N16)) | Q16: =IF($B16="","",IF($T16="Paid in full",$M16,IF($T16="Complete",$M16,$N16))) | V16: =IF($B16="","",IF($T16="Declined","CLOSED",IF($O16=0,"SETTLED",IF($P16="","BALANCE OPEN",IF($P16<TODAY(),"BALANCE OVERDUE",IF($P16-TODAY()<=7,"BALANCE DUE SOON","BALANCE OPEN")))))) | X16: =IF($B16="",0,IF(COUNTIF('VENDORS + APPOINTMENTS'!$B$6:$B$65,$B16)>1,1,0)) | Y16: =IF(OR(N($M16)>0,N($Q16)>0),IF($L16="",1,IF(COUNTIF('MASTER BUDGET'!$D$6:$D$25,$L16)=0,1,0)),0) | Z16: =IF($I16="",0,IF(COUNTIF('CHRISTMAS CALENDAR'!$B$6:$B$205,$I16)=0,1,0))
O17: =IF($B17="","",MAX(0,$M17-$N17)) | Q17: =IF($B17="","",IF($T17="Paid in full",$M17,IF($T17="Complete",$M17,$N17))) | V17: =IF($B17="","",IF($T17="Declined","CLOSED",IF($O17=0,"SETTLED",IF($P17="","BALANCE OPEN",IF($P17<TODAY(),"BALANCE OVERDUE",IF($P17-TODAY()<=7,"BALANCE DUE SOON","BALANCE OPEN")))))) | X17: =IF($B17="",0,IF(COUNTIF('VENDORS + APPOINTMENTS'!$B$6:$B$65,$B17)>1,1,0)) | Y17: =IF(OR(N($M17)>0,N($Q17)>0),IF($L17="",1,IF(COUNTIF('MASTER BUDGET'!$D$6:$D$25,$L17)=0,1,0)),0) | Z17: =IF($I17="",0,IF(COUNTIF('CHRISTMAS CALENDAR'!$B$6:$B$205,$I17)=0,1,0))
O18: =IF($B18="","",MAX(0,$M18-$N18)) | Q18: =IF($B18="","",IF($T18="Paid in full",$M18,IF($T18="Complete",$M18,$N18))) | V18: =IF($B18="","",IF($T18="Declined","CLOSED",IF($O18=0,"SETTLED",IF($P18="","BALANCE OPEN",IF($P18<TODAY(),"BALANCE OVERDUE",IF($P18-TODAY()<=7,"BALANCE DUE SOON","BALANCE OPEN")))))) | X18: =IF($B18="",0,IF(COUNTIF('VENDORS + APPOINTMENTS'!$B$6:$B$65,$B18)>1,1,0)) | Y18: =IF(OR(N($M18)>0,N($Q18)>0),IF($L18="",1,IF(COUNTIF('MASTER BUDGET'!$D$6:$D$25,$L18)=0,1,0)),0) | Z18: =IF($I18="",0,IF(COUNTIF('CHRISTMAS CALENDAR'!$B$6:$B$205,$I18)=0,1,0))
O19: =IF($B19="","",MAX(0,$M19-$N19)) | Q19: =IF($B19="","",IF($T19="Paid in full",$M19,IF($T19="Complete",$M19,$N19))) | V19: =IF($B19="","",IF($T19="Declined","CLOSED",IF($O19=0,"SETTLED",IF($P19="","BALANCE OPEN",IF($P19<TODAY(),"BALANCE OVERDUE",IF($P19-TODAY()<=7,"BALANCE DUE SOON","BALANCE OPEN")))))) | X19: =IF($B19="",0,IF(COUNTIF('VENDORS + APPOINTMENTS'!$B$6:$B$65,$B19)>1,1,0)) | Y19: =IF(OR(N($M19)>0,N($Q19)>0),IF($L19="",1,IF(COUNTIF('MASTER BUDGET'!$D$6:$D$25,$L19)=0,1,0)),0) | Z19: =IF($I19="",0,IF(COUNTIF('CHRISTMAS CALENDAR'!$B$6:$B$205,$I19)=0,1,0))
O20: =IF($B20="","",MAX(0,$M20-$N20)) | Q20: =IF($B20="","",IF($T20="Paid in full",$M20,IF($T20="Complete",$M20,$N20))) | V20: =IF($B20="","",IF($T20="Declined","CLOSED",IF($O20=0,"SETTLED",IF($P20="","BALANCE OPEN",IF($P20<TODAY(),"BALANCE OVERDUE",IF($P20-TODAY()<=7,"BALANCE DUE SOON","BALANCE OPEN")))))) | X20: =IF($B20="",0,IF(COUNTIF('VENDORS + APPOINTMENTS'!$B$6:$B$65,$B20)>1,1,0)) | Y20: =IF(OR(N($M20)>0,N($Q20)>0),IF($L20="",1,IF(COUNTIF('MASTER BUDGET'!$D$6:$D$25,$L20)=0,1,0)),0) | Z20: =IF($I20="",0,IF(COUNTIF('CHRISTMAS CALENDAR'!$B$6:$B$205,$I20)=0,1,0))
... O65: =IF($B65="","",MAX(0,$M65-$N65)) | Q65: =IF($B65="","",IF($T65="Paid in full",$M65,IF($T65="Complete",$M65,$N65))) | V65: =IF($B65="","",IF($T65="Declined","CLOSED",IF($O65=0,"SETTLED",IF($P65="","BALANCE OPEN",IF($P65<TODAY(),"BALANCE OVERDUE",IF($P65-TODAY()<=7,"BALANCE DUE SOON","BALANCE OPEN")))))) | X65: =IF($B65="",0,IF(COUNTIF('VENDORS + APPOINTMENTS'!$B$6:$B$65,$B65)>1,1,0)) | Y65: =IF(OR(N($M65)>0,N($Q65)>0),IF($L65="",1,IF(COUNTIF('MASTER BUDGET'!$D$6:$D$25,$L65)=0,1,0)),0) | Z65: =IF($I65="",0,IF(COUNTIF('CHRISTMAS CALENDAR'!$B$6:$B$205,$I65)=0,1,0))

Sheet DECOR INVENTORY
B1: Dashboard | D1: Start here | E1: Calendar | F1: Budget | G1: All sheets
B2: DECOR INVENTORY
B3: What you already own, where it lives, and what genuinely needs replacing.
B4: Cream cells are yours to fill in · pale green cells calculate themselves · amber rows are examples you can delete
B5: Décor ID | C5: Item | D5: Category | E5: Style / colour | F5: Qty | G5: Condition | H5: Room | I5: Storage bin | J5: Bought | K5: Heirloom? | L5: Replace? | M5: Replacement status | N5: Replacement cost | O5: Budget category | P5: Counted planned | Q5: Actual cost | R5: Stock | S5: Photo or link | T5: Notes | U5: QA · duplicate ID | V5: QA · budget mapping
B6: X-001 | C6: Mercury glass candlesticks, pair | D6: Candles | E6: Antiqued silver | F6: 2 | G6: Good | H6: Dining room | I6: Bin 3, attic | J6: 2019 | K6: No | L6: No | M6: Not needed | O6: Decorations | P6: =IF($B6="","",IF($M6="Approved",$N6,0)) | R6: =IF($B6="","",IF($F6="","NO COUNT",IF($F6<=Set_LowStock,"LOW","IN STOCK"))) | T6: EXAMPLE — DELETE ME | U6: =IF($B6="",0,IF(COUNTIF('DECOR INVENTORY'!$B$6:$B$105,$B6)>1,1,0)) | V6: =IF(OR(N($P6)>0,N($Q6)>0),IF($O6="",1,IF(COUNTIF('MASTER BUDGET'!$D$6:$D$25,$O6)=0,1,0)),0)
B7: X-002 | C7: Grandmother's glass baubles | D7: Ornaments | E7: Hand-painted, faded gilt | F7: 14 | G7: Worn | H7: Living room | I7: Padded case, cellar | J7: 1962 | K7: Yes | L7: No | M7: Not needed | O7: Decorations | P7: =IF($B7="","",IF($M7="Approved",$N7,0)) | R7: =IF($B7="","",IF($F7="","NO COUNT",IF($F7<=Set_LowStock,"LOW","IN STOCK"))) | T7: EXAMPLE — DELETE ME | U7: =IF($B7="",0,IF(COUNTIF('DECOR INVENTORY'!$B$6:$B$105,$B7)>1,1,0)) | V7: =IF(OR(N($P7)>0,N($Q7)>0),IF($O7="",1,IF(COUNTIF('MASTER BUDGET'!$D$6:$D$25,$O7)=0,1,0)),0)
B8: X-003 | C8: Outdoor door garland | D8: Wreaths & garland | E8: Noble fir, dried orange | F8: 1 | G8: Retire | H8: Entry | I8: Composted each year | J8: 2025 | K8: No | L8: Yes | M8: Approved | N8: 180 | O8: Decorations | P8: =IF($B8="","",IF($M8="Approved",$N8,0)) | Q8: 180 | R8: =IF($B8="","",IF($F8="","NO COUNT",IF($F8<=Set_LowStock,"LOW","IN STOCK"))) | T8: EXAMPLE — DELETE ME · bought, and the cost lands once | U8: =IF($B8="",0,IF(COUNTIF('DECOR INVENTORY'!$B$6:$B$105,$B8)>1,1,0)) | V8: =IF(OR(N($P8)>0,N($Q8)>0),IF($O8="",1,IF(COUNTIF('MASTER BUDGET'!$D$6:$D$25,$O8)=0,1,0)),0)
P9: =IF($B9="","",IF($M9="Approved",$N9,0)) | R9: =IF($B9="","",IF($F9="","NO COUNT",IF($F9<=Set_LowStock,"LOW","IN STOCK"))) | U9: =IF($B9="",0,IF(COUNTIF('DECOR INVENTORY'!$B$6:$B$105,$B9)>1,1,0)) | V9: =IF(OR(N($P9)>0,N($Q9)>0),IF($O9="",1,IF(COUNTIF('MASTER BUDGET'!$D$6:$D$25,$O9)=0,1,0)),0)
P10: =IF($B10="","",IF($M10="Approved",$N10,0)) | R10: =IF($B10="","",IF($F10="","NO COUNT",IF($F10<=Set_LowStock,"LOW","IN STOCK"))) | U10: =IF($B10="",0,IF(COUNTIF('DECOR INVENTORY'!$B$6:$B$105,$B10)>1,1,0)) | V10: =IF(OR(N($P10)>0,N($Q10)>0),IF($O10="",1,IF(COUNTIF('MASTER BUDGET'!$D$6:$D$25,$O10)=0,1,0)),0)
P11: =IF($B11="","",IF($M11="Approved",$N11,0)) | R11: =IF($B11="","",IF($F11="","NO COUNT",IF($F11<=Set_LowStock,"LOW","IN STOCK"))) | U11: =IF($B11="",0,IF(COUNTIF('DECOR INVENTORY'!$B$6:$B$105,$B11)>1,1,0)) | V11: =IF(OR(N($P11)>0,N($Q11)>0),IF($O11="",1,IF(COUNTIF('MASTER BUDGET'!$D$6:$D$25,$O11)=0,1,0)),0)
P12: =IF($B12="","",IF($M12="Approved",$N12,0)) | R12: =IF($B12="","",IF($F12="","NO COUNT",IF($F12<=Set_LowStock,"LOW","IN STOCK"))) | U12: =IF($B12="",0,IF(COUNTIF('DECOR INVENTORY'!$B$6:$B$105,$B12)>1,1,0)) | V12: =IF(OR(N($P12)>0,N($Q12)>0),IF($O12="",1,IF(COUNTIF('MASTER BUDGET'!$D$6:$D$25,$O12)=0,1,0)),0)
P13: =IF($B13="","",IF($M13="Approved",$N13,0)) | R13: =IF($B13="","",IF($F13="","NO COUNT",IF($F13<=Set_LowStock,"LOW","IN STOCK"))) | U13: =IF($B13="",0,IF(COUNTIF('DECOR INVENTORY'!$B$6:$B$105,$B13)>1,1,0)) | V13: =IF(OR(N($P13)>0,N($Q13)>0),IF($O13="",1,IF(COUNTIF('MASTER BUDGET'!$D$6:$D$25,$O13)=0,1,0)),0)
P14: =IF($B14="","",IF($M14="Approved",$N14,0)) | R14: =IF($B14="","",IF($F14="","NO COUNT",IF($F14<=Set_LowStock,"LOW","IN STOCK"))) | U14: =IF($B14="",0,IF(COUNTIF('DECOR INVENTORY'!$B$6:$B$105,$B14)>1,1,0)) | V14: =IF(OR(N($P14)>0,N($Q14)>0),IF($O14="",1,IF(COUNTIF('MASTER BUDGET'!$D$6:$D$25,$O14)=0,1,0)),0)
P15: =IF($B15="","",IF($M15="Approved",$N15,0)) | R15: =IF($B15="","",IF($F15="","NO COUNT",IF($F15<=Set_LowStock,"LOW","IN STOCK"))) | U15: =IF($B15="",0,IF(COUNTIF('DECOR INVENTORY'!$B$6:$B$105,$B15)>1,1,0)) | V15: =IF(OR(N($P15)>0,N($Q15)>0),IF($O15="",1,IF(COUNTIF('MASTER BUDGET'!$D$6:$D$25,$O15)=0,1,0)),0)
P16: =IF($B16="","",IF($M16="Approved",$N16,0)) | R16: =IF($B16="","",IF($F16="","NO COUNT",IF($F16<=Set_LowStock,"LOW","IN STOCK"))) | U16: =IF($B16="",0,IF(COUNTIF('DECOR INVENTORY'!$B$6:$B$105,$B16)>1,1,0)) | V16: =IF(OR(N($P16)>0,N($Q16)>0),IF($O16="",1,IF(COUNTIF('MASTER BUDGET'!$D$6:$D$25,$O16)=0,1,0)),0)
P17: =IF($B17="","",IF($M17="Approved",$N17,0)) | R17: =IF($B17="","",IF($F17="","NO COUNT",IF($F17<=Set_LowStock,"LOW","IN STOCK"))) | U17: =IF($B17="",0,IF(COUNTIF('DECOR INVENTORY'!$B$6:$B$105,$B17)>1,1,0)) | V17: =IF(OR(N($P17)>0,N($Q17)>0),IF($O17="",1,IF(COUNTIF('MASTER BUDGET'!$D$6:$D$25,$O17)=0,1,0)),0)
P18: =IF($B18="","",IF($M18="Approved",$N18,0)) | R18: =IF($B18="","",IF($F18="","NO COUNT",IF($F18<=Set_LowStock,"LOW","IN STOCK"))) | U18: =IF($B18="",0,IF(COUNTIF('DECOR INVENTORY'!$B$6:$B$105,$B18)>1,1,0)) | V18: =IF(OR(N($P18)>0,N($Q18)>0),IF($O18="",1,IF(COUNTIF('MASTER BUDGET'!$D$6:$D$25,$O18)=0,1,0)),0)
P19: =IF($B19="","",IF($M19="Approved",$N19,0)) | R19: =IF($B19="","",IF($F19="","NO COUNT",IF($F19<=Set_LowStock,"LOW","IN STOCK"))) | U19: =IF($B19="",0,IF(COUNTIF('DECOR INVENTORY'!$B$6:$B$105,$B19)>1,1,0)) | V19: =IF(OR(N($P19)>0,N($Q19)>0),IF($O19="",1,IF(COUNTIF('MASTER BUDGET'!$D$6:$D$25,$O19)=0,1,0)),0)
P20: =IF($B20="","",IF($M20="Approved",$N20,0)) | R20: =IF($B20="","",IF($F20="","NO COUNT",IF($F20<=Set_LowStock,"LOW","IN STOCK"))) | U20: =IF($B20="",0,IF(COUNTIF('DECOR INVENTORY'!$B$6:$B$105,$B20)>1,1,0)) | V20: =IF(OR(N($P20)>0,N($Q20)>0),IF($O20="",1,IF(COUNTIF('MASTER BUDGET'!$D$6:$D$25,$O20)=0,1,0)),0)
... P105: =IF($B105="","",IF($M105="Approved",$N105,0)) | R105: =IF($B105="","",IF($F105="","NO COUNT",IF($F105<=Set_LowStock,"LOW","IN STOCK"))) | U105: =IF($B105="",0,IF(COUNTIF('DECOR INVENTORY'!$B$6:$B$105,$B105)>1,1,0)) | V105: =IF(OR(N($P105)>0,N($Q105)>0),IF($O105="",1,IF(COUNTIF('MASTER BUDGET'!$D$6:$D$25,$O105)=0,1,0)),0)
B107: Only replacements marked Approved reach the budget. A wish list should not look like a commitment.

Sheet DECORATING PLAN
B1: Dashboard | D1: Start here | E1: Calendar | F1: Budget | G1: All sheets
B2: DECORATING PLAN
B3: Room by room: what it should feel like, what you have, and what is still missing.
B4: Cream cells are yours to fill in · pale green cells calculate themselves · amber rows are examples you can delete
B5: Plan ID | C5: Area | D5: Design intention | E5: Using from store | F5: Still needed | G5: Budget category | H5: Planned cost | I5: Actual cost | J5: Install | K5: Owner | L5: Done? | M5: Takedown | N5: Back into | O5: When | P5: Notes | Q5: QA · duplicate ID | R5: QA · budget mapping
B6: DP-001 | C6: Entry | D6: One tall garland, candlelight, nothing else | E6: X-003 | F6: New garland | G6: Decorations | H6: 0 | J6: 46357 | K6: Me | L6: No | M6: 46393 | N6: Composted | O6: =IF($B6="","",IF($L6="Yes","COMPLETE",IF($J6="","NO DATE",IF($J6<TODAY(),"OVERDUE",IF($J6-TODAY()<=7,"THIS WEEK","SCHEDULED"))))) | P6: EXAMPLE — DELETE ME · the garland is costed on DÉCOR INVENTORY, so it is not costed again here | Q6: =IF($B6="",0,IF(COUNTIF('DECORATING PLAN'!$B$6:$B$65,$B6)>1,1,0)) | R6: =IF(OR(N($H6)>0,N($I6)>0),IF($G6="",1,IF(COUNTIF('MASTER BUDGET'!$D$6:$D$25,$G6)=0,1,0)),0)
B7: DP-002 | C7: Dining room | D7: Evergreen and glass, low enough to talk across | E7: X-001 | G7: Decorations | H7: 90 | J7: 46376 | K7: Me | L7: No | M7: 46393 | N7: Bin 3, attic | O7: =IF($B7="","",IF($L7="Yes","COMPLETE",IF($J7="","NO DATE",IF($J7<TODAY(),"OVERDUE",IF($J7-TODAY()<=7,"THIS WEEK","SCHEDULED"))))) | P7: EXAMPLE — DELETE ME | Q7: =IF($B7="",0,IF(COUNTIF('DECORATING PLAN'!$B$6:$B$65,$B7)>1,1,0)) | R7: =IF(OR(N($H7)>0,N($I7)>0),IF($G7="",1,IF(COUNTIF('MASTER BUDGET'!$D$6:$D$25,$G7)=0,1,0)),0)
B8: DP-003 | C8: Living room | D8: The old baubles, and only the old baubles | E8: X-002 | G8: Decorations | H8: 0 | J8: 46362 | K8: James | L8: No | M8: 46393 | N8: Padded case, cellar | O8: =IF($B8="","",IF($L8="Yes","COMPLETE",IF($J8="","NO DATE",IF($J8<TODAY(),"OVERDUE",IF($J8-TODAY()<=7,"THIS WEEK","SCHEDULED"))))) | P8: EXAMPLE — DELETE ME | Q8: =IF($B8="",0,IF(COUNTIF('DECORATING PLAN'!$B$6:$B$65,$B8)>1,1,0)) | R8: =IF(OR(N($H8)>0,N($I8)>0),IF($G8="",1,IF(COUNTIF('MASTER BUDGET'!$D$6:$D$25,$G8)=0,1,0)),0)
O9: =IF($B9="","",IF($L9="Yes","COMPLETE",IF($J9="","NO DATE",IF($J9<TODAY(),"OVERDUE",IF($J9-TODAY()<=7,"THIS WEEK","SCHEDULED"))))) | Q9: =IF($B9="",0,IF(COUNTIF('DECORATING PLAN'!$B$6:$B$65,$B9)>1,1,0)) | R9: =IF(OR(N($H9)>0,N($I9)>0),IF($G9="",1,IF(COUNTIF('MASTER BUDGET'!$D$6:$D$25,$G9)=0,1,0)),0)
O10: =IF($B10="","",IF($L10="Yes","COMPLETE",IF($J10="","NO DATE",IF($J10<TODAY(),"OVERDUE",IF($J10-TODAY()<=7,"THIS WEEK","SCHEDULED"))))) | Q10: =IF($B10="",0,IF(COUNTIF('DECORATING PLAN'!$B$6:$B$65,$B10)>1,1,0)) | R10: =IF(OR(N($H10)>0,N($I10)>0),IF($G10="",1,IF(COUNTIF('MASTER BUDGET'!$D$6:$D$25,$G10)=0,1,0)),0)
O11: =IF($B11="","",IF($L11="Yes","COMPLETE",IF($J11="","NO DATE",IF($J11<TODAY(),"OVERDUE",IF($J11-TODAY()<=7,"THIS WEEK","SCHEDULED"))))) | Q11: =IF($B11="",0,IF(COUNTIF('DECORATING PLAN'!$B$6:$B$65,$B11)>1,1,0)) | R11: =IF(OR(N($H11)>0,N($I11)>0),IF($G11="",1,IF(COUNTIF('MASTER BUDGET'!$D$6:$D$25,$G11)=0,1,0)),0)
O12: =IF($B12="","",IF($L12="Yes","COMPLETE",IF($J12="","NO DATE",IF($J12<TODAY(),"OVERDUE",IF($J12-TODAY()<=7,"THIS WEEK","SCHEDULED"))))) | Q12: =IF($B12="",0,IF(COUNTIF('DECORATING PLAN'!$B$6:$B$65,$B12)>1,1,0)) | R12: =IF(OR(N($H12)>0,N($I12)>0),IF($G12="",1,IF(COUNTIF('MASTER BUDGET'!$D$6:$D$25,$G12)=0,1,0)),0)
O13: =IF($B13="","",IF($L13="Yes","COMPLETE",IF($J13="","NO DATE",IF($J13<TODAY(),"OVERDUE",IF($J13-TODAY()<=7,"THIS WEEK","SCHEDULED"))))) | Q13: =IF($B13="",0,IF(COUNTIF('DECORATING PLAN'!$B$6:$B$65,$B13)>1,1,0)) | R13: =IF(OR(N($H13)>0,N($I13)>0),IF($G13="",1,IF(COUNTIF('MASTER BUDGET'!$D$6:$D$25,$G13)=0,1,0)),0)
O14: =IF($B14="","",IF($L14="Yes","COMPLETE",IF($J14="","NO DATE",IF($J14<TODAY(),"OVERDUE",IF($J14-TODAY()<=7,"THIS WEEK","SCHEDULED"))))) | Q14: =IF($B14="",0,IF(COUNTIF('DECORATING PLAN'!$B$6:$B$65,$B14)>1,1,0)) | R14: =IF(OR(N($H14)>0,N($I14)>0),IF($G14="",1,IF(COUNTIF('MASTER BUDGET'!$D$6:$D$25,$G14)=0,1,0)),0)
O15: =IF($B15="","",IF($L15="Yes","COMPLETE",IF($J15="","NO DATE",IF($J15<TODAY(),"OVERDUE",IF($J15-TODAY()<=7,"THIS WEEK","SCHEDULED"))))) | Q15: =IF($B15="",0,IF(COUNTIF('DECORATING PLAN'!$B$6:$B$65,$B15)>1,1,0)) | R15: =IF(OR(N($H15)>0,N($I15)>0),IF($G15="",1,IF(COUNTIF('MASTER BUDGET'!$D$6:$D$25,$G15)=0,1,0)),0)
O16: =IF($B16="","",IF($L16="Yes","COMPLETE",IF($J16="","NO DATE",IF($J16<TODAY(),"OVERDUE",IF($J16-TODAY()<=7,"THIS WEEK","SCHEDULED"))))) | Q16: =IF($B16="",0,IF(COUNTIF('DECORATING PLAN'!$B$6:$B$65,$B16)>1,1,0)) | R16: =IF(OR(N($H16)>0,N($I16)>0),IF($G16="",1,IF(COUNTIF('MASTER BUDGET'!$D$6:$D$25,$G16)=0,1,0)),0)
O17: =IF($B17="","",IF($L17="Yes","COMPLETE",IF($J17="","NO DATE",IF($J17<TODAY(),"OVERDUE",IF($J17-TODAY()<=7,"THIS WEEK","SCHEDULED"))))) | Q17: =IF($B17="",0,IF(COUNTIF('DECORATING PLAN'!$B$6:$B$65,$B17)>1,1,0)) | R17: =IF(OR(N($H17)>0,N($I17)>0),IF($G17="",1,IF(COUNTIF('MASTER BUDGET'!$D$6:$D$25,$G17)=0,1,0)),0)
O18: =IF($B18="","",IF($L18="Yes","COMPLETE",IF($J18="","NO DATE",IF($J18<TODAY(),"OVERDUE",IF($J18-TODAY()<=7,"THIS WEEK","SCHEDULED"))))) | Q18: =IF($B18="",0,IF(COUNTIF('DECORATING PLAN'!$B$6:$B$65,$B18)>1,1,0)) | R18: =IF(OR(N($H18)>0,N($I18)>0),IF($G18="",1,IF(COUNTIF('MASTER BUDGET'!$D$6:$D$25,$G18)=0,1,0)),0)
O19: =IF($B19="","",IF($L19="Yes","COMPLETE",IF($J19="","NO DATE",IF($J19<TODAY(),"OVERDUE",IF($J19-TODAY()<=7,"THIS WEEK","SCHEDULED"))))) | Q19: =IF($B19="",0,IF(COUNTIF('DECORATING PLAN'!$B$6:$B$65,$B19)>1,1,0)) | R19: =IF(OR(N($H19)>0,N($I19)>0),IF($G19="",1,IF(COUNTIF('MASTER BUDGET'!$D$6:$D$25,$G19)=0,1,0)),0)
O20: =IF($B20="","",IF($L20="Yes","COMPLETE",IF($J20="","NO DATE",IF($J20<TODAY(),"OVERDUE",IF($J20-TODAY()<=7,"THIS WEEK","SCHEDULED"))))) | Q20: =IF($B20="",0,IF(COUNTIF('DECORATING PLAN'!$B$6:$B$65,$B20)>1,1,0)) | R20: =IF(OR(N($H20)>0,N($I20)>0),IF($G20="",1,IF(COUNTIF('MASTER BUDGET'!$D$6:$D$25,$G20)=0,1,0)),0)
... O65: =IF($B65="","",IF($L65="Yes","COMPLETE",IF($J65="","NO DATE",IF($J65<TODAY(),"OVERDUE",IF($J65-TODAY()<=7,"THIS WEEK","SCHEDULED"))))) | Q65: =IF($B65="",0,IF(COUNTIF('DECORATING PLAN'!$B$6:$B$65,$B65)>1,1,0)) | R65: =IF(OR(N($H65)>0,N($I65)>0),IF($G65="",1,IF(COUNTIF('MASTER BUDGET'!$D$6:$D$25,$G65)=0,1,0)),0)

Sheet TABLESCAPE + FLORALS
B1: Dashboard | D1: Start here | E1: Calendar | G1: Budget | H1: All sheets
B2: TABLESCAPE + FLORALS
B3: The table, laid out on paper first: linen, glass, flowers, candles and who sets it.
B4: Cream cells are yours to fill in · pale green cells calculate themselves · amber rows are examples you can delete
B5: Table ID | C5: Event ID | D5: Table or room | E5: Guests | F5: Direction | G5: Linen | H5: China | I5: Flatware | J5: Glassware | K5: Place cards | L5: Centrepiece / floral recipe | M5: Candles | N5: Rental source | O5: Owned or hired | P5: Qty | Q5: Budget category | R5: Planned cost | S5: Actual cost | T5: Set by | U5: Set at | V5: Ready? | W5: Notes | X5: QA · duplicate ID | Y5: QA · budget mapping | Z5: QA · Event ID exists
B6: T-001 | C6: K-002 | D6: Dining room, long table | E6: 12 | F6: Evergreen, ivory, one note of oxblood | G6: Damask, ivory | H6: The Wedgwood | I6: Grandmother's silver | J6: Cut crystal, six each | K6: Hand-written, ivory card | L6: Low bowls: noble fir, hellebore, dried orange | M6: Ivory tapers, twelve | O6: Owned | P6: 1 | Q6: Hosting | R6: 240 | T6: Me | U6: 16:00 | V6: No | W6: EXAMPLE — DELETE ME | X6: =IF($B6="",0,IF(COUNTIF('TABLESCAPE + FLORALS'!$B$6:$B$65,$B6)>1,1,0)) | Y6: =IF(OR(N($R6)>0,N($S6)>0),IF($Q6="",1,IF(COUNTIF('MASTER BUDGET'!$D$6:$D$25,$Q6)=0,1,0)),0) | Z6: =IF($C6="",0,IF(COUNTIF('CHRISTMAS CALENDAR'!$B$6:$B$205,$C6)=0,1,0))
B7: T-002 | D7: Kitchen, Christmas Eve supper | E7: 6 | F7: Quieter — linen, pewter, one candle | G7: Washed linen, flax | H7: Everyday creamware | O7: Owned | P7: 1 | Q7: Hosting | R7: 0 | T7: Me | V7: No | W7: EXAMPLE — DELETE ME | X7: =IF($B7="",0,IF(COUNTIF('TABLESCAPE + FLORALS'!$B$6:$B$65,$B7)>1,1,0)) | Y7: =IF(OR(N($R7)>0,N($S7)>0),IF($Q7="",1,IF(COUNTIF('MASTER BUDGET'!$D$6:$D$25,$Q7)=0,1,0)),0) | Z7: =IF($C7="",0,IF(COUNTIF('CHRISTMAS CALENDAR'!$B$6:$B$205,$C7)=0,1,0))
B8: T-003 | D8: Drinks, drawing room | E8: 20 | F8: Standing, so nothing that needs a fork | J8: Coupes, hired | N8: Fen & Field hire | O8: Rented | P8: 24 | Q8: Events | R8: 96 | T8: James | U8: 17:30 | V8: No | W8: EXAMPLE — DELETE ME | X8: =IF($B8="",0,IF(COUNTIF('TABLESCAPE + FLORALS'!$B$6:$B$65,$B8)>1,1,0)) | Y8: =IF(OR(N($R8)>0,N($S8)>0),IF($Q8="",1,IF(COUNTIF('MASTER BUDGET'!$D$6:$D$25,$Q8)=0,1,0)),0) | Z8: =IF($C8="",0,IF(COUNTIF('CHRISTMAS CALENDAR'!$B$6:$B$205,$C8)=0,1,0))
X9: =IF($B9="",0,IF(COUNTIF('TABLESCAPE + FLORALS'!$B$6:$B$65,$B9)>1,1,0)) | Y9: =IF(OR(N($R9)>0,N($S9)>0),IF($Q9="",1,IF(COUNTIF('MASTER BUDGET'!$D$6:$D$25,$Q9)=0,1,0)),0) | Z9: =IF($C9="",0,IF(COUNTIF('CHRISTMAS CALENDAR'!$B$6:$B$205,$C9)=0,1,0))
X10: =IF($B10="",0,IF(COUNTIF('TABLESCAPE + FLORALS'!$B$6:$B$65,$B10)>1,1,0)) | Y10: =IF(OR(N($R10)>0,N($S10)>0),IF($Q10="",1,IF(COUNTIF('MASTER BUDGET'!$D$6:$D$25,$Q10)=0,1,0)),0) | Z10: =IF($C10="",0,IF(COUNTIF('CHRISTMAS CALENDAR'!$B$6:$B$205,$C10)=0,1,0))
X11: =IF($B11="",0,IF(COUNTIF('TABLESCAPE + FLORALS'!$B$6:$B$65,$B11)>1,1,0)) | Y11: =IF(OR(N($R11)>0,N($S11)>0),IF($Q11="",1,IF(COUNTIF('MASTER BUDGET'!$D$6:$D$25,$Q11)=0,1,0)),0) | Z11: =IF($C11="",0,IF(COUNTIF('CHRISTMAS CALENDAR'!$B$6:$B$205,$C11)=0,1,0))
X12: =IF($B12="",0,IF(COUNTIF('TABLESCAPE + FLORALS'!$B$6:$B$65,$B12)>1,1,0)) | Y12: =IF(OR(N($R12)>0,N($S12)>0),IF($Q12="",1,IF(COUNTIF('MASTER BUDGET'!$D$6:$D$25,$Q12)=0,1,0)),0) | Z12: =IF($C12="",0,IF(COUNTIF('CHRISTMAS CALENDAR'!$B$6:$B$205,$C12)=0,1,0))
X13: =IF($B13="",0,IF(COUNTIF('TABLESCAPE + FLORALS'!$B$6:$B$65,$B13)>1,1,0)) | Y13: =IF(OR(N($R13)>0,N($S13)>0),IF($Q13="",1,IF(COUNTIF('MASTER BUDGET'!$D$6:$D$25,$Q13)=0,1,0)),0) | Z13: =IF($C13="",0,IF(COUNTIF('CHRISTMAS CALENDAR'!$B$6:$B$205,$C13)=0,1,0))
